Workbook
Name NativeTimeline_FECHA1: #N/A

Sheet TEMAS
B2: SECTOR | C2: RESP | D2: PRIORIDAD | E2: TEMA | F2: REVISÓN | G2: FECHA INICIO | H2: DÍAS TRANSCU | I2: FECHA OBJETIVO | J2: CANT. MODIF FECHA OBJETIVO | K2: DÍAS A FAVOR | L2: NIVEL DE AVANCE | M2: CERRADO
B3: CALIDAD | C3: RODRI | D3: 1 | E3: Exceso de sodio | F3: INDIVIDUAL | G3: 45992 | H3: =+IF(M3="SI","CERRADO",IF(G3="-","NO INICIADO",IF(I3="-","SIN FECHA OBJ.",IF(I3="--","EN PAUSA",TODAY()-G3)))) -> 115 | I3: 46081 | J3: 0 | K3: =IF(I3="DEFINIR","DEFINIR",IF(M3="SI","CERRADO",IF(I3="-","-",IF(I3="--","EN PAUSA",I3-TODAY())))) -> -26 | L3: 0.5 | M3: NO
B4: CALIDAD | C4: RODRI | D4: 1 | E4: BRCGS al día | F4: MESA | G4: 46023 | H4: =+IF(M4="SI","CERRADO",IF(G4="-","NO INICIADO",IF(I4="-","SIN FECHA OBJ.",IF(I4="--","EN PAUSA",TODAY()-G4)))) -> 84 | I4: 46202 | J4: 0 | K4: =IF(I4="DEFINIR","DEFINIR",IF(M4="SI","CERRADO",IF(I4="-","-",IF(I4="--","EN PAUSA",I4-TODAY())))) -> 95 | L4: 0.2 | M4: NO
B5: CALIDAD | C5: RODRI | D5: 2 | E5: Fórmulas comparativas: soja | F5: INDIVIDUAL | G5: 45962 | H5: =+IF(M5="SI","CERRADO",IF(G5="-","NO INICIADO",IF(I5="-","SIN FECHA OBJ.",IF(I5="--","EN PAUSA",TODAY()-G5)))) -> SIN FECHA OBJ. | I5: - | J5: 0 | K5: =IF(I5="DEFINIR","DEFINIR",IF(M5="SI","CERRADO",IF(I5="-","-",IF(I5="--","EN PAUSA",I5-TODAY())))) -> - | L5: 0.4 | M5: NO
B6: CALIDAD | C6: RODRI | D6: 2 | E6: Control de Calidad: Adit, Emb y Nuggets en app o excel | F6: INDIVIDUAL | G6: 46002 | H6: =+IF(M6="SI","CERRADO",IF(G6="-","NO INICIADO",IF(I6="-","SIN FECHA OBJ.",IF(I6="--","EN PAUSA",TODAY()-G6)))) -> SIN FECHA OBJ. | I6: - | J6: 0 | K6: =IF(I6="DEFINIR","DEFINIR",IF(M6="SI","CERRADO",IF(I6="-","-",IF(I6="--","EN PAUSA",I6-TODAY())))) -> - | L6: 0.5 | M6: NO
B7: CALIDAD | C7: RODRI | D7: 3 | E7: Pruebas grasa S en microondas | F7: INDIVIDUAL | G7: 46002 | H7: =+IF(M7="SI","CERRADO",IF(G7="-","NO INICIADO",IF(I7="-","SIN FECHA OBJ.",IF(I7="--","EN PAUSA",TODAY()-G7)))) -> SIN FECHA OBJ. | I7: - | J7: 0 | K7: =IF(I7="DEFINIR","DEFINIR",IF(M7="SI","CERRADO",IF(I7="-","-",IF(I7="--","EN PAUSA",I7-TODAY())))) -> - | L7: 0.2 | M7: NO
B8: CALIDAD | C8: RODRI | D8: - | E8: Cambio de foodscan | F8: INDIVIDUAL | G8: 45962 | H8: =+IF(M8="SI","CERRADO",IF(G8="-","NO INICIADO",IF(I8="-","SIN FECHA OBJ.",IF(I8="--","EN PAUSA",TODAY()-G8)))) -> CERRADO | I8: 46041 | J8: 1 | K8: =IF(I8="DEFINIR","DEFINIR",IF(M8="SI","CERRADO",IF(I8="-","-",IF(I8="--","EN PAUSA",I8-TODAY())))) -> CERRADO | L8: 0.9 | M8: SI
B9: CALIDAD | C9: RODRI | D9: - | E9: Etiquetas aprobadas vs fechador | F9: INDIVIDUAL | G9: 46002 | H9: =+IF(M9="SI","CERRADO",IF(G9="-","NO INICIADO",IF(I9="-","SIN FECHA OBJ.",IF(I9="--","EN PAUSA",TODAY()-G9)))) -> CERRADO | I9: 46037 | J9: 1 | K9: =IF(I9="DEFINIR","DEFINIR",IF(M9="SI","CERRADO",IF(I9="-","-",IF(I9="--","EN PAUSA",I9-TODAY())))) -> CERRADO | L9: 1 | M9: SI
B10: PRODUCCIÓN | C10: JULIO | D10: 1 | E10: Placa de 11 | F10: MESA | G10: 45976 | H10: =+IF(M10="SI","CERRADO",IF(G10="-","NO INICIADO",IF(I10="-","SIN FECHA OBJ.",IF(I10="--","EN PAUSA",TODAY()-G10)))) -> SIN FECHA OBJ. | I10: - | J10: 0 | K10: =IF(I10="DEFINIR","DEFINIR",IF(M10="SI","CERRADO",IF(I10="-","-",IF(I10="--","EN PAUSA",I10-TODAY())))) -> - | L10: 0.6 | M10: NO
B11: PRODUCCIÓN | C11: JULIO | D11: 1 | E11: Reducir batch de 700 | F11: MESA | G11: 46037 | H11: =+IF(M11="SI","CERRADO",IF(G11="-","NO INICIADO",IF(I11="-","SIN FECHA OBJ.",IF(I11="--","EN PAUSA",TODAY()-G11)))) -> SIN FECHA OBJ. | I11: - | J11: 0 | K11: =IF(I11="DEFINIR","DEFINIR",IF(M11="SI","CERRADO",IF(I11="-","-",IF(I11="--","EN PAUSA",I11-TODAY())))) -> - | L11: 0.5 | M11: NO
B12: PRODUCCIÓN | C12: JULIO | D12: 1 | E12: Reproceso con etiqueta | F12: MESA | G12: 46001 | H12: =+IF(M12="SI","CERRADO",IF(G12="-","NO INICIADO",IF(I12="-","SIN FECHA OBJ.",IF(I12="--","EN PAUSA",TODAY()-G12)))) -> SIN FECHA OBJ. | I12: - | J12: 0 | K12: =IF(I12="DEFINIR","DEFINIR",IF(M12="SI","CERRADO",IF(I12="-","-",IF(I12="--","EN PAUSA",I12-TODAY())))) -> - | L12: 0 | M12: NO
B13: PRODUCCIÓN | C13: JULIO | D13: 1 | E13: Merma recupero para venta | F13: INDIVIDUAL | G13: 46001 | H13: =+IF(M13="SI","CERRADO",IF(G13="-","NO INICIADO",IF(I13="-","SIN FECHA OBJ.",IF(I13="--","EN PAUSA",TODAY()-G13)))) -> SIN FECHA OBJ. | I13: - | J13: 0 | K13: =IF(I13="DEFINIR","DEFINIR",IF(M13="SI","CERRADO",IF(I13="-","-",IF(I13="--","EN PAUSA",I13-TODAY())))) -> - | L13: 0 | M13: NO
B14: PRODUCCIÓN | C14: JULIO | D14: 2 | E14: Nueva dotación de producción | F14: INDIVIDUAL | G14: 46054 | H14: =+IF(M14="SI","CERRADO",IF(G14="-","NO INICIADO",IF(I14="-","SIN FECHA OBJ.",IF(I14="--","EN PAUSA",TODAY()-G14)))) -> 53 | I14: 46142 | J14: 0 | K14: =IF(I14="DEFINIR","DEFINIR",IF(M14="SI","CERRADO",IF(I14="-","-",IF(I14="--","EN PAUSA",I14-TODAY())))) -> 35 | L14: 0.3 | M14: NO
B15: PRODUCCIÓN | C15: JULIO | D15: P | E15: Hamburguesas con mezcla de cerdo - (lograr el producto) | F15: INDIVIDUAL | G15: 45962 | H15: =+IF(M15="SI","CERRADO",IF(G15="-","NO INICIADO",IF(I15="-","SIN FECHA OBJ.",IF(I15="--","EN PAUSA",TODAY()-G15)))) -> EN PAUSA | I15: -- | J15: 0 | K15: =IF(I15="DEFINIR","DEFINIR",IF(M15="SI","CERRADO",IF(I15="-","-",IF(I15="--","EN PAUSA",I15-TODAY())))) -> EN PAUSA | L15: 0 | M15: NO
B16: PRODUCCIÓN | C16: JULIO | D16: P | E16: Chorizo cerdo (recorte + panceta) - (lograr el producto) | F16: INDIVIDUAL | G16: 45962 | H16: =+IF(M16="SI","CERRADO",IF(G16="-","NO INICIADO",IF(I16="-","SIN FECHA OBJ.",IF(I16="--","EN PAUSA",TODAY()-G16)))) -> EN PAUSA | I16: -- | J16: 0 | K16: =IF(I16="DEFINIR","DEFINIR",IF(M16="SI","CERRADO",IF(I16="-","-",IF(I16="--","EN PAUSA",I16-TODAY())))) -> EN PAUSA | L16: 0 | M16: NO
B17: PRODUCCIÓN | C17: JULIO | D17: - | E17: Hamburguesa 6mm - (lograr el producto) | F17: INDIVIDUAL | G17: 45931 | H17: =+IF(M17="SI","CERRADO",IF(G17="-","NO INICIADO",IF(I17="-","SIN FECHA OBJ.",IF(I17="--","EN PAUSA",TODAY()-G17)))) -> CERRADO | I17: - | J17: 0 | K17: =IF(I17="DEFINIR","DEFINIR",IF(M17="SI","CERRADO",IF(I17="-","-",IF(I17="--","EN PAUSA",I17-TODAY())))) -> CERRADO | L17: 0.5 | M17: SI
B18: PRODUCCIÓN | C18: JULIO | D18: - | E18: Selladora de pulpetas CPC - (lograr el producto) | F18: MESA | G18: 45962 | H18: =+IF(M18="SI","CERRADO",IF(G18="-","NO INICIADO",IF(I18="-","SIN FECHA OBJ.",IF(I18="--","EN PAUSA",TODAY()-G18)))) -> CERRADO | I18: - | J18: 0 | K18: =IF(I18="DEFINIR","DEFINIR",IF(M18="SI","CERRADO",IF(I18="-","-",IF(I18="--","EN PAUSA",I18-TODAY())))) -> CERRADO | L18: 1 | M18: SI
B19: ABASTECIMIENTO | C19: CARLOS | D19: 1 | E19: Implementar Quadmins | F19: INDIVIDUAL | G19: 45931 | H19: =+IF(M19="SI","CERRADO",IF(G19="-","NO INICIADO",IF(I19="-","SIN FECHA OBJ.",IF(I19="--","EN PAUSA",TODAY()-G19)))) -> 176 | I19: 46022 | J19: 0 | K19: =IF(I19="DEFINIR","DEFINIR",IF(M19="SI","CERRADO",IF(I19="-","-",IF(I19="--","EN PAUSA",I19-TODAY())))) -> -85 | L19: 0.7 | M19: NO
B20: ABASTECIMIENTO | C20: CARLOS | D20: 1 | E20: Orden HH con producción | F20: INDIVIDUAL | G20: 45931 | H20: =+IF(M20="SI","CERRADO",IF(G20="-","NO INICIADO",IF(I20="-","SIN FECHA OBJ.",IF(I20="--","EN PAUSA",TODAY()-G20)))) -> SIN FECHA OBJ. | I20: - | J20: 0 | K20: =IF(I20="DEFINIR","DEFINIR",IF(M20="SI","CERRADO",IF(I20="-","-",IF(I20="--","EN PAUSA",I20-TODAY())))) -> - | L20: 0 | M20: NO
B21: ABASTECIMIENTO | C21: CARLOS | D21: - | E21: Implementar Escobar/Ituzaingó | F21: MESA | G21: 45962 | H21: =+IF(M21="SI","CERRADO",IF(G21="-","NO INICIADO",IF(I21="-","SIN FECHA OBJ.",IF(I21="--","EN PAUSA",TODAY()-G21)))) -> CERRADO | I21: 46011 | J21: 0 | K21: =IF(I21="DEFINIR","DEFINIR",IF(M21="SI","CERRADO",IF(I21="-","-",IF(I21="--","EN PAUSA",I21-TODAY())))) -> CERRADO | L21: 1 | M21: SI
B22: ABASTECIMIENTO | C22: CARLOS | D22: - | E22: Rampa niveladora para descarga de semis pareja | F22: INDIVIDUAL | G22: 45962 | H22: =+IF(M22="SI","CERRADO",IF(G22="-","NO INICIADO",IF(I22="-","SIN FECHA OBJ.",IF(I22="--","EN PAUSA",TODAY()-G22)))) -> CERRADO | I22: 46022 | J22: 0 | K22: =IF(I22="DEFINIR","DEFINIR",IF(M22="SI","CERRADO",IF(I22="-","-",IF(I22="--","EN PAUSA",I22-TODAY())))) -> CERRADO | L22: 1 | M22: SI
B23: ABASTECIMIENTO | C23: CARLOS | D23: - | E23: Tabla carga equipos de carga | F23: INDIVIDUAL | G23: 45962 | H23: =+IF(M23="SI","CERRADO",IF(G23="-","NO INICIADO",IF(I23="-","SIN FECHA OBJ.",IF(I23="--","EN PAUSA",TODAY()-G23)))) -> CERRADO | I23: 46011 | J23: 0 | K23: =IF(I23="DEFINIR","DEFINIR",IF(M23="SI","CERRADO",IF(I23="-","-",IF(I23="--","EN PAUSA",I23-TODAY())))) -> CERRADO | L23: 1 | M23: SI
B24: HIGIENE | C24: DAVID | D24: 1 | E24: Lavado de cintas automático | F24: INDIVIDUAL | G24: 45931 | H24: =+IF(M24="SI","CERRADO",IF(G24="-","NO INICIADO",IF(I24="-","SIN FECHA OBJ.",IF(I24="--","EN PAUSA",TODAY()-G24)))) -> 176 | I24: 46081 | J24: 1 | K24: =IF(I24="DEFINIR","DEFINIR",IF(M24="SI","CERRADO",IF(I24="-","-",IF(I24="--","EN PAUSA",I24-TODAY())))) -> -26 | L24: 0.2 | M24: NO
B25: HIGIENE | C25: DAVID | D25: 2 | E25: Vestuaristas + cerrado de vestuario menos en almuerzo | F25: MESA | G25: 45962 | H25: =+IF(M25="SI","CERRADO",IF(G25="-","NO INICIADO",IF(I25="-","SIN FECHA OBJ.",IF(I25="--","EN PAUSA",TODAY()-G25)))) -> 145 | I25: 46052 | J25: 1 | K25: =IF(I25="DEFINIR","DEFINIR",IF(M25="SI","CERRADO",IF(I25="-","-",IF(I25="--","EN PAUSA",I25-TODAY())))) -> -55 | L25: 0.9 | M25: NO
B26: HIGIENE | C26: DAVID | D26: 3 | E26: Lavarropas - nuevo | F26: INDIVIDUAL | G26: 46052 | H26: =+IF(M26="SI","CERRADO",IF(G26="-","NO INICIADO",IF(I26="-","SIN FECHA OBJ.",IF(I26="--","EN PAUSA",TODAY()-G26)))) -> SIN FECHA OBJ. | I26: - | J26: 0 | K26: =IF(I26="DEFINIR","DEFINIR",IF(M26="SI","CERRADO",IF(I26="-","-",IF(I26="--","EN PAUSA",I26-TODAY())))) -> - | L26: 0.2 | M26: NO
B27: HIGIENE | C27: DAVID | D27: 3 | E27: Frecuencias de limpieza | F27: INDIVIDUAL | G27: 46077 | H27: =+IF(M27="SI","CERRADO",IF(G27="-","NO INICIADO",IF(I27="-","SIN FECHA OBJ.",IF(I27="--","EN PAUSA",TODAY()-G27)))) -> SIN FECHA OBJ. | I27: - | J27: 0 | K27: =IF(I27="DEFINIR","DEFINIR",IF(M27="SI","CERRADO",IF(I27="-","-",IF(I27="--","EN PAUSA",I27-TODAY())))) -> - | L27: 0 | M27: NO
B28: HIGIENE | C28: DAVID | D28: 3 | E28: Secamanos (5), guillotinas (4) y autocortes (5) | F28: INDIVIDUAL | G28: 45962 | H28: =+IF(M28="SI","CERRADO",IF(G28="-","NO INICIADO",IF(I28="-","SIN FECHA OBJ.",IF(I28="--","EN PAUSA",TODAY()-G28)))) -> 145 | I28: 46053 | J28: 0 | K28: =IF(I28="DEFINIR","DEFINIR",IF(M28="SI","CERRADO",IF(I28="-","-",IF(I28="--","EN PAUSA",I28-TODAY())))) -> -54 | L28: 0.99 | M28: NO
B29: HIGIENE | C29: DAVID | D29: - | E29: Lavado con agua caliente (contenedor y disificación) | F29: INDIVIDUAL | G29: 45931 | H29: =+IF(M29="SI","CERRADO",IF(G29="-","NO INICIADO",IF(I29="-","SIN FECHA OBJ.",IF(I29="--","EN PAUSA",TODAY()-G29)))) -> CERRADO | I29: 45976 | J29: 0 | K29: =IF(I29="DEFINIR","DEFINIR",IF(M29="SI","CERRADO",IF(I29="-","-",IF(I29="--","EN PAUSA",I29-TODAY())))) -> CERRADO | L29: 1 | M29: SI
B30: HIGIENE | C30: DAVID | D30: - | E30: Máquina a vapor | F30: MESA | G30: 45931 | H30: =+IF(M30="SI","CERRADO",IF(G30="-","NO INICIADO",IF(I30="-","SIN FECHA OBJ.",IF(I30="--","EN PAUSA",TODAY()-G30)))) -> CERRADO | I30: 45992 | J30: 0 | K30: =IF(I30="DEFINIR","DEFINIR",IF(M30="SI","CERRADO",IF(I30="-","-",IF(I30="--","EN PAUSA",I30-TODAY())))) -> CERRADO | L30: 1 | M30: SI
B31: HIGIENE | C31: DAVID | D31: - | E31: Limpiezas diarias comedor | F31: MESA | G31: 45981 | H31: =+IF(M31="SI","CERRADO",IF(G31="-","NO INICIADO",IF(I31="-","SIN FECHA OBJ.",IF(I31="--","EN PAUSA",TODAY()-G31)))) -> CERRADO | I31: 45991 | J31: 0 | K31: =IF(I31="DEFINIR","DEFINIR",IF(M31="SI","CERRADO",IF(I31="-","-",IF(I31="--","EN PAUSA",I31-TODAY())))) -> CERRADO | L31: 1 | M31: SI
B32: MANTENIMIENTO | C32: FACU | D32: 1 | E32: Trafo: análisis, informe y acciones a tomar (Electrotech) | F32: INDIVIDUAL | G32: 45931 | H32: =+IF(M32="SI","CERRADO",IF(G32="-","NO INICIADO",IF(I32="-","SIN FECHA OBJ.",IF(I32="--","EN PAUSA",TODAY()-G32)))) -> 176 | I32: 46081 | J32: 1 | K32: =IF(I32="DEFINIR","DEFINIR",IF(M32="SI","CERRADO",IF(I32="-","-",IF(I32="--","EN PAUSA",I32-TODAY())))) -> -26 | L32: 0.7 | M32: NO
B33: MANTENIMIENTO | C33: FACU | D33: 1 | E33: Torre de enfriamiento | F33: INDIVIDUAL | G33: 45931 | H33: =+IF(M33="SI","CERRADO",IF(G33="-","NO INICIADO",IF(I33="-","SIN FECHA OBJ.",IF(I33="--","EN PAUSA",TODAY()-G33)))) -> 176 | I33: 46118 | J33: 1 | K33: =IF(I33="DEFINIR","DEFINIR",IF(M33="SI","CERRADO",IF(I33="-","-",IF(I33="--","EN PAUSA",I33-TODAY())))) -> 11 | L33: 0.98 | M33: NO
B34: MANTENIMIENTO | C34: FACU | D34: 1 | E34: Preventivo GYRO | F34: INDIVIDUAL | G34: 45931 | H34: =+IF(M34="SI","CERRADO",IF(G34="-","NO INICIADO",IF(I34="-","SIN FECHA OBJ.",IF(I34="--","EN PAUSA",TODAY()-G34)))) -> 176 | I34: 46111 | J34: 0 | K34: =IF(I34="DEFINIR","DEFINIR",IF(M34="SI","CERRADO",IF(I34="-","-",IF(I34="--","EN PAUSA",I34-TODAY())))) -> 4 | L34: 0.5 | M34: NO
B35: MANTENIMIENTO | C35: FACU | D35: 1 | E35: Preventivo Formax | F35: INDIVIDUAL | G35: 46002 | H35: =+IF(M35="SI","CERRADO",IF(G35="-","NO INICIADO",IF(I35="-","SIN FECHA OBJ.",IF(I35="--","EN PAUSA",TODAY()-G35)))) -> 105 | I35: 46111 | J35: 0 | K35: =IF(I35="DEFINIR","DEFINIR",IF(M35="SI","CERRADO",IF(I35="-","-",IF(I35="--","EN PAUSA",I35-TODAY())))) -> 4 | L35: 0.2 | M35: NO
B36: MANTENIMIENTO | C36: FACU | D36: 1 | E36: Arreglo piso 1.2 y 1.3 | F36: INDIVIDUAL | G36: 46106 | H36: =+IF(M36="SI","CERRADO",IF(G36="-","NO INICIADO",IF(I36="-","SIN FECHA OBJ.",IF(I36="--","EN PAUSA",TODAY()-G36)))) -> SIN FECHA OBJ. | I36: - | J36: 0 | K36: =IF(I36="DEFINIR","DEFINIR",IF(M36="SI","CERRADO",IF(I36="-","-",IF(I36="--","EN PAUSA",I36-TODAY())))) -> - | L36: 0 | M36: NO
B37: MANTENIMIENTO | C37: FACU | D37: 2 | E37: Pulmón | F37: MESA | G37: 46054 | H37: =+IF(M37="SI","CERRADO",IF(G37="-","NO INICIADO",IF(I37="-","SIN FECHA OBJ.",IF(I37="--","EN PAUSA",TODAY()-G37)))) -> SIN FECHA OBJ. | I37: - | J37: 0 | K37: =IF(I37="DEFINIR","DEFINIR",IF(M37="SI","CERRADO",IF(I37="-","-",IF(I37="--","EN PAUSA",I37-TODAY())))) -> - | L37: 0 | M37: NO
B38: MANTENIMIENTO | C38: FACU | D38: 2 | E38: Bomba de lavado | F38: INDIVIDUAL | G38: 45931 | H38: =+IF(M38="SI","CERRADO",IF(G38="-","NO INICIADO",IF(I38="-","SIN FECHA OBJ.",IF(I38="--","EN PAUSA",TODAY()-G38)))) -> 176 | I38: 46081 | J38: 1 | K38: =IF(I38="DEFINIR","DEFINIR",IF(M38="SI","CERRADO",IF(I38="-","-",IF(I38="--","EN PAUSA",I38-TODAY())))) -> -26 | L38: 0.8 | M38: NO
B39: MANTENIMIENTO | C39: FACU | D39: 2 | E39: Goteras: dep. cajas, estuchado, palletizado | F39: INDIVIDUAL | G39: 45962 | H39: =+IF(M39="SI","CERRADO",IF(G39="-","NO INICIADO",IF(I39="-","SIN FECHA OBJ.",IF(I39="--","EN PAUSA",TODAY()-G39)))) -> 145 | I39: 46081 | J39: 0 | K39: =IF(I39="DEFINIR","DEFINIR",IF(M39="SI","CERRADO",IF(I39="-","-",IF(I39="--","EN PAUSA",I39-TODAY())))) -> -26 | L39: 0.5 | M39: NO
B40: MANTENIMIENTO | C40: FACU | D40: 2 | E40: Evaporadores 03 y producción | F40: INDIVIDUAL | G40: 46058 | H40: =+IF(M40="SI","CERRADO",IF(G40="-","NO INICIADO",IF(I40="-","SIN FECHA OBJ.",IF(I40="--","EN PAUSA",TODAY()-G40)))) -> SIN FECHA OBJ. | I40: - | J40: 0 | K40: =IF(I40="DEFINIR","DEFINIR",IF(M40="SI","CERRADO",IF(I40="-","-",IF(I40="--","EN PAUSA",I40-TODAY())))) -> - | L40: 0.7 | M40: NO
B41: MANTENIMIENTO | C41: FACU | D41: 2 | E41: Tomra | F41: MESA | G41: 45962 | H41: =+IF(M41="SI","CERRADO",IF(G41="-","NO INICIADO",IF(I41="-","SIN FECHA OBJ.",IF(I41="--","EN PAUSA",TODAY()-G41)))) -> 145 | I41: 46081 | J41: 0 | K41: =IF(I41="DEFINIR","DEFINIR",IF(M41="SI","CERRADO",IF(I41="-","-",IF(I41="--","EN PAUSA",I41-TODAY())))) -> -26 | L41: 0.2 | M41: NO
B42: MANTENIMIENTO | C42: FACU | D42: 2 | E42: Impermeabilizar la terraza del lado del comedor | F42: INDIVIDUAL | G42: 46106 | H42: =+IF(M42="SI","CERRADO",IF(G42="-","NO INICIADO",IF(I42="-","SIN FECHA OBJ.",IF(I42="--","EN PAUSA",TODAY()-G42)))) -> SIN FECHA OBJ. | I42: - | J42: 0 | K42: =IF(I42="DEFINIR","DEFINIR",IF(M42="SI","CERRADO",IF(I42="-","-",IF(I42="--","EN PAUSA",I42-TODAY())))) -> - | L42: 0 | M42: NO
B43: MANTENIMIENTO | C43: FACU | D43: 3 | E43: Pintura de tanque | F43: INDIVIDUAL | G43: 46009 | H43: =+IF(M43="SI","CERRADO",IF(G43="-","NO INICIADO",IF(I43="-","SIN FECHA OBJ.",IF(I43="--","EN PAUSA",TODAY()-G43)))) -> 98 | I43: 46111 | J43: 0 | K43: =IF(I43="DEFINIR","DEFINIR",IF(M43="SI","CERRADO",IF(I43="-","-",IF(I43="--","EN PAUSA",I43-TODAY())))) -> 4 | L43: 0 | M43: NO
B44: MANTENIMIENTO | C44: FACU | D44: H | E44: Efluentes | F44: INDIVIDUAL | G44: 45962 | H44: =+IF(M44="SI","CERRADO",IF(G44="-","NO INICIADO",IF(I44="-","SIN FECHA OBJ.",IF(I44="--","EN PAUSA",TODAY()-G44)))) -> SIN FECHA OBJ. | I44: - | J44: 0 | K44: =IF(I44="DEFINIR","DEFINIR",IF(M44="SI","CERRADO",IF(I44="-","-",IF(I44="--","EN PAUSA",I44-TODAY())))) -> - | L44: 0.9 | M44: NO
B45: MANTENIMIENTO | C45: FACU | D45: H | E45: Sabroes | F45: INDIVIDUAL | G45: 45992 | H45: =+IF(M45="SI","CERRADO",IF(G45="-","NO INICIADO",IF(I45="-","SIN FECHA OBJ.",IF(I45="--","EN PAUSA",TODAY()-G45)))) -> SIN FECHA OBJ. | I45: - | J45: 0 | K45: =IF(I45="DEFINIR","DEFINIR",IF(M45="SI","CERRADO",IF(I45="-","-",IF(I45="--","EN PAUSA",I45-TODAY())))) -> - | L45: 0.99 | M45: NO
B46: MANTENIMIENTO | C46: FACU | D46: H | E46: Implementar Protecnus | F46: INDIVIDUAL | G46: 45931 | H46: =+IF(M46="SI","CERRADO",IF(G46="-","NO INICIADO",IF(I46="-","SIN FECHA OBJ.",IF(I46="--","EN PAUSA",TODAY()-G46)))) -> SIN FECHA OBJ. | I46: - | J46: 0 | K46: =IF(I46="DEFINIR","DEFINIR",IF(M46="SI","CERRADO",IF(I46="-","-",IF(I46="--","EN PAUSA",I46-TODAY())))) -> - | L46: 0.99 | M46: NO | N46: Recordar certificados aceites
B47: MANTENIMIENTO | C47: FACU | D47: H | E47: Stock motores | F47: INDIVIDUAL | G47: 45992 | H47: =+IF(M47="SI","CERRADO",IF(G47="-","NO INICIADO",IF(I47="-","SIN FECHA OBJ.",IF(I47="--","EN PAUSA",TODAY()-G47)))) -> SIN FECHA OBJ. | I47: - | J47: 0 | K47: =IF(I47="DEFINIR","DEFINIR",IF(M47="SI","CERRADO",IF(I47="-","-",IF(I47="--","EN PAUSA",I47-TODAY())))) -> - | L47: 0 | M47: NO
B48: MANTENIMIENTO | C48: FACU | D48: H | E48: Stock grandes repuestos | F48: INDIVIDUAL | G48: 45992 | H48: =+IF(M48="SI","CERRADO",IF(G48="-","NO INICIADO",IF(I48="-","SIN FECHA OBJ.",IF(I48="--","EN PAUSA",TODAY()-G48)))) -> SIN FECHA OBJ. | I48: - | J48: 0 | K48: =IF(I48="DEFINIR","DEFINIR",IF(M48="SI","CERRADO",IF(I48="-","-",IF(I48="--","EN PAUSA",I48-TODAY())))) -> - | L48: 0 | M48: NO
B49: MANTENIMIENTO | C49: FACU | D49: P | E49: Cinta estuchadora 2 | F49: MESA | G49: 45962 | H49: =+IF(M49="SI","CERRADO",IF(G49="-","NO INICIADO",IF(I49="-","SIN FECHA OBJ.",IF(I49="--","EN PAUSA",TODAY()-G49)))) -> EN PAUSA | I49: -- | J49: 0 | K49: =IF(I49="DEFINIR","DEFINIR",IF(M49="SI","CERRADO",IF(I49="-","-",IF(I49="--","EN PAUSA",I49-TODAY())))) -> EN PAUSA | L49: 0.3 | M49: NO
B50: MANTENIMIENTO | C50: FACU | D50: P | E50: Techo depósito varios | F50: INDIVIDUAL | G50: 46002 | H50: =+IF(M50="SI","CERRADO",IF(G50="-","NO INICIADO",IF(I50="-","SIN FECHA OBJ.",IF(I50="--","EN PAUSA",TODAY()-G50)))) -> EN PAUSA | I50: -- | J50: 0 | K50: =IF(I50="DEFINIR","DEFINIR",IF(M50="SI","CERRADO",IF(I50="-","-",IF(I50="--","EN PAUSA",I50-TODAY())))) -> EN PAUSA | L50: 0 | M50: NO
B51: MANTENIMIENTO | C51: FACU | D51: - | E51: Mezcladora congelada: temporizador de motor | F51: INDIVIDUAL | G51: 46054 | H51: =+IF(M51="SI","CERRADO",IF(G51="-","NO INICIADO",IF(I51="-","SIN FECHA OBJ.",IF(I51="--","EN PAUSA",TODAY()-G51)))) -> CERRADO | I51: 46082 | J51: 0 | K51: =IF(I51="DEFINIR","DEFINIR",IF(M51="SI","CERRADO",IF(I51="-","-",IF(I51="--","EN PAUSA",I51-TODAY())))) -> CERRADO | L51: 1 | M51: SI
B52: MANTENIMIENTO | C52: FACU | D52: - | E52: Pintura de piso: de calle o acrílica | F52: INDIVIDUAL | G52: 45976 | H52: =+IF(M52="SI","CERRADO",IF(G52="-","NO INICIADO",IF(I52="-","SIN FECHA OBJ.",IF(I52="--","EN PAUSA",TODAY()-G52)))) -> CERRADO | I52: 46081 | J52: 1 | K52: =IF(I52="DEFINIR","DEFINIR",IF(M52="SI","CERRADO",IF(I52="-","-",IF(I52="--","EN PAUSA",I52-TODAY())))) -> CERRADO | L52: 1 | M52: SI
B53: MANTENIMIENTO | C53: FACU | D53: - | E53: Máquina film pallets | F53: MESA | G53: 45992 | H53: =+IF(M53="SI","CERRADO",IF(G53="-","NO INICIADO",IF(I53="-","SIN FECHA OBJ.",IF(I53="--","EN PAUSA",TODAY()-G53)))) -> CERRADO | I53: 46053 | J53: 0 | K53: =IF(I53="DEFINIR","DEFINIR",IF(M53="SI","CERRADO",IF(I53="-","-",IF(I53="--","EN PAUSA",I53-TODAY())))) -> CERRADO | L53: 1 | M53: SI
B54: MANTENIMIENTO | C54: FACU | D54: - | E54: Empuje de prensa: pistón o malacate | F54: MESA | G54: 45962 | H54: =+IF(M54="SI","CERRADO",IF(G54="-","NO INICIADO",IF(I54="-","SIN FECHA OBJ.",IF(I54="--","EN PAUSA",TODAY()-G54)))) -> CERRADO | I54: 46053 | J54: 0 | K54: =IF(I54="DEFINIR","DEFINIR",IF(M54="SI","CERRADO",IF(I54="-","-",IF(I54="--","EN PAUSA",I54-TODAY())))) -> CERRADO | L54: 1 | M54: SI
B55: MANTENIMIENTO | C55: FACU | D55: - | E55: Texturizado de soja (sincro de mezclado + dos salidas de agua) - (Otto) | F55: INDIVIDUAL | G55: 45992 | H55: =+IF(M55="SI","CERRADO",IF(G55="-","NO INICIADO",IF(I55="-","SIN FECHA OBJ.",IF(I55="--","EN PAUSA",TODAY()-G55)))) -> CERRADO | I55: 46022 | J55: 0 | K55: =IF(I55="DEFINIR","DEFINIR",IF(M55="SI","CERRADO",IF(I55="-","-",IF(I55="--","EN PAUSA",I55-TODAY())))) -> CERRADO | L55: 1 | M55: SI
B56: PRODUCCIÓN | C56: MIGUE | D56: 1 | E56: Línea 2 producción | F56: MESA | G56: 45931 | H56: =+IF(M56="SI","CERRADO",IF(G56="-","NO INICIADO",IF(I56="-","SIN FECHA OBJ.",IF(I56="--","EN PAUSA",TODAY()-G56)))) -> SIN FECHA OBJ. | I56: - | J56: 0 | K56: =IF(I56="DEFINIR","DEFINIR",IF(M56="SI","CERRADO",IF(I56="-","-",IF(I56="--","EN PAUSA",I56-TODAY())))) -> - | L56: 0.6 | M56: NO
B57: PRODUCCIÓN | C57: MIGUE | D57: 1 | E57: Racionalización de productos | F57: MESA | G57: 45931 | H57: =+IF(M57="SI","CERRADO",IF(G57="-","NO INICIADO",IF(I57="-","SIN FECHA OBJ.",IF(I57="--","EN PAUSA",TODAY()-G57)))) -> SIN FECHA OBJ. | I57: - | J57: 0 | K57: =IF(I57="DEFINIR","DEFINIR",IF(M57="SI","CERRADO",IF(I57="-","-",IF(I57="--","EN PAUSA",I57-TODAY())))) -> - | L57: 0.6 | M57: NO
B58: EMBALAJE | C58: MIGUE | D58: 1 | E58: Circuito embalaje: pedidos a Tigre y recepción Perón | F58: INDIVIDUAL | G58: 46054 | H58: =+IF(M58="SI","CERRADO",IF(G58="-","NO INICIADO",IF(I58="-","SIN FECHA OBJ.",IF(I58="--","EN PAUSA",TODAY()-G58)))) -> SIN FECHA OBJ. | I58: - | J58: 0 | K58: =IF(I58="DEFINIR","DEFINIR",IF(M58="SI","CERRADO",IF(I58="-","-",IF(I58="--","EN PAUSA",I58-TODAY())))) -> - | L58: N/A | M58: N/A
B59: PRODUCCIÓN | C59: MIGUE | D59: 1 | E59: Uso de tablet en producción con aplicación en cálculo eficiencia | F59: INDIVIDUAL | G59: 46054 | H59: =+IF(M59="SI","CERRADO",IF(G59="-","NO INICIADO",IF(I59="-","SIN FECHA OBJ.",IF(I59="--","EN PAUSA",TODAY()-G59)))) -> SIN FECHA OBJ. | I59: - | J59: 0 | K59: =IF(I59="DEFINIR","DEFINIR",IF(M59="SI","CERRADO",IF(I59="-","-",IF(I59="--","EN PAUSA",I59-TODAY())))) -> - | L59: N/A | M59: N/A
B60: PRODUCCIÓN | C60: MIGUE | D60: 2 | E60: Dónde colocan los cuchillos en los relevos | F60: INDIVIDUAL | G60: 46054 | H60: =+IF(M60="SI","CERRADO",IF(G60="-","NO INICIADO",IF(I60="-","SIN FECHA OBJ.",IF(I60="--","EN PAUSA",TODAY()-G60)))) -> SIN FECHA OBJ. | I60: - | J60: 0 | K60: =IF(I60="DEFINIR","DEFINIR",IF(M60="SI","CERRADO",IF(I60="-","-",IF(I60="--","EN PAUSA",I60-TODAY())))) -> - | L60: N/A | M60: N/A
B61: PRODUCCIÓN | C61: MIGUE | D61: 2 | E61: Protectores auditivos copa colgados en pared | F61: INDIVIDUAL | G61: 46054 | H61: =+IF(M61="SI","CERRADO",IF(G61="-","NO INICIADO",IF(I61="-","SIN FECHA OBJ.",IF(I61="--","EN PAUSA",TODAY()-G61)))) -> SIN FECHA OBJ. | I61: - | J61: 0 | K61: =IF(I61="DEFINIR","DEFINIR",IF(M61="SI","CERRADO",IF(I61="-","-",IF(I61="--","EN PAUSA",I61-TODAY())))) -> - | L61: N/A | M61: N/A
B62: EMBALAJE | C62: MIGUE | D62: 2 | E62: Estandarización de flow, estuches y cajas | F62: INDIVIDUAL | G62: 45931 | H62: =+IF(M62="SI","CERRADO",IF(G62="-","NO INICIADO",IF(I62="-","SIN FECHA OBJ.",IF(I62="--","EN PAUSA",TODAY()-G62)))) -> SIN FECHA OBJ. | I62: - | J62: 0 | K62: =IF(I62="DEFINIR","DEFINIR",IF(M62="SI","CERRADO",IF(I62="-","-",IF(I62="--","EN PAUSA",I62-TODAY())))) -> - | L62: N/A | M62: NO
B63: EMBALAJE | C63: MIGUE | D63: 2 | E63: Uso de flow viejos para agotar stock | F63: INDIVIDUAL | G63: 45931 | H63: =+IF(M63="SI","CERRADO",IF(G63="-","NO INICIADO",IF(I63="-","SIN FECHA OBJ.",IF(I63="--","EN PAUSA",TODAY()-G63)))) -> SIN FECHA OBJ. | I63: - | J63: 0 | K63: =IF(I63="DEFINIR","DEFINIR",IF(M63="SI","CERRADO",IF(I63="-","-",IF(I63="--","EN PAUSA",I63-TODAY())))) -> - | L63: N/A | M63: NO
B64: PROYECTOS | C64: MIGUE | D64: 2 | E64: Etiquetadora automática | F64: MESA | G64: 45931 | H64: =+IF(M64="SI","CERRADO",IF(G64="-","NO INICIADO",IF(I64="-","SIN FECHA OBJ.",IF(I64="--","EN PAUSA",TODAY()-G64)))) -> SIN FECHA OBJ. | I64: - | J64: 0 | K64: =IF(I64="DEFINIR","DEFINIR",IF(M64="SI","CERRADO",IF(I64="-","-",IF(I64="--","EN PAUSA",I64-TODAY())))) -> - | L64: N/A | M64: NO
B65: PROYECTOS | C65: MIGUE | D65: 3 | E65: Estuchadora de 12 y de 20 | F65: INDIVIDUAL | G65: 45931 | H65: =+IF(M65="SI","CERRADO",IF(G65="-","NO INICIADO",IF(I65="-","SIN FECHA OBJ.",IF(I65="--","EN PAUSA",TODAY()-G65)))) -> SIN FECHA OBJ. | I65: - | J65: 0 | K65: =IF(I65="DEFINIR","DEFINIR",IF(M65="SI","CERRADO",IF(I65="-","-",IF(I65="--","EN PAUSA",I65-TODAY())))) -> - | L65: N/A | M65: NO
B66: PROYECTOS | C66: MIGUE | D66: 3 | E66: Hamburguesas estilo artesanal | F66: INDIVIDUAL | G66: 45931 | H66: =+IF(M66="SI","CERRADO",IF(G66="-","NO INICIADO",IF(I66="-","SIN FECHA OBJ.",IF(I66="--","EN PAUSA",TODAY()-G66)))) -> SIN FECHA OBJ. | I66: - | J66: 0 | K66: =IF(I66="DEFINIR","DEFINIR",IF(M66="SI","CERRADO",IF(I66="-","-",IF(I66="--","EN PAUSA",I66-TODAY())))) -> - | L66: N/A | M66: NO
B67: EMBALAJE | C67: MIGUE | D67: H | E67: Inventario bimestral Tigre | F67: INDIVIDUAL | G67: 46046 | H67: =+IF(M67="SI","CERRADO",IF(G67="-","NO INICIADO",IF(I67="-","SIN FECHA OBJ.",IF(I67="--","EN PAUSA",TODAY()-G67)))) -> SIN FECHA OBJ. | I67: - | J67: 0 | K67: =IF(I67="DEFINIR","DEFINIR",IF(M67="SI","CERRADO",IF(I67="-","-",IF(I67="--","EN PAUSA",I67-TODAY())))) -> - | L67: N/A | M67: N/A
B68: EMBALAJE | C68: MIGUE | D68: H | E68: Gestión depósito Tigre y Perón | F68: INDIVIDUAL | G68: 46062 | H68: =+IF(M68="SI","CERRADO",IF(G68="-","NO INICIADO",IF(I68="-","SIN FECHA OBJ.",IF(I68="--","EN PAUSA",TODAY()-G68)))) -> SIN FECHA OBJ. | I68: - | J68: 0 | K68: =IF(I68="DEFINIR","DEFINIR",IF(M68="SI","CERRADO",IF(I68="-","-",IF(I68="--","EN PAUSA",I68-TODAY())))) -> - | L68: N/A | M68: N/A
B69: EMBALAJE | C69: MIGUE | D69: - | E69: Inventario Tigre aditivos y embalaje | F69: INDIVIDUAL | G69: 46002 | H69: =+IF(M69="SI","CERRADO",IF(G69="-","NO INICIADO",IF(I69="-","SIN FECHA OBJ.",IF(I69="--","EN PAUSA",TODAY()-G69)))) -> CERRADO | I69: 46073 | J69: 0 | K69: =IF(I69="DEFINIR","DEFINIR",IF(M69="SI","CERRADO",IF(I69="-","-",IF(I69="--","EN PAUSA",I69-TODAY())))) -> CERRADO | L69: 1 | M69: SI
B70: GENERAL | C70: JUSTI | D70: 1 | E70: Relevamiento circuito: ingreso de rechazos y devoluciones | F70: INDIVIDUAL | G70: 46034 | H70: =+IF(M70="SI","CERRADO",IF(G70="-","NO INICIADO",IF(I70="-","SIN FECHA OBJ.",IF(I70="--","EN PAUSA",TODAY()-G70)))) -> SIN FECHA OBJ. | I70: - | J70: 0 | K70: =IF(I70="DEFINIR","DEFINIR",IF(M70="SI","CERRADO",IF(I70="-","-",IF(I70="--","EN PAUSA",I70-TODAY())))) -> - | L70: 0 | M70: NO
B71: GENERAL | C71: JUSTI | D71: 2 | E71: Abastecimiento Catter: definir circuito | F71: INDIVIDUAL | G71: 46034 | H71: =+IF(M71="SI","CERRADO",IF(G71="-","NO INICIADO",IF(I71="-","SIN FECHA OBJ.",IF(I71="--","EN PAUSA",TODAY()-G71)))) -> SIN FECHA OBJ. | I71: - | J71: 0 | K71: =IF(I71="DEFINIR","DEFINIR",IF(M71="SI","CERRADO",IF(I71="-","-",IF(I71="--","EN PAUSA",I71-TODAY())))) -> - | L71: 0 | M71: NO
B72: GENERAL | C72: JUSTI | D72: 2 | E72: Orden sector Recepción | F72: INDIVIDUAL | G72: 46034 | H72: =+IF(M72="SI","CERRADO",IF(G72="-","NO INICIADO",IF(I72="-","SIN FECHA OBJ.",IF(I72="--","EN PAUSA",TODAY()-G72)))) -> SIN FECHA OBJ. | I72: - | J72: 0 | K72: =IF(I72="DEFINIR","DEFINIR",IF(M72="SI","CERRADO",IF(I72="-","-",IF(I72="--","EN PAUSA",I72-TODAY())))) -> - | L72: 0 | M72: NO
B73: GENERAL | C73: JUSTI | D73: 3 | E73: Dotación Cazadores | F73: INDIVIDUAL | G73: 46034 | H73: =+IF(M73="SI","CERRADO",IF(G73="-","NO INICIADO",IF(I73="-","SIN FECHA OBJ.",IF(I73="--","EN PAUSA",TODAY()-G73)))) -> 73 | I73: 46112 | J73: 1 | K73: =IF(I73="DEFINIR","DEFINIR",IF(M73="SI","CERRADO",IF(I73="-","-",IF(I73="--","EN PAUSA",I73-TODAY())))) -> 5 | L73: 0 | M73: NO
B74: GENERAL | C74: JUSTI | D74: - | E74: Dotación Mantenimiento | F74: INDIVIDUAL | G74: 45962 | H74: =+IF(M74="SI","CERRADO",IF(G74="-","NO INICIADO",IF(I74="-","SIN FECHA OBJ.",IF(I74="--","EN PAUSA",TODAY()-G74)))) -> CERRADO | I74: 45991 | J74: 0 | K74: =IF(I74="DEFINIR","DEFINIR",IF(M74="SI","CERRADO",IF(I74="-","-",IF(I74="--","EN PAUSA",I74-TODAY())))) -> CERRADO | L74: 0.99 | M74: SI
B75: GENERAL | C75: JUSTI | D75: - | E75: Dotación Calidad | F75: INDIVIDUAL | G75: 45992 | H75: =+IF(M75="SI","CERRADO",IF(G75="-","NO INICIADO",IF(I75="-","SIN FECHA OBJ.",IF(I75="--","EN PAUSA",TODAY()-G75)))) -> CERRADO | I75: 46022 | J75: 0 | K75: =IF(I75="DEFINIR","DEFINIR",IF(M75="SI","CERRADO",IF(I75="-","-",IF(I75="--","EN PAUSA",I75-TODAY())))) -> CERRADO | L75: 0.99 | M75: SI
B76: GENERAL | C76: JUSTI | D76: - | E76: Dotación Higiene | F76: INDIVIDUAL | G76: 45931 | H76: =+IF(M76="SI","CERRADO",IF(G76="-","NO INICIADO",IF(I76="-","SIN FECHA OBJ.",IF(I76="--","EN PAUSA",TODAY()-G76)))) -> CERRADO | I76: 45961 | J76: 0 | K76: =IF(I76="DEFINIR","DEFINIR",IF(M76="SI","CERRADO",IF(I76="-","-",IF(I76="--","EN PAUSA",I76-TODAY())))) -> CERRADO | L76: 0.99 | M76: SI
B77: GENERAL | C77: JUSTI | D77: - | E77: Recorridas | F77: MESA | G77: 45931 | H77: =+IF(M77="SI","CERRADO",IF(G77="-","NO INICIADO",IF(I77="-","SIN FECHA OBJ.",IF(I77="--","EN PAUSA",TODAY()-G77)))) -> CERRADO | I77: 46022 | J77: 0 | K77: =IF(I77="DEFINIR","DEFINIR",IF(M77="SI","CERRADO",IF(I77="-","-",IF(I77="--","EN PAUSA",I77-TODAY())))) -> CERRADO | L77: 1 | M77: SI

Sheet MES CERRADO
D2: 44927 | E2: 44958 | F2: 44986 | G2: 45017 | H2: 45047 | I2: 45078 | J2: 45108 | K2: 45139 | L2: 45170 | M2: 45200 | N2: 45231 | O2: 45261 | P2: 45292 | Q2: 45323 | R2: 45352 | S2: 45383 | T2: 45413 | U2: 45444 | V2: 45474 | W2: 45505 | X2: 45536 | Y2: 45566 | Z2: 45597 | AA2: 45627 | AB2: 45658 | AC2: 45689 | AD2: 45717 | AE2: 45748 | AF2: 45778 | AG2: 45809 | AH2: 45839 | AI2: 45870 | AJ2: 45901 | AK2: 45931 | AL2: 45962 | AM2: 45992 | AN2: 46023 | AO2: 46054 | BA2: 2023 | BB2: 2024 | BC2: 2025
B3: PRODUCCIÓN REAL | C3: TN | D3: 992 | E3: 957 | F3: 1079 | G3: 1120 | H3: 1068 | I3: 983 | J3: 920 | K3: 987 | L3: 836 | M3: 887 | N3: 1034 | O3: 735 | P3: 863 | Q3: 654 | R3: 801 | S3: 826 | T3: 893 | U3: 691 | V3: 907 | W3: 953 | X3: 948 | Y3: 1074 | Z3: 1064 | AA3: 1082 | AB3: 1220 | AC3: 1151 | AD3: 1134 | AE3: 1126 | AF3: 1127.684 | AG3: 816.474 | AH3: =SUMIFS('TABLERO DIARIO'!$I$6:$ZZ$6,'TABLERO DIARIO'!$I$2:$ZZ$2,">="&DATE(2025,MONTH(AH$2),1),'TABLERO DIARIO'!$I$2:$ZZ$2,"<="&EOMONTH(AH$2,0))/1000 -> 1119.4608 | AI3: =SUMIFS('TABLERO DIARIO'!$I$6:$ZZ$6,'TABLERO DIARIO'!$I$2:$ZZ$2,">="&DATE(2025,MONTH(AI$2),1),'TABLERO DIARIO'!$I$2:$ZZ$2,"<="&EOMONTH(AI$2,0))/1000 -> 947.0842 | AJ3: =SUMIFS('TABLERO DIARIO'!$I$6:$ABL$6,'TABLERO DIARIO'!$I$2:$ABL$2,">="&DATE(2025,MONTH(AJ$2),1),'TABLERO DIARIO'!$I$2:$ABL$2,"<="&EOMONTH(AJ$2,0))/1000 -> 1009.3253 | AK3: =SUMIFS('TABLERO DIARIO'!$I$6:$AEV$6,'TABLERO DIARIO'!$I$2:$AEV$2,">="&DATE(2025,MONTH(AK$2),1),'TABLERO DIARIO'!$I$2:$AEV$2,"<="&EOMONTH(AK$2,0))/1000 -> 1079.8902 | AL3: =SUMIFS('TABLERO DIARIO'!$I$6:$AMA$6,'TABLERO DIARIO'!$I$2:$AMA$2,">="&DATE(2025,MONTH(AL$2),1),'TABLERO DIARIO'!$I$2:$AMA$2,"<="&EOMONTH(AL$2,0))/1000 -> 984.7747 | AM3: =SUMIFS('TABLERO DIARIO'!$I$6:$AMA$6,'TABLERO DIARIO'!$I$2:$AMA$2,">="&DATE(2025,MONTH(AM$2),1),'TABLERO DIARIO'!$I$2:$AMA$2,"<="&EOMONTH(AM$2,0))/1000 -> 1089.6389 | AN3: =SUMIFS('TABLERO DIARIO'!$ALW$6:$ASW$6,'TABLERO DIARIO'!$ALW$2:$ASW$2,">="&DATE(2026,MONTH(AN$2),1),'TABLERO DIARIO'!$ALW$2:$ASW$2,"<="&EOMONTH(AN$2,0))/1000 -> 1163.6429 | AO3: =SUMIFS('TABLERO DIARIO'!$ALW$6:$ASW$6,'TABLERO DIARIO'!$ALW$2:$ASW$2,">="&DATE(2026,MONTH(AO$2),1),'TABLERO DIARIO'!$ALW$2:$ASW$2,"<="&EOMONTH(AO$2,0))/1000 -> 1070.7313 | BA3: =IFERROR(AVERAGE(D3:O3),"-") -> 966.5 | BB3: =IFERROR(AVERAGE(P3:AA3),"-") -> 896.33333 | BC3: =IFERROR(SUMIFS(AB3:AM3,AB3:AM3,"<>0",AB3:AM3,"<>-",AB3:AM3,"<>",AB3:AM3,"<> ")/COUNTIFS(AB3:AM3,"<>0",AB3:AM3,"<>-",AB3:AM3,"<>",AB3:AM3,"<> "),"-") -> 1067.111
B4: PRODUCCIÓN OBJETIVO | C4: TN | D4: 1141 | E4: 1047 | F4: 1119 | G4: 1071 | H4: 1096 | I4: 1065 | J4: 1108 | K4: 966 | L4: 882 | M4: 840 | N4: 1008 | O4: 798 | P4: 924 | Q4: 798 | R4: 777 | S4: 820 | T4: 902 | U4: 672 | V4: 940 | W4: 955 | X4: 1099 | Y4: 1107 | Z4: 1087 | AA4: 1037 | AB4: 1176 | AC4: 1126 | AD4: 1148 | AE4: 1110 | AF4: 1185 | AG4: 850 | AH4: 1140 | AI4: =+CALENDARIO!AV23 -> 945 | AJ4: =+CALENDARIO!BD23 -> 1070 | AK4: =+CALENDARIO!BL23 -> 1090 | AL4: =+CALENDARIO!BT23 -> 1015 | AM4: =+CALENDARIO!CB23 -> 1115 | AN4: =+CALENDARIO!CJ23 -> 1105 | AO4: =+CALENDARIO!CR23 -> 1050 | BA4: =IFERROR(AVERAGE(D4:O4),"-") -> 1011.75 | BB4: =IFERROR(AVERAGE(P4:AA4),"-") -> 926.5 | BC4: =IFERROR(SUMIFS(AB4:AM4,AB4:AM4,"<>0",AB4:AM4,"<>-",AB4:AM4,"<>",AB4:AM4,"<> ")/COUNTIFS(AB4:AM4,"<>0",AB4:AM4,"<>-",AB4:AM4,"<>",AB4:AM4,"<> "),"-") -> 1080.8333
B5: PRODUCCIÓN REAL VS OBJETIVO | C5: % | D5: 0.87 | E5: 0.91 | F5: 0.96 | G5: 1.05 | H5: 0.97 | I5: 0.92 | J5: 0.83 | K5: 1.02 | L5: 0.95 | M5: 1.06 | N5: 1.03 | O5: 0.92 | P5: 0.93 | Q5: 0.82 | R5: 1.03 | S5: 1.01 | T5: 0.99 | U5: 1.03 | V5: 0.97 | W5: 1 | X5: 0.86 | Y5: 0.97 | Z5: 0.98 | AA5: 1.04 | AB5: 1.04 | AC5: =IFERROR(IF(AC3<>0,AC3/AC4,"-"),"FD") -> 1.0222025 | AD5: =IFERROR(IF(AD3<>0,AD3/AD4,"-"),"FD") -> 0.98780488 | AE5: =IFERROR(IF(AE3<>0,AE3/AE4,"-"),"FD") -> 1.0144144 | AF5: =IFERROR(IF(AF3<>0,AF3/AF4,"-"),"FD") -> 0.95163207 | AG5: =IFERROR(IF(AG3<>0,AG3/AG4,"-"),"FD") -> 0.96055765 | AH5: =IFERROR(IF(AH3<>0,AH3/AH4,"-"),"FD") -> 0.98198316 | AI5: =IFERROR(IF(AI3<>0,AI3/AI4,"-"),"FD") -> 1.0022055 | AJ5: =IFERROR(IF(AJ3<>0,AJ3/AJ4,"-"),"FD") -> 0.94329467 | ... AO5: =IFERROR(IF(AO3<>0,AO3/AO4,"-"),"FD") -> 1.0197441 | BA5: =IFERROR(IF(BA3<>0,BA3/BA4,"-"),"FD") -> 0.95527551 | BB5: =IFERROR(IF(BB3<>0,BB3/BB4,"-"),"FD") -> 0.96744019 | BC5: =IFERROR(SUMIFS(AB5:AM5,AB5:AM5,"<>0",AB5:AM5,"<>-",AB5:AM5,"<>",AB5:AM5,"<> ")/COUNTIFS(AB5:AM5,"<>0",AB5:AM5,"<>-",AB5:AM5,"<>",AB5:AM5,"<> "),"-") -> 0.98685798
B6: PRODUCCIÓN PROM POR DÍA | C6: TN | D6: - | E6: - | F6: - | G6: - | H6: - | I6: - | J6: - | K6: - | L6: - | M6: - | N6: - | P6: - | Q6: - | R6: - | S6: - | T6: - | U6: - | V6: - | W6: - | X6: - | Y6: - | Z6: - | AA6: - | AB6: - | AC6: =(SUMIFS('TABLERO DIARIO'!$I$6:$ZZ$6,'TABLERO DIARIO'!$I$2:$ZZ$2,">="&DATE(2025,MONTH(AC$2),1),'TABLERO DIARIO'!$I$2:$ZZ$2,"<="&EOMONTH(AC$2,0))/COUNTIFS('TABLERO DIARIO'!$I$2:$ZZ$2,">="&DATE(2025,MONTH(AC$2),1),'TABLERO DIARIO'!$I$2:$ZZ$2,"<="&EOMONTH(AC$2,0),'TABLERO DIARIO'!$I$6:$ZZ$6,"<>0"))/1000 -> 41.102932 | AD6: =(SUMIFS('TABLERO DIARIO'!$I$6:$ZZ$6,'TABLERO DIARIO'!$I$2:$ZZ$2,">="&DATE(2025,MONTH(AD$2),1),'TABLERO DIARIO'!$I$2:$ZZ$2,"<="&EOMONTH(AD$2,0))/COUNTIFS('TABLERO DIARIO'!$I$2:$ZZ$2,">="&DATE(2025,MONTH(AD$2),1),'TABLERO DIARIO'!$I$2:$ZZ$2,"<="&EOMONTH(AD$2,0),'TABLERO DIARIO'!$I$6:$ZZ$6,"<>0"))/1000 -> 40.506011 | AE6: =(SUMIFS('TABLERO DIARIO'!$I$6:$ZZ$6,'TABLERO DIARIO'!$I$2:$ZZ$2,">="&DATE(2025,MONTH(AE$2),1),'TABLERO DIARIO'!$I$2:$ZZ$2,"<="&EOMONTH(AE$2,0))/COUNTIFS('TABLERO DIARIO'!$I$2:$ZZ$2,">="&DATE(2025,MONTH(AE$2),1),'TABLERO DIARIO'!$I$2:$ZZ$2,"<="&EOMONTH(AE$2,0),'TABLERO DIARIO'!$I$6:$ZZ$6,"<>0"))/1000 -> 43.317158 | AF6: =(SUMIFS('TABLERO DIARIO'!$I$6:$ZZ$6,'TABLERO DIARIO'!$I$2:$ZZ$2,">="&DATE(2025,MONTH(AF$2),1),'TABLERO DIARIO'!$I$2:$ZZ$2,"<="&EOMONTH(AF$2,0))/COUNTIFS('TABLERO DIARIO'!$I$2:$ZZ$2,">="&DATE(2025,MONTH(AF$2),1),'TABLERO DIARIO'!$I$2:$ZZ$2,"<="&EOMONTH(AF$2,0),'TABLERO DIARIO'!$I$6:$ZZ$6,"<>0"))/1000 -> 45.10734 | AG6: =(SUMIFS('TABLERO DIARIO'!$I$6:$ZZ$6,'TABLERO DIARIO'!$I$2:$ZZ$2,">="&DATE(2025,MONTH(AG$2),1),'TABLERO DIARIO'!$I$2:$ZZ$2,"<="&EOMONTH(AG$2,0))/COUNTIFS('TABLERO DIARIO'!$I$2:$ZZ$2,">="&DATE(2025,MONTH(AG$2),1),'TABLERO DIARIO'!$I$2:$ZZ$2,"<="&EOMONTH(AG$2,0),'TABLERO DIARIO'!$I$6:$ZZ$6,"<>0"))/1000 -> 42.966907 | AH6: =(SUMIFS('TABLERO DIARIO'!$I$6:$ZZ$6,'TABLERO DIARIO'!$I$2:$ZZ$2,">="&DATE(2025,MONTH(AH$2),1),'TABLERO DIARIO'!$I$2:$ZZ$2,"<="&EOMONTH(AH$2,0))/COUNTIFS('TABLERO DIARIO'!$I$2:$ZZ$2,">="&DATE(2025,MONTH(AH$2),1),'TABLERO DIARIO'!$I$2:$ZZ$2,"<="&EOMONTH(AH$2,0),'TABLERO DIARIO'!$I$6:$ZZ$6,"<>0"))/1000 -> 43.056185 | AI6: =IFERROR((SUMIFS('TABLERO DIARIO'!$I$6:$ZZ$6,'TABLERO DIARIO'!$I$2:$ZZ$2,">="&DATE(2025,MONTH(AI$2),1),'TABLERO DIARIO'!$I$2:$ZZ$2,"<="&EOMONTH(AI$2,0))/COUNTIFS('TABLERO DIARIO'!$I$2:$ZZ$2,">="&DATE(2025,MONTH(AI$2),1),'TABLERO DIARIO'!$I$2:$ZZ$2,"<="&EOMONTH(AI$2,0),'TABLERO DIARIO'!$I$6:$ZZ$6,"<>0"))/1000,"-") -> 45.099248 | AJ6: =IFERROR((SUMIFS('TABLERO DIARIO'!$I$6:$ABL$6,'TABLERO DIARIO'!$I$2:$ABL$2,">="&DATE(2025,MONTH(AJ$2),1),'TABLERO DIARIO'!$I$2:$ABL$2,"<="&EOMONTH(AJ$2,0))/COUNTIFS('TABLERO DIARIO'!$I$2:$ABL$2,">="&DATE(2025,MONTH(AJ$2),1),'TABLERO DIARIO'!$I$2:$ABL$2,"<="&EOMONTH(AJ$2,0),'TABLERO DIARIO'!$I$6:$ABL$6,"<>0"))/1000,"-") -> 42.055221 | AK6: =IFERROR((SUMIFS('TABLERO DIARIO'!$I$6:$AEV$6,'TABLERO DIARIO'!$I$2:$AEV$2,">="&DATE(2025,MONTH(AK$2),1),'TABLERO DIARIO'!$I$2:$AEV$2,"<="&EOMONTH(AK$2,0))/COUNTIFS('TABLERO DIARIO'!$I$2:$AEV$2,">="&DATE(2025,MONTH(AK$2),1),'TABLERO DIARIO'!$I$2:$AEV$2,"<="&EOMONTH(AK$2,0),'TABLERO DIARIO'!$I$6:$AEV$6,"<>0"))/1000,"-") -> 38.567507 | AL6: =IFERROR((SUMIFS('TABLERO DIARIO'!$AEV$6:$AMA$6,'TABLERO DIARIO'!$AEV$2:$AMA$2,">="&DATE(2025,MONTH(AL$2),1),'TABLERO DIARIO'!$AEV$2:$AMA$2,"<="&EOMONTH(AL$2,0))/COUNTIFS('TABLERO DIARIO'!$AEV$2:$AMA$2,">="&DATE(2025,MONTH(AL$2),1),'TABLERO DIARIO'!$AEV$2:$AMA$2,"<="&EOMONTH(AL$2,0),'TABLERO DIARIO'!$AEV$6:$AMA$6,"<>0"))/1000,"-") -> 37.87595 | AM6: =IFERROR((SUMIFS('TABLERO DIARIO'!$AEV$6:$AMA$6,'TABLERO DIARIO'!$AEV$2:$AMA$2,">="&DATE(2025,MONTH(AM$2),1),'TABLERO DIARIO'!$AEV$2:$AMA$2,"<="&EOMONTH(AM$2,0))/COUNTIFS('TABLERO DIARIO'!$AEV$2:$AMA$2,">="&DATE(2025,MONTH(AM$2),1),'TABLERO DIARIO'!$AEV$2:$AMA$2,"<="&EOMONTH(AM$2,0),'TABLERO DIARIO'!$AEV$6:$AMA$6,"<>0"))/1000,"-") -> 38.915675 | AN6: =IFERROR((SUMIFS('TABLERO DIARIO'!$AEV$6:$ASW$6,'TABLERO DIARIO'!$AEV$2:$ASW$2,">="&DATE(2026,MONTH(AN$2),1),'TABLERO DIARIO'!$AEV$2:$ASW$2,"<="&EOMONTH(AN$2,0))/COUNTIFS('TABLERO DIARIO'!$AEV$2:$ASW$2,">="&DATE(2026,MONTH(AN$2),1),'TABLERO DIARIO'!$AEV$2:$ASW$2,"<="&EOMONTH(AN$2,0),'TABLERO DIARIO'!$AEV$6:$ASW$6,"<>0"))/1000,"-") -> 43.097885 | AO6: =IFERROR((SUMIFS('TABLERO DIARIO'!$AEV$6:$ASW$6,'TABLERO DIARIO'!$AEV$2:$ASW$2,">="&DATE(2026,MONTH(AO$2),1),'TABLERO DIARIO'!$AEV$2:$ASW$2,"<="&EOMONTH(AO$2,0))/COUNTIFS('TABLERO DIARIO'!$AEV$2:$ASW$2,">="&DATE(2026,MONTH(AO$2),1),'TABLERO DIARIO'!$AEV$2:$ASW$2,"<="&EOMONTH(AO$2,0),'TABLERO DIARIO'!$AEV$6:$ASW$6,"<>0"))/1000,"-") -> 44.613804 | BA6: =IFERROR(AVERAGE(D6:O6),"-") -> - | BB6: =IFERROR(AVERAGE(P6:AA6),"-") -> - | BC6: =IFERROR(SUMIFS(AB6:AM6,AB6:AM6,"<>0",AB6:AM6,"<>-",AB6:AM6,"<>",AB6:AM6,"<> ")/COUNTIFS(AB6:AM6,"<>0",AB6:AM6,"<>-",AB6:AM6,"<>",AB6:AM6,"<> "),"-") -> 41.688194
B7: PRODUCCIÓN PROM SDF | C7: TN | AC7: =(SUMIFS('TABLERO DIARIO'!$I$6:$ZZ$6,'TABLERO DIARIO'!$I$2:$ZZ$2,">="&DATE(2025,MONTH(AC$2),1),'TABLERO DIARIO'!$I$2:$ZZ$2,"<="&EOMONTH(AC$2,0),'TABLERO DIARIO'!$I$5:$ZZ$5,"SDF")/COUNTIFS('TABLERO DIARIO'!$I$2:$ZZ$2,">="&DATE(2025,MONTH(AC$2),1),'TABLERO DIARIO'!$I$2:$ZZ$2,"<="&EOMONTH(AC$2,0),'TABLERO DIARIO'!$I$5:$ZZ$5,"SDF",'TABLERO DIARIO'!$I$6:$ZZ$6,"<>0"))/1000 -> 32.164625 | AD7: =(SUMIFS('TABLERO DIARIO'!$I$6:$ZZ$6,'TABLERO DIARIO'!$I$2:$ZZ$2,">="&DATE(2025,MONTH(AD$2),1),'TABLERO DIARIO'!$I$2:$ZZ$2,"<="&EOMONTH(AD$2,0),'TABLERO DIARIO'!$I$5:$ZZ$5,"SDF")/COUNTIFS('TABLERO DIARIO'!$I$2:$ZZ$2,">="&DATE(2025,MONTH(AD$2),1),'TABLERO DIARIO'!$I$2:$ZZ$2,"<="&EOMONTH(AD$2,0),'TABLERO DIARIO'!$I$5:$ZZ$5,"SDF",'TABLERO DIARIO'!$I$6:$ZZ$6,"<>0"))/1000 -> 35.487044 | AE7: =(SUMIFS('TABLERO DIARIO'!$I$6:$ZZ$6,'TABLERO DIARIO'!$I$2:$ZZ$2,">="&DATE(2025,MONTH(AE$2),1),'TABLERO DIARIO'!$I$2:$ZZ$2,"<="&EOMONTH(AE$2,0),'TABLERO DIARIO'!$I$5:$ZZ$5,"SDF")/COUNTIFS('TABLERO DIARIO'!$I$2:$ZZ$2,">="&DATE(2025,MONTH(AE$2),1),'TABLERO DIARIO'!$I$2:$ZZ$2,"<="&EOMONTH(AE$2,0),'TABLERO DIARIO'!$I$5:$ZZ$5,"SDF",'TABLERO DIARIO'!$I$6:$ZZ$6,"<>0"))/1000 -> 32.40424 | AF7: =(SUMIFS('TABLERO DIARIO'!$I$6:$ZZ$6,'TABLERO DIARIO'!$I$2:$ZZ$2,">="&DATE(2025,MONTH(AF$2),1),'TABLERO DIARIO'!$I$2:$ZZ$2,"<="&EOMONTH(AF$2,0),'TABLERO DIARIO'!$I$5:$ZZ$5,"SDF")/COUNTIFS('TABLERO DIARIO'!$I$2:$ZZ$2,">="&DATE(2025,MONTH(AF$2),1),'TABLERO DIARIO'!$I$2:$ZZ$2,"<="&EOMONTH(AF$2,0),'TABLERO DIARIO'!$I$5:$ZZ$5,"SDF",'TABLERO DIARIO'!$I$6:$ZZ$6,"<>0"))/1000 -> 41.107675 | AG7: =(SUMIFS('TABLERO DIARIO'!$I$6:$ZZ$6,'TABLERO DIARIO'!$I$2:$ZZ$2,">="&DATE(2025,MONTH(AG$2),1),'TABLERO DIARIO'!$I$2:$ZZ$2,"<="&EOMONTH(AG$2,0),'TABLERO DIARIO'!$I$5:$ZZ$5,"SDF")/COUNTIFS('TABLERO DIARIO'!$I$2:$ZZ$2,">="&DATE(2025,MONTH(AG$2),1),'TABLERO DIARIO'!$I$2:$ZZ$2,"<="&EOMONTH(AG$2,0),'TABLERO DIARIO'!$I$5:$ZZ$5,"SDF",'TABLERO DIARIO'!$I$6:$ZZ$6,"<>0"))/1000 -> 42.126 | AH7: =(SUMIFS('TABLERO DIARIO'!$I$6:$ZZ$6,'TABLERO DIARIO'!$I$2:$ZZ$2,">="&DATE(2025,MONTH(AH$2),1),'TABLERO DIARIO'!$I$2:$ZZ$2,"<="&EOMONTH(AH$2,0),'TABLERO DIARIO'!$I$5:$ZZ$5,"SDF")/COUNTIFS('TABLERO DIARIO'!$I$2:$ZZ$2,">="&DATE(2025,MONTH(AH$2),1),'TABLERO DIARIO'!$I$2:$ZZ$2,"<="&EOMONTH(AH$2,0),'TABLERO DIARIO'!$I$5:$ZZ$5,"SDF",'TABLERO DIARIO'!$I$6:$ZZ$6,"<>0"))/1000 -> 38.04065 | AI7: =IFERROR((SUMIFS('TABLERO DIARIO'!$I$6:$ZZ$6,'TABLERO DIARIO'!$I$2:$ZZ$2,">="&DATE(2025,MONTH(AI$2),1),'TABLERO DIARIO'!$I$2:$ZZ$2,"<="&EOMONTH(AI$2,0),'TABLERO DIARIO'!$I$5:$ZZ$5,"SDF")/COUNTIFS('TABLERO DIARIO'!$I$2:$ZZ$2,">="&DATE(2025,MONTH(AI$2),1),'TABLERO DIARIO'!$I$2:$ZZ$2,"<="&EOMONTH(AI$2,0),'TABLERO DIARIO'!$I$5:$ZZ$5,"SDF",'TABLERO DIARIO'!$I$6:$ZZ$6,"<>0"))/1000,"-") -> - | AJ7: =IFERROR((SUMIFS('TABLERO DIARIO'!$I$6:$ABL$6,'TABLERO DIARIO'!$I$2:$ABL$2,">="&DATE(2025,MONTH(AJ$2),1),'TABLERO DIARIO'!$I$2:$ABL$2,"<="&EOMONTH(AJ$2,0),'TABLERO DIARIO'!$I$5:$ABL$5,"SDF")/COUNTIFS('TABLERO DIARIO'!$I$2:$ABL$2,">="&DATE(2025,MONTH(AJ$2),1),'TABLERO DIARIO'!$I$2:$ABL$2,"<="&EOMONTH(AJ$2,0),'TABLERO DIARIO'!$I$5:$ABL$5,"SDF",'TABLERO DIARIO'!$I$6:$ABL$6,"<>0"))/1000,"-") -> 37.4382 | AK7: =IFERROR((SUMIFS('TABLERO DIARIO'!$I$6:$AEV$6,'TABLERO DIARIO'!$I$2:$AEV$2,">="&DATE(2025,MONTH(AK$2),1),'TABLERO DIARIO'!$I$2:$AEV$2,"<="&EOMONTH(AK$2,0),'TABLERO DIARIO'!$I$5:$AEV$5,"SDF")/(-2+COUNTIFS('TABLERO DIARIO'!$I$2:$AEV$2,">="&DATE(2025,MONTH(AK$2),1),'TABLERO DIARIO'!$I$2:$AEV$2,"<="&EOMONTH(AK$2,0),'TABLERO DIARIO'!$I$5:$AEV$5,"SDF",'TABLERO DIARIO'!$I$6:$AEV$6,"<>0")))/1000,"-") -> 37.536 | AL7: =IFERROR(((SUMIFS('TABLERO DIARIO'!$AEV$7:$ALW$7,'TABLERO DIARIO'!$AEV$2:$ALW$2,">="&DATE(2025,MONTH(AL$2),1),'TABLERO DIARIO'!$AEV$2:$ALW$2,"<="&EOMONTH(AL$2,0),'TABLERO DIARIO'!$AEV$5:$ALW$5,"SDF")+SUMIFS('TABLERO DIARIO'!$AEV$8:$ALW$8,'TABLERO DIARIO'!$AEV$2:$ALW$2,">="&DATE(2025,MONTH(AL$2),1),'TABLERO DIARIO'!$AEV$2:$ALW$2,"<="&EOMONTH(AL$2,0),'TABLERO DIARIO'!$AEV$5:$ALW$5,"SDF"))/(COUNTIFS('TABLERO DIARIO'!$AEV$2:$ALW$2,">="&DATE(2025,MONTH(AL$2),1),'TABLERO DIARIO'!$AEV$2:$ALW$2,"<="&EOMONTH(AL$2,0),'TABLERO DIARIO'!$AEV$5:$ALW$5,"SDF",'TABLERO DIARIO'!$AEV$7:$ALW$7,"<>0")+COUNTIFS('TABLERO DIARIO'!$AEV$2:$ALW$2,">="&DATE(2025,MONTH(AL$2),1),'TABLERO DIARIO'!$AEV$2:$ALW$2,"<="&EOMONTH(AL$2,0),'TABLERO DIARIO'!$AEV$5:$ALW$5,"SDF",'TABLERO DIARIO'!$AEV$8:$ALW$8,"<>0"))*2)/1000,"-") -> 38.43665 | AM7: =IFERROR(((SUMIFS('TABLERO DIARIO'!$AEV$7:$ALW$7,'TABLERO DIARIO'!$AEV$2:$ALW$2,">="&DATE(2025,MONTH(AM$2),1),'TABLERO DIARIO'!$AEV$2:$ALW$2,"<="&EOMONTH(AM$2,0),'TABLERO DIARIO'!$AEV$5:$ALW$5,"SDF")+SUMIFS('TABLERO DIARIO'!$AEV$8:$ALW$8,'TABLERO DIARIO'!$AEV$2:$ALW$2,">="&DATE(2025,MONTH(AM$2),1),'TABLERO DIARIO'!$AEV$2:$ALW$2,"<="&EOMONTH(AM$2,0),'TABLERO DIARIO'!$AEV$5:$ALW$5,"SDF"))/(COUNTIFS('TABLERO DIARIO'!$AEV$2:$ALW$2,">="&DATE(2025,MONTH(AM$2),1),'TABLERO DIARIO'!$AEV$2:$ALW$2,"<="&EOMONTH(AM$2,0),'TABLERO DIARIO'!$AEV$5:$ALW$5,"SDF",'TABLERO DIARIO'!$AEV$7:$ALW$7,"<>0")+COUNTIFS('TABLERO DIARIO'!$AEV$2:$ALW$2,">="&DATE(2025,MONTH(AM$2),1),'TABLERO DIARIO'!$AEV$2:$ALW$2,"<="&EOMONTH(AM$2,0),'TABLERO DIARIO'!$AEV$5:$ALW$5,"SDF",'TABLERO DIARIO'!$AEV$8:$ALW$8,"<>0"))*2)/1000,"-") -> 36.045215 | AN7: =IFERROR(((SUMIFS('TABLERO DIARIO'!$ALW$7:$ASW$7,'TABLERO DIARIO'!$ALW$2:$ASW$2,">="&DATE(2026,MONTH(AN$2),1),'TABLERO DIARIO'!$ALW$2:$ASW$2,"<="&EOMONTH(AN$2,0),'TABLERO DIARIO'!$ALW$5:$ASW$5,"SDF")+SUMIFS('TABLERO DIARIO'!$ALW$8:$ASW$8,'TABLERO DIARIO'!$ALW$2:$ASW$2,">="&DATE(2026,MONTH(AN$2),1),'TABLERO DIARIO'!$ALW$2:$ASW$2,"<="&EOMONTH(AN$2,0),'TABLERO DIARIO'!$ALW$5:$ASW$5,"SDF"))/(COUNTIFS('TABLERO DIARIO'!$ALW$2:$ASW$2,">="&DATE(2026,MONTH(AN$2),1),'TABLERO DIARIO'!$ALW$2:$ASW$2,"<="&EOMONTH(AN$2,0),'TABLERO DIARIO'!$ALW$5:$ASW$5,"SDF",'TABLERO DIARIO'!$ALW$7:$ASW$7,"<>0")+COUNTIFS('TABLERO DIARIO'!$ALW$2:$ASW$2,">="&DATE(2026,MONTH(AN$2),1),'TABLERO DIARIO'!$ALW$2:$ASW$2,"<="&EOMONTH(AN$2,0),'TABLERO DIARIO'!$ALW$5:$ASW$5,"SDF",'TABLERO DIARIO'!$ALW$8:$ASW$8,"<>0"))*2)/1000,"-") -> 39.393464 | AO7: =IFERROR(((SUMIFS('TABLERO DIARIO'!$ALW$7:$ASW$7,'TABLERO DIARIO'!$ALW$2:$ASW$2,">="&DATE(2026,MONTH(AO$2),1),'TABLERO DIARIO'!$ALW$2:$ASW$2,"<="&EOMONTH(AO$2,0),'TABLERO DIARIO'!$ALW$5:$ASW$5,"SDF")+SUMIFS('TABLERO DIARIO'!$ALW$8:$ASW$8,'TABLERO DIARIO'!$ALW$2:$ASW$2,">="&DATE(2026,MONTH(AO$2),1),'TABLERO DIARIO'!$ALW$2:$ASW$2,"<="&EOMONTH(AO$2,0),'TABLERO DIARIO'!$ALW$5:$ASW$5,"SDF"))/(COUNTIFS('TABLERO DIARIO'!$ALW$2:$ASW$2,">="&DATE(2026,MONTH(AO$2),1),'TABLERO DIARIO'!$ALW$2:$ASW$2,"<="&EOMONTH(AO$2,0),'TABLERO DIARIO'!$ALW$5:$ASW$5,"SDF",'TABLERO DIARIO'!$ALW$7:$ASW$7,"<>0")+COUNTIFS('TABLERO DIARIO'!$ALW$2:$ASW$2,">="&DATE(2026,MONTH(AO$2),1),'TABLERO DIARIO'!$ALW$2:$ASW$2,"<="&EOMONTH(AO$2,0),'TABLERO DIARIO'!$ALW$5:$ASW$5,"SDF",'TABLERO DIARIO'!$ALW$8:$ASW$8,"<>0"))*2)/1000,"-") -> 40.433067 | BA7: =IFERROR(AVERAGE(D7:O7),"-") -> - | BB7: =IFERROR(AVERAGE(P7:AA7),"-") -> - | BC7: =IFERROR(SUMIFS(AB7:AM7,AB7:AM7,"<>0",AB7:AM7,"<>-",AB7:AM7,"<>",AB7:AM7,"<> ")/COUNTIFS(AB7:AM7,"<>0",AB7:AM7,"<>-",AB7:AM7,"<>",AB7:AM7,"<> "),"-") -> 37.07863
B8: PRODUCCIÓN PROM LV | C8: TN | D8: - | E8: - | F8: - | G8: - | H8: - | I8: - | J8: - | K8: - | L8: - | M8: - | N8: - | P8: - | Q8: - | R8: - | S8: - | T8: - | U8: - | V8: - | W8: - | X8: - | Y8: - | Z8: - | AA8: - | AB8: - | AC8: 44.6 | AD8: 42.1 | AE8: 45.9 | AF8: 45.8 | AG8: =(SUMIFS('TABLERO DIARIO'!$I$6:$ZZ$6,'TABLERO DIARIO'!$I$2:$ZZ$2,">="&DATE(2025,MONTH(AG$2),1),'TABLERO DIARIO'!$I$2:$ZZ$2,"<="&EOMONTH(AG$2,0),'TABLERO DIARIO'!$I$5:$ZZ$5,"LV")/COUNTIFS('TABLERO DIARIO'!$I$2:$ZZ$2,">="&DATE(2025,MONTH(AG$2),1),'TABLERO DIARIO'!$I$2:$ZZ$2,"<="&EOMONTH(AG$2,0),'TABLERO DIARIO'!$I$5:$ZZ$5,"LV",'TABLERO DIARIO'!$I$6:$ZZ$6,"<>0"))/1000 -> 43.013624 | AH8: =(SUMIFS('TABLERO DIARIO'!$I$6:$ZZ$6,'TABLERO DIARIO'!$I$2:$ZZ$2,">="&DATE(2025,MONTH(AH$2),1),'TABLERO DIARIO'!$I$2:$ZZ$2,"<="&EOMONTH(AH$2,0),'TABLERO DIARIO'!$I$5:$ZZ$5,"LV")/COUNTIFS('TABLERO DIARIO'!$I$2:$ZZ$2,">="&DATE(2025,MONTH(AH$2),1),'TABLERO DIARIO'!$I$2:$ZZ$2,"<="&EOMONTH(AH$2,0),'TABLERO DIARIO'!$I$5:$ZZ$5,"LV",'TABLERO DIARIO'!$I$6:$ZZ$6,"<>0"))/1000 -> 43.9681 | AI8: =IFERROR((SUMIFS('TABLERO DIARIO'!$I$6:$ZZ$6,'TABLERO DIARIO'!$I$2:$ZZ$2,">="&DATE(2025,MONTH(AI$2),1),'TABLERO DIARIO'!$I$2:$ZZ$2,"<="&EOMONTH(AI$2,0),'TABLERO DIARIO'!$I$5:$ZZ$5,"LV")/COUNTIFS('TABLERO DIARIO'!$I$2:$ZZ$2,">="&DATE(2025,MONTH(AI$2),1),'TABLERO DIARIO'!$I$2:$ZZ$2,"<="&EOMONTH(AI$2,0),'TABLERO DIARIO'!$I$5:$ZZ$5,"LV",'TABLERO DIARIO'!$I$6:$ZZ$6,"<>0"))/1000,"-") -> 45.099248 | AJ8: =IFERROR((SUMIFS('TABLERO DIARIO'!$I$6:$ABL$6,'TABLERO DIARIO'!$I$2:$ABL$2,">="&DATE(2025,MONTH(AJ$2),1),'TABLERO DIARIO'!$I$2:$ABL$2,"<="&EOMONTH(AJ$2,0),'TABLERO DIARIO'!$I$5:$ABL$5,"LV")/COUNTIFS('TABLERO DIARIO'!$I$2:$ABL$2,">="&DATE(2025,MONTH(AJ$2),1),'TABLERO DIARIO'!$I$2:$ABL$2,"<="&EOMONTH(AJ$2,0),'TABLERO DIARIO'!$I$5:$ABL$5,"LV",'TABLERO DIARIO'!$I$6:$ABL$6,"<>0"))/1000,"-") -> 42.47495 | AK8: =IFERROR((SUMIFS('TABLERO DIARIO'!$I$6:$AEV$6,'TABLERO DIARIO'!$I$2:$AEV$2,">="&DATE(2025,MONTH(AK$2),1),'TABLERO DIARIO'!$I$2:$AEV$2,"<="&EOMONTH(AK$2,0),'TABLERO DIARIO'!$I$5:$AEV$5,"LV")/COUNTIFS('TABLERO DIARIO'!$I$2:$AEV$2,">="&DATE(2025,MONTH(AK$2),1),'TABLERO DIARIO'!$I$2:$AEV$2,"<="&EOMONTH(AK$2,0),'TABLERO DIARIO'!$I$5:$AEV$5,"LV",'TABLERO DIARIO'!$I$6:$AEV$6,"<>0"))/1000,"-") -> 42.261191 | AL8: =IFERROR((SUMIFS('TABLERO DIARIO'!$AEV$6:$AMA$6,'TABLERO DIARIO'!$AEV$2:$AMA$2,">="&DATE(2025,MONTH(AL$2),1),'TABLERO DIARIO'!$AEV$2:$AMA$2,"<="&EOMONTH(AL$2,0),'TABLERO DIARIO'!$AEV$5:$AMA$5,"LV")/COUNTIFS('TABLERO DIARIO'!$AEV$2:$AMA$2,">="&DATE(2025,MONTH(AL$2),1),'TABLERO DIARIO'!$AEV$2:$AMA$2,"<="&EOMONTH(AL$2,0),'TABLERO DIARIO'!$AEV$5:$AMA$5,"LV",'TABLERO DIARIO'!$AEV$6:$AMA$6,"<>0"))/1000,"-") -> 43.738321 | AM8: =IFERROR((SUMIFS('TABLERO DIARIO'!$AEV$6:$AMA$6,'TABLERO DIARIO'!$AEV$2:$AMA$2,">="&DATE(2025,MONTH(AM$2),1),'TABLERO DIARIO'!$AEV$2:$AMA$2,"<="&EOMONTH(AM$2,0),'TABLERO DIARIO'!$AEV$5:$AMA$5,"LV")/COUNTIFS('TABLERO DIARIO'!$AEV$2:$AMA$2,">="&DATE(2025,MONTH(AM$2),1),'TABLERO DIARIO'!$AEV$2:$AMA$2,"<="&EOMONTH(AM$2,0),'TABLERO DIARIO'!$AEV$5:$AMA$5,"LV",'TABLERO DIARIO'!$AEV$6:$AMA$6,"<>0"))/1000,"-") -> 40.730714 | AN8: =IFERROR((SUMIFS('TABLERO DIARIO'!$ALW$6:$ASW$6,'TABLERO DIARIO'!$ALW$2:$ASW$2,">="&DATE(2026,MONTH(AN$2),1),'TABLERO DIARIO'!$ALW$2:$ASW$2,"<="&EOMONTH(AN$2,0),'TABLERO DIARIO'!$ALW$5:$ASW$5,"LV")/COUNTIFS('TABLERO DIARIO'!$ALW$2:$ASW$2,">="&DATE(2026,MONTH(AN$2),1),'TABLERO DIARIO'!$ALW$2:$ASW$2,"<="&EOMONTH(AN$2,0),'TABLERO DIARIO'!$ALW$5:$ASW$5,"LV",'TABLERO DIARIO'!$ALW$6:$ASW$6,"<>0"))/1000,"-") -> 44.15629 | AO8: =IFERROR((SUMIFS('TABLERO DIARIO'!$ALW$6:$ASW$6,'TABLERO DIARIO'!$ALW$2:$ASW$2,">="&DATE(2026,MONTH(AO$2),1),'TABLERO DIARIO'!$ALW$2:$ASW$2,"<="&EOMONTH(AO$2,0),'TABLERO DIARIO'!$ALW$5:$ASW$5,"LV")/COUNTIFS('TABLERO DIARIO'!$ALW$2:$ASW$2,">="&DATE(2026,MONTH(AO$2),1),'TABLERO DIARIO'!$ALW$2:$ASW$2,"<="&EOMONTH(AO$2,0),'TABLERO DIARIO'!$ALW$5:$ASW$5,"LV",'TABLERO DIARIO'!$ALW$6:$ASW$6,"<>0"))/1000,"-") -> 46.007383 | BA8: =IFERROR(AVERAGE(D8:O8),"-") -> - | BB8: =IFERROR(AVERAGE(P8:AA8),"-") -> - | BC8: =IFERROR(SUMIFS(AB8:AM8,AB8:AM8,"<>0",AB8:AM8,"<>-",AB8:AM8,"<>",AB8:AM8,"<> ")/COUNTIFS(AB8:AM8,"<>0",AB8:AM8,"<>-",AB8:AM8,"<>",AB8:AM8,"<> "),"-") -> 43.607832
B9: EFICIENCIA | C9: % | D9: 0.69 | E9: 0.75 | F9: 0.77 | G9: 0.83 | H9: 0.84 | I9: 0.78 | J9: 0.76 | K9: 0.78 | L9: 0.75 | M9: 0.76 | N9: 0.79 | O9: 0.71 | P9: 0.72 | Q9: 0.61 | R9: 0.68 | S9: 0.76 | T9: 0.75 | U9: 0.77 | V9: 0.7 | W9: 0.74 | X9: 0.66 | Y9: 0.73 | Z9: 0.74 | AA9: 0.8 | AB9: 0.8 | AC9: 0.8 | AD9: 0.789 | AE9: 0.808 | AF9: 0.821 | AG9: 0.816 | AH9: 0.793 | AI9: 0.807 | AJ9: 0.76 | AK9: 0.76 | AL9: 0.787 | AM9: 0.764 | AN9: 0.791 | AO9: 0.832 | BA9: =IFERROR(AVERAGE(D9:O9),"-") -> 0.7675 | BB9: =IFERROR(AVERAGE(P9:AA9),"-") -> 0.72166667 | BC9: =IFERROR(SUMIFS(AB9:AM9,AB9:AM9,"<>0",AB9:AM9,"<>-",AB9:AM9,"<>",AB9:AM9,"<> ")/COUNTIFS(AB9:AM9,"<>0",AB9:AM9,"<>-",AB9:AM9,"<>",AB9:AM9,"<> "),"-") -> 0.79208333
B10: MERMA | C10: % | D10: 0.029 | E10: 0.036 | F10: 0.033 | G10: 0.036 | H10: 0.036 | I10: 0.031 | J10: 0.032 | K10: 0.037 | L10: 0.036 | M10: 0.036 | N10: 0.037 | O10: 0.039 | P10: 0.035 | Q10: 0.035 | R10: 0.032 | S10: 0.028 | T10: 0.023 | U10: 0.022 | V10: 0.018 | W10: 0.019 | X10: 0.02 | Y10: 0.02 | Z10: 0.018 | AA10: 0.021 | AB10: 0.024 | AC10: 0.023 | AD10: 0.019 | AE10: =SUM(AE11:AE15) -> 0.0196 | AF10: =SUM(AF11:AF15) -> 0.019 | AG10: =SUM(AG11:AG15) -> 0.0256 | AH10: =SUM(AH11:AH15) -> 0.02292 | AI10: =SUM(AI11:AI15) -> 0.02111 | AJ10: 0.02291 | AK10: 0.02664 | AL10: =+SUM(AL11:AL15) -> 0.02571 | AM10: 0.02249 | AN10: 0.02126 | AO10: 0.02203 | BA10: =IFERROR(AVERAGE(D10:O10),"-") -> 0.034833333 | BB10: =IFERROR(AVERAGE(P10:AA10),"-") -> 0.02425 | BC10: =IFERROR(SUMIFS(AB10:AM10,AB10:AM10,"<>0",AB10:AM10,"<>-",AB10:AM10,"<>",AB10:AM10,"<> ")/COUNTIFS(AB10:AM10,"<>0",AB10:AM10,"<>-",AB10:AM10,"<>",AB10:AM10,"<> "),"-") -> 0.022665
B11: DECOMISO | C11: % | G11: 0.016 | H11: 0.014 | I11: 0.014 | J11: 0.015 | K11: 0.014 | L11: 0.016 | M11: 0.016 | N11: 0.017 | O11: 0.018 | P11: 0.015 | Q11: 0.018 | R11: 0.016 | S11: 0.014 | T11: 0.013 | U11: 0.008 | V11: 0.005 | W11: 0.004 | X11: 0.005 | Y11: 0.006 | Z11: 0.007 | AA11: 0.006 | AB11: 0.7% | AC11: 0.7% | AD11: 0.007 | AE11: 0.0068 | AF11: 0.0069 | AG11: 0.00654 | AH11: =+AH16 -> 0.00742 | AI11: 0.00756 | AJ11: 0.00755 | AK11: 0.0085 | AL11: 0.0089 | AM11: 0.00987 | AN11: 0.0084 | AO11: 0.00779 | BA11: =IFERROR(AVERAGE(D11:O11),"-") -> 0.015555556 | BB11: =IFERROR(AVERAGE(P11:AA11),"-") -> 0.00975 | BC11: =IFERROR(SUMIFS(AB11:AM11,AB11:AM11,"<>0",AB11:AM11,"<>-",AB11:AM11,"<>",AB11:AM11,"<> ")/COUNTIFS(AB11:AM11,"<>0",AB11:AM11,"<>-",AB11:AM11,"<>",AB11:AM11,"<> "),"-") -> 0.00642
B12: PÉRDIDA POR PESO | C12: % | G12: 0.004 | H12: 0.005 | I12: 0.004 | J12: 0.004 | K12: 0.004 | L12: 0.006 | M12: 0.007 | N12: 0.004 | O12: 0.006 | P12: 0.006 | Q12: 0.007 | R12: 0.002 | S12: 0 | T12: 0.001 | U12: 0.001 | V12: 0.003 | W12: 0.002 | X12: 0.002 | Y12: 0.001 | Z12: 0.001 | AA12: 0.001 | AB12: 0.5% | AC12: 0.3% | AD12: 0.002 | AE12: 0.0005 | AF12: 0.0024 | AG12: 0.0018 | AH12: 0.0039 | AI12: 0.0009 | AJ12: 0.0023 | AK12: 0.0048 | AL12: 0.0034 | AM12: 0.0027 | AN12: 0.0039 | BA12: =IFERROR(AVERAGE(D12:O12),"-") -> 0.0048888889 | BB12: =IFERROR(AVERAGE(P12:AA12),"-") -> 0.00225 | BC12: =IFERROR(SUMIFS(AB12:AM12,AB12:AM12,"<>0",AB12:AM12,"<>-",AB12:AM12,"<>",AB12:AM12,"<> ")/COUNTIFS(AB12:AM12,"<>0",AB12:AM12,"<>-",AB12:AM12,"<>",AB12:AM12,"<> "),"-") -> 0.0020583333
B13: PÉRDIDA POR FRÍO | C13: % | G13: 0.003 | H13: 0.003 | I13: 0.004 | J13: 0.004 | K13: 0.002 | L13: 0.004 | M13: 0.003 | N13: 0.003 | O13: 0.004 | P13: 0.004 | Q13: 0.003 | R13: 0.003 | S13: 0.003 | T13: 0.003 | U13: 0.004 | V13: 0.004 | W13: 0.002 | X13: 0.002 | Y13: 0.003 | Z13: 0.003 | AA13: 0.003 | AB13: 0.2% | AC13: 0.3% | AD13: 0.003 | AE13: 0.0023 | AF13: 0.0014 | AG13: 0.001 | AH13: 0.0026 | AI13: 0.0019 | AJ13: 0.0022 | AK13: 0.0034 | AL13: 0.0018 | AM13: 0.0019 | AN13: 0.0018 | BA13: =IFERROR(AVERAGE(D13:O13),"-") -> 0.0033333333 | BB13: =IFERROR(AVERAGE(P13:AA13),"-") -> 0.0030833333 | BC13: =IFERROR(SUMIFS(AB13:AM13,AB13:AM13,"<>0",AB13:AM13,"<>-",AB13:AM13,"<>",AB13:AM13,"<> ")/COUNTIFS(AB13:AM13,"<>0",AB13:AM13,"<>-",AB13:AM13,"<>",AB13:AM13,"<> "),"-") -> 0.0017916667
B14: SIN EXPLICACIÓN | C14: % | G14: 0.012 | H14: 0.014 | I14: 0.01 | J14: 0.01 | K14: 0.015 | L14: 0.01 | M14: 0.01 | N14: 0.012 | O14: 0.011 | P14: 0.01 | Q14: 0.007 | R14: 0.011 | S14: 0.011 | T14: 0.006 | U14: 0.009 | V14: 0.006 | W14: 0.011 | X14: 0.011 | Y14: 0.01 | Z14: 0.007 | AA14: 0.011 | AB14: 1.0% | AC14: 1.0% | AD14: 0.007 | AE14: 0.009 | AF14: 0.009 | AG14: 0.0117 | AH14: 0.005 | AI14: 0.0071 | AJ14: 0.0075 | AK14: 0.0059 | AL14: 0.00766 | AM14: 0.0115 | AN14: 0.01126 | BA14: =IFERROR(AVERAGE(D14:O14),"-") -> 0.011555556 | BB14: =IFERROR(AVERAGE(P14:AA14),"-") -> 0.0091666667 | BC14: =IFERROR(SUMIFS(AB14:AM14,AB14:AM14,"<>0",AB14:AM14,"<>-",AB14:AM14,"<>",AB14:AM14,"<> ")/COUNTIFS(AB14:AM14,"<>0",AB14:AM14,"<>-",AB14:AM14,"<>",AB14:AM14,"<> "),"-") -> 0.00678
B15: HIELO | C15: % | AE15: 0.001 | AF15: -0.0007 | AG15: 0.00456 | AH15: 0.004 | AI15: 0.00365 | AJ15: 0.00333 | AK15: 0.004 | AL15: 0.00395 | AM15: -0.0038 | AN15: -0.00413 | AO15: -0.00043 | BA15: =IFERROR(AVERAGE(D15:O15),"-") -> - | BB15: =IFERROR(AVERAGE(P15:AA15),"-") -> - | BC15: =IFERROR(SUMIFS(AB15:AM15,AB15:AM15,"<>0",AB15:AM15,"<>-",AB15:AM15,"<>",AB15:AM15,"<> ")/COUNTIFS(AB15:AM15,"<>0",AB15:AM15,"<>-",AB15:AM15,"<>",AB15:AM15,"<> "),"-") -> 0.0022211111
B16: DECOMISO | C16: % | D16: 0.01 | E16: 0.018 | F16: 0.018 | G16: 0.016 | H16: 0.014 | I16: 0.014 | J16: 0.015 | K16: 0.015 | L16: 0.016 | M16: 0.016 | N16: 0.017 | O16: 0.018 | P16: 0.015 | Q16: 0.018 | R16: 0.016 | S16: 0.014 | T16: 0.013 | U16: 0.008 | V16: 0.005 | W16: 0.004 | X16: 0.005 | Y16: 0.006 | Z16: 0.007 | AA16: 0.006 | AB16: 0.007 | AC16: 0.007 | AD16: 0.007 | AE16: 0.0068 | AF16: 0.0069 | AG16: 0.00654 | AH16: 0.00742 | AI16: 0.00756 | AJ16: 0.00755 | AK16: 0.0085 | AL16: =+SUM(AL17:AL22) -> 0.0089 | AM16: =+SUM(AM17:AM22) -> 0.00985 | AN16: =+SUM(AN17:AN22) -> 0.0084 | AO16: =+SUM(AO17:AO22) -> 0.00778 | BA16: =IFERROR(AVERAGE(D16:O16),"-") -> 0.015583333 | BB16: =IFERROR(AVERAGE(P16:AA16),"-") -> 0.00975 | BC16: =IFERROR(SUMIFS(AB16:AM16,AB16:AM16,"<>0",AB16:AM16,"<>-",AB16:AM16,"<>",AB16:AM16,"<> ")/COUNTIFS(AB16:AM16,"<>0",AB16:AM16,"<>-",AB16:AM16,"<>",AB16:AM16,"<> "),"-") -> 0.007585
B17: FORMAX OPERACIÓN | C17: % | D17: 0.01 | E17: 0.01 | F17: 0.01 | G17: 0.01 | H17: 0.01 | I17: 0.009 | J17: 0.01 | K17: 0.011 | L17: 0.011 | M17: 0.011 | N17: 0.01 | O17: 0.01 | P17: 0.012 | Q17: 0.014 | R17: 0.012 | S17: 0.01 | T17: 0.005 | U17: 0.006 | V17: 0.005 | W17: 0.003 | X17: 0.004 | Y17: 0.005 | Z17: 0.005 | AA17: 0.005 | AB17: 0.006 | AC17: 0.006 | AD17: 0.00596 | AE17: 0.0055 | AF17: 0.00556 | AG17: 0.00498 | AH17: 0.00548 | AI17: 0.00487 | AJ17: 0.0055 | AK17: 0.00412 | AL17: 0.00563 | AM17: 0.00581 | AN17: 0.00506 | AO17: 0.0045 | BA17: =IFERROR(AVERAGE(D17:O17),"-") -> 0.010166667 | BB17: =IFERROR(AVERAGE(P17:AA17),"-") -> 0.0071666667 | BC17: =IFERROR(SUMIFS(AB17:AM17,AB17:AM17,"<>0",AB17:AM17,"<>-",AB17:AM17,"<>",AB17:AM17,"<> ")/COUNTIFS(AB17:AM17,"<>0",AB17:AM17,"<>-",AB17:AM17,"<>",AB17:AM17,"<> "),"-") -> 0.0054508333
B18: DURO | C18: % | D18: 0 | E18: 0.005 | F18: 0.005 | G18: 0.003 | H18: 0.002 | I18: 0.001 | J18: 0.002 | K18: 0.002 | L18: 0.003 | M18: 0.002 | N18: 0.005 | O18: 0.007 | P18: 0.002 | Q18: 0.003 | R18: 0.003 | S18: 0.002 | T18: 0.001 | U18: 0.001 | V18: 0 | W18: 0 | X18: 0 | Y18: 0 | Z18: 0 | AA18: 0 | AB18: 0 | AC18: 0 | AD18: 0 | AE18: 0 | AF18: 0 | AG18: 0 | AH18: 0 | AI18: 0 | AJ18: 0 | AK18: 0 | AL18: 0 | AM18: 0 | AN18: 0 | AO18: 0 | BA18: =IFERROR(AVERAGE(D18:O18),"-") -> 0.0030833333 | BB18: =IFERROR(AVERAGE(P18:AA18),"-") -> 0.001 | BC18: =IFERROR(SUMIFS(AB18:AM18,AB18:AM18,"<>0",AB18:AM18,"<>-",AB18:AM18,"<>",AB18:AM18,"<> ")/COUNTIFS(AB18:AM18,"<>0",AB18:AM18,"<>-",AB18:AM18,"<>",AB18:AM18,"<> "),"-") -> -
B19: PISO | C19: % | D19: 0 | E19: 0.002 | F19: 0.002 | G19: 0.001 | H19: 0.001 | I19: 0.001 | J19: 0.001 | K19: 0.001 | L19: 0.001 | M19: 0.001 | N19: 0 | O19: 0 | P19: 0 | Q19: 0.001 | R19: 0 | S19: 0 | T19: 0 | U19: 0.001 | V19: 0 | W19: 0.001 | X19: 0 | Y19: 0.001 | Z19: 0 | AA19: 0.001 | AB19: 0 | AC19: 0.001 | AD19: 0.00052 | AE19: 0.00048 | AF19: 0.00065 | AG19: 0.00031 | AH19: 0.00083 | AI19: 0.00153 | AJ19: 0.00092 | AK19: 0.00074 | AL19: 0.00106 | AM19: 0.00091 | AN19: 0.00087 | AO19: 0.0008 | BA19: =IFERROR(AVERAGE(D19:O19),"-") -> 0.00091666667 | BB19: =IFERROR(AVERAGE(P19:AA19),"-") -> 0.00041666667 | BC19: =IFERROR(SUMIFS(AB19:AM19,AB19:AM19,"<>0",AB19:AM19,"<>-",AB19:AM19,"<>",AB19:AM19,"<> ")/COUNTIFS(AB19:AM19,"<>0",AB19:AM19,"<>-",AB19:AM19,"<>",AB19:AM19,"<> "),"-") -> 0.00081363636
B20: BARRIDO HIGIENE | C20: % | D20: 0 | E20: 0.001 | F20: 0.001 | G20: 0.001 | H20: 0.001 | I20: 0.001 | J20: 0.001 | K20: 0.001 | L20: 0.001 | M20: 0.001 | N20: 0.001 | O20: 0.001 | P20: 0.001 | Q20: 0.001 | R20: 0.001 | S20: 0.001 | T20: 0.001 | U20: 0.001 | V20: 0 | W20: 0.001 | X20: 0.001 | Y20: 0.001 | Z20: 0.001 | AA20: 0.001 | AB20: 0.001 | AC20: 0.001 | AD20: 0.00075 | AE20: 0.00076 | AF20: 0.0007 | AG20: 0.00076 | AH20: 0.00079 | AI20: 0.00106 | AJ20: 0.00098 | AK20: 0.00106 | AL20: 0.00106 | AM20: 0.00104 | AN20: 0.00105 | AO20: 0.00122 | BA20: =IFERROR(AVERAGE(D20:O20),"-") -> 0.00091666667 | BB20: =IFERROR(AVERAGE(P20:AA20),"-") -> 0.00091666667 | BC20: =IFERROR(SUMIFS(AB20:AM20,AB20:AM20,"<>0",AB20:AM20,"<>-",AB20:AM20,"<>",AB20:AM20,"<> ")/COUNTIFS(AB20:AM20,"<>0",AB20:AM20,"<>-",AB20:AM20,"<>",AB20:AM20,"<> "),"-") -> 0.00091333333
B21: SOJA | C21: % | D21: 0 | E21: 0.001 | F21: 0.001 | G21: 0.001 | H21: 0.001 | I21: 0.002 | J21: 0.001 | K21: 0.001 | L21: 0.001 | M21: 0.002 | N21: 0 | O21: 0 | P21: 0.001 | Q21: 0.001 | R21: 0 | S21: 0 | T21: 0.001 | U21: 0 | V21: 0 | W21: 0 | X21: 0 | Y21: 0 | Z21: 0 | AA21: 0 | AB21: 0 | AC21: 0 | AD21: 0.0001 | AE21: 7e-05 | AF21: 3e-05 | AG21: 8e-05 | AH21: 0.00032 | AI21: 0.00011 | AJ21: 0.00013 | AK21: 7e-05 | AL21: 0.00022 | AM21: 0.00012 | AN21: 0.00036 | AO21: 0.00012 | BA21: =IFERROR(AVERAGE(D21:O21),"-") -> 0.00091666667 | BB21: =IFERROR(AVERAGE(P21:AA21),"-") -> 0.00025 | BC21: =IFERROR(SUMIFS(AB21:AM21,AB21:AM21,"<>0",AB21:AM21,"<>-",AB21:AM21,"<>",AB21:AM21,"<> ")/COUNTIFS(AB21:AM21,"<>0",AB21:AM21,"<>-",AB21:AM21,"<>",AB21:AM21,"<> "),"-") -> 0.000125
B22: OTRO | C22: % | D22: - | E22: - | F22: - | G22: - | H22: - | I22: - | J22: - | K22: - | L22: - | M22: - | N22: - | O22: - | P22: - | Q22: - | R22: - | S22: - | T22: 0.004 | U22: - | V22: - | W22: - | X22: - | Y22: - | Z22: - | AA22: - | AB22: 0.1% | AC22: - | AD22: - | AE22: - | AF22: - | AG22: - | AH22: - | AI22: - | AJ22: 1e-05 | AK22: 0.00251 | AL22: 0.00093 | AM22: 0.00197 | AN22: 0.00106 | AO22: 0.00114 | BA22: =IFERROR(AVERAGE(D22:O22),"-") -> - | BB22: =IFERROR(AVERAGE(P22:AA22),"-") -> 0.004 | BC22: =IFERROR(SUMIFS(AB22:AM22,AB22:AM22,"<>0",AB22:AM22,"<>-",AB22:AM22,"<>",AB22:AM22,"<> ")/COUNTIFS(AB22:AM22,"<>0",AB22:AM22,"<>-",AB22:AM22,"<>",AB22:AM22,"<> "),"-") -> 0.001084
B23: DESVÍO COSTO STD VS REAL - SIN REP | C23: % | D23: - | E23: - | F23: - | G23: - | H23: - | I23: - | J23: - | K23: - | L23: - | M23: - | N23: - | O23: - | S23: 0.019 | T23: 0.004 | U23: 0.018 | V23: 0.011 | W23: 0.03 | X23: 0.048 | Y23: 0.064 | Z23: 0.069 | AA23: 0.033 | AB23: 0.038 | AC23: 0.029 | AD23: 0.028 | AE23: -0.002 | AF23: 0.013 | AG23: 0.01 | AH23: -0.009 | AI23: -0.01 | AJ23: 0.052 | AK23: 0.036 | AL23: 0.027 | AM23: 0.023 | AN23: 0.006 | AO23: -0.016 | BA23: =IFERROR(AVERAGE(D23:O23),"-") -> - | BB23: =IFERROR(AVERAGE(P23:AA23),"-") -> 0.032888889 | BC23: =IFERROR(SUMIFS(AB23:AM23,AB23:AM23,"<>0",AB23:AM23,"<>-",AB23:AM23,"<>",AB23:AM23,"<> ")/COUNTIFS(AB23:AM23,"<>0",AB23:AM23,"<>-",AB23:AM23,"<>",AB23:AM23,"<> "),"-") -> 0.019583333
B24: DESVÍO COSTO STD VS REAL - SIN REP | C24: MILL | D24: - | E24: - | F24: - | G24: - | H24: - | I24: - | J24: - | K24: - | L24: - | M24: - | N24: - | O24: - | S24: 33.17 | T24: 8.06 | U24: 32.29 | V24: 23.74 | W24: 75.57 | X24: 129.09 | Y24: 204.13 | Z24: 234.88 | AA24: 121.72 | AB24: 143.61 | AC24: 114.05 | AD24: 111.52 | AE24: -7.41 | AF24: 51.75 | AG24: 36.376 | AH24: -41.693 | AI24: -37.929 | AJ24: 229.319 | AK24: 177.918 | AL24: 136.571 | AM24: 142.38064 | AN24: 36.638508 | AO24: -92.70639 | BA24: =IFERROR(AVERAGE(D24:O24),"-") -> - | BB24: =IFERROR(AVERAGE(P24:AA24),"-") -> 95.85 | BC24: =IFERROR(SUMIFS(AB24:AM24,AB24:AM24,"<>0",AB24:AM24,"<>-",AB24:AM24,"<>",AB24:AM24,"<> ")/COUNTIFS(AB24:AM24,"<>0",AB24:AM24,"<>-",AB24:AM24,"<>",AB24:AM24,"<> "),"-") -> 88.038554
B25: DESVÍO COSTO STD VS REAL - CON REP | C25: % | D25: - | E25: - | F25: - | G25: - | H25: - | I25: - | J25: - | K25: - | L25: - | M25: - | N25: - | O25: - | P25: 0.07 | Q25: 0.035 | R25: 0.06 | S25: 0.051 | T25: 0.029 | U25: 0.023 | V25: 0.014 | W25: 0.032 | X25: 0.052 | Y25: 0.07 | Z25: 0.073 | AA25: 0.035 | AB25: 0.039 | AC25: 0.031 | AD25: 0.03 | AE25: -0.001 | AF25: 0.016 | AG25: 0.016 | AH25: 0 | AI25: 0.013 | AJ25: 0.06 | AK25: 0.04 | AL25: 0.036 | AM25: 0.022 | AN25: 0.01 | AO25: -0.005 | BA25: =IFERROR(AVERAGE(D25:O25),"-") -> - | BB25: =IFERROR(AVERAGE(P25:AA25),"-") -> 0.045333333 | BC25: =IFERROR(SUMIFS(AB25:AM25,AB25:AM25,"<>0",AB25:AM25,"<>-",AB25:AM25,"<>",AB25:AM25,"<> ")/COUNTIFS(AB25:AM25,"<>0",AB25:AM25,"<>-",AB25:AM25,"<>",AB25:AM25,"<> "),"-") -> 0.027454545
B26: DESVÍO COSTO STD VS REAL - CON REP | C26: MILL | D26: - | E26: - | F26: - | G26: - | H26: - | I26: - | J26: - | K26: - | L26: - | M26: - | N26: - | O26: - | P26: 138.98 | Q26: 61.14 | R26: 100.2 | S26: 92.16 | T26: 54.54 | U26: 41.63 | V26: 32.12 | W26: 79.38 | X26: 138.99 | Y26: 224.09 | Z26: 247.78 | AA26: 128.75 | AB26: 148.11 | AC26: 124.63 | AD26: 126.92 | AE26: -3.51 | AF26: 62.03 | AG26: 56.835 | AH26: 0.762335 | AI26: 49.221 | AJ26: 260.723 | AK26: 196.9 | AL26: 183.329 | AM26: 135.9646 | AN26: 61.89194 | AO26: -31.568728 | BA26: =IFERROR(AVERAGE(D26:O26),"-") -> - | BB26: =IFERROR(AVERAGE(P26:AA26),"-") -> 111.64667 | BC26: =IFERROR(SUMIFS(AB26:AM26,AB26:AM26,"<>0",AB26:AM26,"<>-",AB26:AM26,"<>",AB26:AM26,"<> ")/COUNTIFS(AB26:AM26,"<>0",AB26:AM26,"<>-",AB26:AM26,"<>",AB26:AM26,"<> "),"-") -> 111.82624
B27: COSTO PRODUCCIÓN POR KG | C27: $ | AG27: 4428.73 | AH27: 4290.93 | AI27: 4822.09 | AJ27: 5128.77 | AK27: 5383 | AL27: 5555.75 | AM27: 6209.8565 | AN27: 6327.68 | AO27: 6135.5
B28: CONSUMO CARNE POR KG | C28: $ | AG28: 4038.63 | AH28: 3884.73 | AI28: 4375.53 | AJ28: 4723.68 | AK28: 4960.1 | AL28: 5107.69 | AM28: 5836.2225 | AN28: 5918.98 | AO28: 5686.16
B29: CONSUMO ADITIVOS POR KG | C29: $ | AG29: 108.62 | AH29: 103.18 | AI29: 95.39 | AJ29: 113.44 | AK29: 124.11 | AL29: 122.12 | AM29: 109.54415 | AN29: 113.94 | AO29: 108.3
B30: CONSUMOS EMBALAJE POR KG | C30: $ | AG30: 255.13 | AH30: 267.63 | AI30: 256.79 | AJ30: 272.25 | AK30: 276.28 | AL30: 274.63 | AM30: 267.75448 | AN30: 265.44 | AO30: 274.12
B31: CONSUMO HIELO POR KG S, TH Y J | C31: $ | AG31: 26.2 | AH31: 35.5 | AI31: 34.41 | AJ31: 32.88 | AK31: 27.88 | AL31: 26.76 | AM31: 26.099609 | AN31: 23.68 | AO31: 29.2
B32: CONSUMO REPROCESO POR KG | C32: $ | AG32: 185.05 | AH32: 301.84 | AI32: 934.57 | AJ32: 154.68 | AK32: 133.34 | AL32: 315.54 | AM32: -36.637227 | AN32: 159.41 | AO32: 483.24
B33: CONSUMO REENVASADO POR KG DE REENVASADO | C33: $ | AG33: 400.35 | AH33: 377.8 | AI33: 384.69 | AJ33: 360.65 | AK33: 305.42 | AL33: 433.43 | AM33: 357.01957 | AN33: 395.02 | AO33: 385.66
B34: DESVÍO INGRESO A PICADORA | C34: UNI | D34: 0.02 | E34: 0.013 | F34: 0.015 | G34: 0.017 | H34: 0.013 | I34: 0.014 | J34: 0.045 | K34: 0.031 | L34: 0.031 | M34: 0.016 | N34: 0.012 | O34: 0.013 | P34: 0.015 | Q34: 0.026 | R34: 0.028 | S34: 0.006 | T34: 0.013 | U34: 0.005 | V34: 0.008 | W34: 0.013 | X34: 0.02 | Y34: 0.033 | Z34: 0.022 | AA34: - | AB34: - | AC34: - | AD34: 180 | AE34: 173 | AF34: 280 | AG34: 27 | AH34: =172+48 -> 220 | AI34: 9 | AJ34: 96 | AK34: 40 | AL34: 19 | AM34: 101 | AN34: 50 | BA34: =IFERROR(AVERAGE(D34:O34),"-") -> 0.02 | BB34: =IFERROR(AVERAGE(P34:AA34),"-") -> 0.017181818 | BC34: =IFERROR(SUMIFS(AB34:AM34,AB34:AM34,"<>0",AB34:AM34,"<>-",AB34:AM34,"<>",AB34:AM34,"<> ")/COUNTIFS(AB34:AM34,"<>0",AB34:AM34,"<>-",AB34:AM34,"<>",AB34:AM34,"<> "),"-") -> 114.5
B35: ELIMINADOS | C35: % | D35: 0.01 | E35: 0.004 | F35: 0.004 | G35: 0.004 | H35: 0.005 | I35: 0.004 | J35: 0.005 | K35: 0.003 | L35: 0.003 | M35: 0.006 | N35: 0.004 | O35: 0.003 | P35: 0.003 | Q35: 0.003 | R35: 0.005 | S35: 0.002 | T35: 0.002 | U35: 0.002 | V35: 0.002 | W35: 0.002 | X35: 0.002 | Y35: 0.005 | Z35: 0.003 | AA35: 0.004 | AB35: 0.002 | AC35: 0.001 | AD35: 0.003 | AE35: 0.0022 | AF35: 0.0019 | AG35: 0.0027 | AH35: 0.0023 | AI35: 0.0016 | AJ35: 0.0025 | AK35: 0.0015 | AL35: 0.0024 | AM35: 0.00257 | AN35: 0.0025 | BA35: =IFERROR(AVERAGE(D35:O35),"-") -> 0.0045833333 | BB35: =IFERROR(AVERAGE(P35:AA35),"-") -> 0.0029166667 | BC35: =IFERROR(SUMIFS(AB35:AM35,AB35:AM35,"<>0",AB35:AM35,"<>-",AB35:AM35,"<>",AB35:AM35,"<> ")/COUNTIFS(AB35:AM35,"<>0",AB35:AM35,"<>-",AB35:AM35,"<>",AB35:AM35,"<> "),"-") -> 0.0021391667
B36: ETIQUETAS TOTALES | C36: UNI | P36: - | Q36: - | R36: - | S36: 2.56 | T36: 266 | U36: 315 | V36: 240 | W36: 309 | X36: 307 | Y36: 946 | Z36: 503 | AA36: 724 | AB36: 395 | AC36: 356 | AD36: 347 | AE36: 385 | AF36: 410 | AG36: 367 | AH36: 447 | AI36: 286 | AJ36: 418 | AK36: 295 | AL36: 389 | AM36: 531 | AN36: 537 | BA36: =IFERROR(AVERAGE(D36:O36),"-") -> - | BB36: =IFERROR(AVERAGE(P36:AA36),"-") -> 451.25 | BC36: =IFERROR(SUMIFS(AB36:AM36,AB36:AM36,"<>0",AB36:AM36,"<>-",AB36:AM36,"<>",AB36:AM36,"<> ")/COUNTIFS(AB36:AM36,"<>0",AB36:AM36,"<>-",AB36:AM36,"<>",AB36:AM36,"<> "),"-") -> 385.5
B37: ETIQUETAS REENVASADO | AB37: 42 | AC37: 47 | AD37: 18 | AE37: 64 | AF37: 65 | AG37: 16 | AH37: 44 | AI37: 5 | AJ37: 18 | AK37: 30 | AL37: 60 | AM37: 12 | AN37: 533 | BA37: =IFERROR(AVERAGE(D37:O37),"-") -> - | BB37: =IFERROR(AVERAGE(P37:AA37),"-") -> - | BC37: =IFERROR(SUMIFS(AB37:AM37,AB37:AM37,"<>0",AB37:AM37,"<>-",AB37:AM37,"<>",AB37:AM37,"<> ")/COUNTIFS(AB37:AM37,"<>0",AB37:AM37,"<>-",AB37:AM37,"<>",AB37:AM37,"<> "),"-") -> 35.083333
B38: ETIQUETAS H1 | AB38: 353 | AC38: 309 | AD38: 329 | AE38: 321 | AF38: 345 | AG38: 351 | AH38: 403 | AI38: 281 | AJ38: 400 | AK38: 265 | AL38: 329 | AM38: 519 | AN38: 4 | BA38: =IFERROR(AVERAGE(D38:O38),"-") -> - | BB38: =IFERROR(AVERAGE(P38:AA38),"-") -> - | BC38: =IFERROR(SUMIFS(AB38:AM38,AB38:AM38,"<>0",AB38:AM38,"<>-",AB38:AM38,"<>",AB38:AM38,"<> ")/COUNTIFS(AB38:AM38,"<>0",AB38:AM38,"<>-",AB38:AM38,"<>",AB38:AM38,"<> "),"-") -> 350.41667
B39: ETIQUETAS FISICAS/ JUSTIFICADAS | C39: UNI | P39: - | Q39: - | R39: - | S39: 116 | T39: 127 | U39: 186 | V39: 108 | W39: 147 | X39: 123 | Y39: 633 | Z39: 295 | AA39: 396 | AB39: 215 | AC39: - | AD39: - | AE39: - | AF39: - | AG39: - | AH39: 107 | AI39: - | AJ39: 170 | AK39: 16 | BA39: =IFERROR(AVERAGE(D39:O39),"-") -> - | BB39: =IFERROR(AVERAGE(P39:AA39),"-") -> 236.77778 | BC39: =IFERROR(SUMIFS(AB39:AM39,AB39:AM39,"<>0",AB39:AM39,"<>-",AB39:AM39,"<>",AB39:AM39,"<> ")/COUNTIFS(AB39:AM39,"<>0",AB39:AM39,"<>-",AB39:AM39,"<>",AB39:AM39,"<> "),"-") -> 84.666667
B40: REPROCESO - REPCAM | C40: KG | D40: 8154 | E40: 3402 | F40: 8517 | G40: 5136 | H40: 5745 | I40: 1141 | J40: 1677 | K40: 1061 | L40: 2965 | M40: 579 | N40: 2083 | O40: 2288 | P40: 794 | Q40: 1366 | R40: 2992 | S40: 5762 | T40: 8015 | U40: 1696 | V40: 2559 | W40: 1708 | X40: 3632 | Y40: 2.52 | Z40: 1489 | AA40: 2418 | AB40: 1015 | AG40: 10919.76 | AH40: 9135 | AI40: 16808 | AJ40: 4566 | AK40: 4640 | AL40: 6630 | AM40: 3022 | BA40: =IFERROR(AVERAGE(D40:O40),"-") -> 3562.3333 | BB40: =IFERROR(AVERAGE(P40:AA40),"-") -> 2948.2727 | BC40: =IFERROR(SUMIFS(AB40:AM40,AB40:AM40,"<>0",AB40:AM40,"<>-",AB40:AM40,"<>",AB40:AM40,"<> ")/COUNTIFS(AB40:AM40,"<>0",AB40:AM40,"<>-",AB40:AM40,"<>",AB40:AM40,"<> "),"-") -> 4727.98
B41: REPROCESO LEIDO | C41: KG | P41: - | Q41: - | R41: - | S41: - | T41: 4617 | U41: 1696 | V41: 2502 | W41: 1708 | X41: 82 | Y41: 2298 | Z41: 1489 | AA41: 2418 | AB41: 1015 | AG41: 5094.35 | AH41: 3638.83 | BA41: - | BB41: - | BC41: =IFERROR(SUMIFS(AB41:AM41,AB41:AM41,"<>0",AB41:AM41,"<>-",AB41:AM41,"<>",AB41:AM41,"<> ")/COUNTIFS(AB41:AM41,"<>0",AB41:AM41,"<>-",AB41:AM41,"<>",AB41:AM41,"<> "),"-") -> 1392.5971
B42: REPROCESO ESTADO E | C42: KG | P42: - | Q42: - | R42: - | S42: - | T42: 3398 | U42: - | V42: 57 | W42: - | X42: - | Y42: - | AB42: - | AG42: 0 | AH42: 0 | BA42: - | BB42: - | BC42: =IFERROR(SUMIFS(AB42:AM42,AB42:AM42,"<>0",AB42:AM42,"<>-",AB42:AM42,"<>",AB42:AM42,"<> ")/COUNTIFS(AB42:AM42,"<>0",AB42:AM42,"<>-",AB42:AM42,"<>",AB42:AM42,"<> "),"-") -> 0
B43: REPROCESO PV | C43: KG | P43: - | Q43: - | R43: - | S43: - | T43: - | U43: - | V43: - | W43: - | X43: 3.55 | Y43: 222 | AG43: 0 | AH43: 0 | BA43: - | BB43: - | BC43: =IFERROR(SUMIFS(AB43:AM43,AB43:AM43,"<>0",AB43:AM43,"<>-",AB43:AM43,"<>",AB43:AM43,"<> ")/COUNTIFS(AB43:AM43,"<>0",AB43:AM43,"<>-",AB43:AM43,"<>",AB43:AM43,"<> "),"-") -> 0
B44: MIN PERDIDOS PROM POR DÍA (SEGÚN HORARIO) | C44: MIN | AB44: =IFERROR((SUMIFS('TABLERO DIARIO'!#REF!,'TABLERO DIARIO'!$I$2:$ZZ$2,">="&DATE(2025,MONTH(AB$2),1),'TABLERO DIARIO'!$I$2:$ZZ$2,"<="&EOMONTH(AB$2,0))/COUNTIFS('TABLERO DIARIO'!$I$2:$ZZ$2,">="&DATE(2025,MONTH(AB$2),1),'TABLERO DIARIO'!$I$2:$ZZ$2,"<="&EOMONTH(AB$2,0),'TABLERO DIARIO'!#REF!,"<>0",'TABLERO DIARIO'!#REF!,"<>-",'TABLERO DIARIO'!#REF!,"<>")),"-") -> - | AC44: =IFERROR((SUMIFS('TABLERO DIARIO'!#REF!,'TABLERO DIARIO'!$I$2:$ZZ$2,">="&DATE(2025,MONTH(AC$2),1),'TABLERO DIARIO'!$I$2:$ZZ$2,"<="&EOMONTH(AC$2,0))/COUNTIFS('TABLERO DIARIO'!$I$2:$ZZ$2,">="&DATE(2025,MONTH(AC$2),1),'TABLERO DIARIO'!$I$2:$ZZ$2,"<="&EOMONTH(AC$2,0),'TABLERO DIARIO'!#REF!,"<>0",'TABLERO DIARIO'!#REF!,"<>-",'TABLERO DIARIO'!#REF!,"<>")),"-") -> - | AD44: =IFERROR((SUMIFS('TABLERO DIARIO'!#REF!,'TABLERO DIARIO'!$I$2:$ZZ$2,">="&DATE(2025,MONTH(AD$2),1),'TABLERO DIARIO'!$I$2:$ZZ$2,"<="&EOMONTH(AD$2,0))/COUNTIFS('TABLERO DIARIO'!$I$2:$ZZ$2,">="&DATE(2025,MONTH(AD$2),1),'TABLERO DIARIO'!$I$2:$ZZ$2,"<="&EOMONTH(AD$2,0),'TABLERO DIARIO'!#REF!,"<>0",'TABLERO DIARIO'!#REF!,"<>-",'TABLERO DIARIO'!#REF!,"<>")),"-") -> - | AE44: =IFERROR((SUMIFS('TABLERO DIARIO'!#REF!,'TABLERO DIARIO'!$I$2:$ZZ$2,">="&DATE(2025,MONTH(AE$2),1),'TABLERO DIARIO'!$I$2:$ZZ$2,"<="&EOMONTH(AE$2,0))/COUNTIFS('TABLERO DIARIO'!$I$2:$ZZ$2,">="&DATE(2025,MONTH(AE$2),1),'TABLERO DIARIO'!$I$2:$ZZ$2,"<="&EOMONTH(AE$2,0),'TABLERO DIARIO'!#REF!,"<>0",'TABLERO DIARIO'!#REF!,"<>-",'TABLERO DIARIO'!#REF!,"<>")),"-") -> - | AF44: =IFERROR((SUMIFS('TABLERO DIARIO'!#REF!,'TABLERO DIARIO'!$I$2:$ZZ$2,">="&DATE(2025,MONTH(AF$2),1),'TABLERO DIARIO'!$I$2:$ZZ$2,"<="&EOMONTH(AF$2,0))/COUNTIFS('TABLERO DIARIO'!$I$2:$ZZ$2,">="&DATE(2025,MONTH(AF$2),1),'TABLERO DIARIO'!$I$2:$ZZ$2,"<="&EOMONTH(AF$2,0),'TABLERO DIARIO'!#REF!,"<>0",'TABLERO DIARIO'!#REF!,"<>-",'TABLERO DIARIO'!#REF!,"<>")),"-") -> - | AG44: =IFERROR((SUMIFS('TABLERO DIARIO'!#REF!,'TABLERO DIARIO'!$I$2:$ZZ$2,">="&DATE(2025,MONTH(AG$2),1),'TABLERO DIARIO'!$I$2:$ZZ$2,"<="&EOMONTH(AG$2,0))/COUNTIFS('TABLERO DIARIO'!$I$2:$ZZ$2,">="&DATE(2025,MONTH(AG$2),1),'TABLERO DIARIO'!$I$2:$ZZ$2,"<="&EOMONTH(AG$2,0),'TABLERO DIARIO'!#REF!,"<>0",'TABLERO DIARIO'!#REF!,"<>-",'TABLERO DIARIO'!#REF!,"<>")),"-") -> - | AH44: =IFERROR((SUMIFS('TABLERO DIARIO'!#REF!,'TABLERO DIARIO'!$I$2:$ZZ$2,">="&DATE(2025,MONTH(AH$2),1),'TABLERO DIARIO'!$I$2:$ZZ$2,"<="&EOMONTH(AH$2,0))/COUNTIFS('TABLERO DIARIO'!$I$2:$ZZ$2,">="&DATE(2025,MONTH(AH$2),1),'TABLERO DIARIO'!$I$2:$ZZ$2,"<="&EOMONTH(AH$2,0),'TABLERO DIARIO'!#REF!,"<>0",'TABLERO DIARIO'!#REF!,"<>-",'TABLERO DIARIO'!#REF!,"<>")),"-") -> - | AI44: =IFERROR((SUMIFS('TABLERO DIARIO'!#REF!,'TABLERO DIARIO'!$I$2:$ZZ$2,">="&DATE(2025,MONTH(AI$2),1),'TABLERO DIARIO'!$I$2:$ZZ$2,"<="&EOMONTH(AI$2,0))/COUNTIFS('TABLERO DIARIO'!$I$2:$ZZ$2,">="&DATE(2025,MONTH(AI$2),1),'TABLERO DIARIO'!$I$2:$ZZ$2,"<="&EOMONTH(AI$2,0),'TABLERO DIARIO'!#REF!,"<>0",'TABLERO DIARIO'!#REF!,"<>-",'TABLERO DIARIO'!#REF!,"<>")),"-") -> - | AJ44: =IFERROR((SUMIFS('TABLERO DIARIO'!#REF!,'TABLERO DIARIO'!$I$2:$ABL$2,">="&DATE(2025,MONTH(AJ$2),1),'TABLERO DIARIO'!$I$2:$ABL$2,"<="&EOMONTH(AJ$2,0))/COUNTIFS('TABLERO DIARIO'!$I$2:$ABL$2,">="&DATE(2025,MONTH(AJ$2),1),'TABLERO DIARIO'!$I$2:$ABL$2,"<="&EOMONTH(AJ$2,0),'TABLERO DIARIO'!#REF!,"<>0",'TABLERO DIARIO'!#REF!,"<>-",'TABLERO DIARIO'!#REF!,"<>")),"-") -> - | AK44: =IFERROR((SUMIFS('TABLERO DIARIO'!#REF!,'TABLERO DIARIO'!$I$2:$AEV$2,">="&DATE(2025,MONTH(AK$2),1),'TABLERO DIARIO'!$I$2:$AEV$2,"<="&EOMONTH(AK$2,0))/COUNTIFS('TABLERO DIARIO'!$I$2:$AEV$2,">="&DATE(2025,MONTH(AK$2),1),'TABLERO DIARIO'!$I$2:$AEV$2,"<="&EOMONTH(AK$2,0),'TABLERO DIARIO'!#REF!,"<>0",'TABLERO DIARIO'!#REF!,"<>-",'TABLERO DIARIO'!#REF!,"<>")),"-") -> - | AL44: =IFERROR((SUMIFS('TABLERO DIARIO'!#REF!,'TABLERO DIARIO'!$AEA$2:$AII$2,">="&DATE(2025,MONTH(AL$2),1),'TABLERO DIARIO'!$AEA$2:$AII$2,"<="&EOMONTH(AL$2,0))/COUNTIFS('TABLERO DIARIO'!$AEA$2:$AII$2,">="&DATE(2025,MONTH(AL$2),1),'TABLERO DIARIO'!$AEA$2:$AII$2,"<="&EOMONTH(AL$2,0),'TABLERO DIARIO'!#REF!,"<>0",'TABLERO DIARIO'!#REF!,"<>-",'TABLERO DIARIO'!#REF!,"<>")),"-") -> - | AM44: =IFERROR((SUMIFS('TABLERO DIARIO'!#REF!,'TABLERO DIARIO'!$AEA$2:$AMC$2,">="&DATE(2025,MONTH(AM$2),1),'TABLERO DIARIO'!$AEA$2:$AMC$2,"<="&EOMONTH(AM$2,0))/COUNTIFS('TABLERO DIARIO'!$AEA$2:$AMC$2,">="&DATE(2025,MONTH(AM$2),1),'TABLERO DIARIO'!$AEA$2:$AMC$2,"<="&EOMONTH(AM$2,0),'TABLERO DIARIO'!#REF!,"<>0",'TABLERO DIARIO'!#REF!,"<>-",'TABLERO DIARIO'!#REF!,"<>")),"-") -> - | AN44: =IFERROR((SUMIFS('TABLERO DIARIO'!#REF!,'TABLERO DIARIO'!$ALW$2:$ASW$2,">="&DATE(2026,MONTH(AN$2),1),'TABLERO DIARIO'!$ALW$2:$ASW$2,"<="&EOMONTH(AN$2,0))/COUNTIFS('TABLERO DIARIO'!$ALW$2:$ASW$2,">="&DATE(2026,MONTH(AN$2),1),'TABLERO DIARIO'!$ALW$2:$ASW$2,"<="&EOMONTH(AN$2,0),'TABLERO DIARIO'!#REF!,"<>0",'TABLERO DIARIO'!#REF!,"<>-",'TABLERO DIARIO'!#REF!,"<>")),"-") -> - | AO44: =IFERROR((SUMIFS('TABLERO DIARIO'!#REF!,'TABLERO DIARIO'!$ALW$2:$ASW$2,">="&DATE(2026,MONTH(AO$2),1),'TABLERO DIARIO'!$ALW$2:$ASW$2,"<="&EOMONTH(AO$2,0))/COUNTIFS('TABLERO DIARIO'!$ALW$2:$ASW$2,">="&DATE(2026,MONTH(AO$2),1),'TABLERO DIARIO'!$ALW$2:$ASW$2,"<="&EOMONTH(AO$2,0),'TABLERO DIARIO'!#REF!,"<>0",'TABLERO DIARIO'!#REF!,"<>-",'TABLERO DIARIO'!#REF!,"<>")),"-") -> - | BA44: =IFERROR(AVERAGE(D44:O44),"-") -> - | BB44: =IFERROR(AVERAGE(P44:AA44),"-") -> - | BC44: =IFERROR(SUMIFS(AB44:AM44,AB44:AM44,"<>0",AB44:AM44,"<>-",AB44:AM44,"<>",AB44:AM44,"<> ")/COUNTIFS(AB44:AM44,"<>0",AB44:AM44,"<>-",AB44:AM44,"<>",AB44:AM44,"<> "),"-") -> -
B45: MIN FORMAX FRENADA TOTAL MES | C45: MIN | AB45: =IF((SUMIFS('TABLERO DIARIO'!#REF!,'TABLERO DIARIO'!$I$2:$ZZ$2,">="&DATE(2025,MONTH(AB$2),1),'TABLERO DIARIO'!$I$2:$ZZ$2,"<="&EOMONTH(AB$2,0)))=0,"-",SUMIFS('TABLERO DIARIO'!#REF!,'TABLERO DIARIO'!$I$2:$ZZ$2,">="&DATE(2025,MONTH(AB$2),1),'TABLERO DIARIO'!$I$2:$ZZ$2,"<="&EOMONTH(AB$2,0))) -> #REF! | AC45: =IF((SUMIFS('TABLERO DIARIO'!#REF!,'TABLERO DIARIO'!$I$2:$ZZ$2,">="&DATE(2025,MONTH(AC$2),1),'TABLERO DIARIO'!$I$2:$ZZ$2,"<="&EOMONTH(AC$2,0)))=0,"-",SUMIFS('TABLERO DIARIO'!#REF!,'TABLERO DIARIO'!$I$2:$ZZ$2,">="&DATE(2025,MONTH(AC$2),1),'TABLERO DIARIO'!$I$2:$ZZ$2,"<="&EOMONTH(AC$2,0))) -> #REF! | AD45: =IF((SUMIFS('TABLERO DIARIO'!#REF!,'TABLERO DIARIO'!$I$2:$ZZ$2,">="&DATE(2025,MONTH(AD$2),1),'TABLERO DIARIO'!$I$2:$ZZ$2,"<="&EOMONTH(AD$2,0)))=0,"-",SUMIFS('TABLERO DIARIO'!#REF!,'TABLERO DIARIO'!$I$2:$ZZ$2,">="&DATE(2025,MONTH(AD$2),1),'TABLERO DIARIO'!$I$2:$ZZ$2,"<="&EOMONTH(AD$2,0))) -> #REF! | AE45: =IF((SUMIFS('TABLERO DIARIO'!#REF!,'TABLERO DIARIO'!$I$2:$ZZ$2,">="&DATE(2025,MONTH(AE$2),1),'TABLERO DIARIO'!$I$2:$ZZ$2,"<="&EOMONTH(AE$2,0)))=0,"-",SUMIFS('TABLERO DIARIO'!#REF!,'TABLERO DIARIO'!$I$2:$ZZ$2,">="&DATE(2025,MONTH(AE$2),1),'TABLERO DIARIO'!$I$2:$ZZ$2,"<="&EOMONTH(AE$2,0))) -> #REF! | AF45: =IF((SUMIFS('TABLERO DIARIO'!#REF!,'TABLERO DIARIO'!$I$2:$ZZ$2,">="&DATE(2025,MONTH(AF$2),1),'TABLERO DIARIO'!$I$2:$ZZ$2,"<="&EOMONTH(AF$2,0)))=0,"-",SUMIFS('TABLERO DIARIO'!#REF!,'TABLERO DIARIO'!$I$2:$ZZ$2,">="&DATE(2025,MONTH(AF$2),1),'TABLERO DIARIO'!$I$2:$ZZ$2,"<="&EOMONTH(AF$2,0))) -> #REF! | AG45: =IF((SUMIFS('TABLERO DIARIO'!#REF!,'TABLERO DIARIO'!$I$2:$ZZ$2,">="&DATE(2025,MONTH(AG$2),1),'TABLERO DIARIO'!$I$2:$ZZ$2,"<="&EOMONTH(AG$2,0)))=0,"-",SUMIFS('TABLERO DIARIO'!#REF!,'TABLERO DIARIO'!$I$2:$ZZ$2,">="&DATE(2025,MONTH(AG$2),1),'TABLERO DIARIO'!$I$2:$ZZ$2,"<="&EOMONTH(AG$2,0))) -> #REF! | AH45: =IFERROR(SUMIFS('TABLERO DIARIO'!#REF!,'TABLERO DIARIO'!$I$2:$ZZ$2,">="&DATE(2025,MONTH(AH$2),1),'TABLERO DIARIO'!$I$2:$ZZ$2,"<="&EOMONTH(AH$2,0)),"-") -> - | AI45: =IF((SUMIFS('TABLERO DIARIO'!#REF!,'TABLERO DIARIO'!$I$2:$ZZ$2,">="&DATE(2025,MONTH(AI$2),1),'TABLERO DIARIO'!$I$2:$ZZ$2,"<="&EOMONTH(AI$2,0)))=0,"-",SUMIFS('TABLERO DIARIO'!#REF!,'TABLERO DIARIO'!$I$2:$ZZ$2,">="&DATE(2025,MONTH(AI$2),1),'TABLERO DIARIO'!$I$2:$ZZ$2,"<="&EOMONTH(AI$2,0))) -> #REF! | AJ45: =IF((SUMIFS('TABLERO DIARIO'!#REF!,'TABLERO DIARIO'!$I$2:$ABL$2,">="&DATE(2025,MONTH(AJ$2),1),'TABLERO DIARIO'!$I$2:$ABL$2,"<="&EOMONTH(AJ$2,0)))=0,"-",SUMIFS('TABLERO DIARIO'!#REF!,'TABLERO DIARIO'!$I$2:$ABL$2,">="&DATE(2025,MONTH(AJ$2),1),'TABLERO DIARIO'!$I$2:$ABL$2,"<="&EOMONTH(AJ$2,0))) -> #REF! | AK45: =IF((SUMIFS('TABLERO DIARIO'!#REF!,'TABLERO DIARIO'!$I$2:$AEV$2,">="&DATE(2025,MONTH(AK$2),1),'TABLERO DIARIO'!$I$2:$AEV$2,"<="&EOMONTH(AK$2,0)))=0,"-",SUMIFS('TABLERO DIARIO'!#REF!,'TABLERO DIARIO'!$I$2:$AEV$2,">="&DATE(2025,MONTH(AK$2),1),'TABLERO DIARIO'!$I$2:$AEV$2,"<="&EOMONTH(AK$2,0))) -> #REF! | AL45: =IF((SUMIFS('TABLERO DIARIO'!#REF!,'TABLERO DIARIO'!$AEA$2:$AII$2,">="&DATE(2025,MONTH(AL$2),1),'TABLERO DIARIO'!$AEA$2:$AII$2,"<="&EOMONTH(AL$2,0)))=0,"-",SUMIFS('TABLERO DIARIO'!#REF!,'TABLERO DIARIO'!$AEA$2:$AII$2,">="&DATE(2025,MONTH(AL$2),1),'TABLERO DIARIO'!$AEA$2:$AII$2,"<="&EOMONTH(AL$2,0))) -> #REF! | AM45: =IF((SUMIFS('TABLERO DIARIO'!#REF!,'TABLERO DIARIO'!$AEA$2:$AMC$2,">="&DATE(2025,MONTH(AM$2),1),'TABLERO DIARIO'!$AEA$2:$AMC$2,"<="&EOMONTH(AM$2,0)))=0,"-",SUMIFS('TABLERO DIARIO'!#REF!,'TABLERO DIARIO'!$AEA$2:$AMC$2,">="&DATE(2025,MONTH(AM$2),1),'TABLERO DIARIO'!$AEA$2:$AMC$2,"<="&EOMONTH(AM$2,0))) -> #REF! | AN45: =IF((SUMIFS('TABLERO DIARIO'!#REF!,'TABLERO DIARIO'!$ALW$2:$AWW$2,">="&DATE(2026,MONTH(AN$2),1),'TABLERO DIARIO'!$ALW$2:$AWW$2,"<="&EOMONTH(AN$2,0)))=0,"-",SUMIFS('TABLERO DIARIO'!#REF!,'TABLERO DIARIO'!$ALW$2:$AWW$2,">="&DATE(2026,MONTH(AN$2),1),'TABLERO DIARIO'!$ALW$2:$AWW$2,"<="&EOMONTH(AN$2,0))) -> #REF! | AO45: =IF((SUMIFS('TABLERO DIARIO'!#REF!,'TABLERO DIARIO'!$ALW$2:$AWW$2,">="&DATE(2026,MONTH(AO$2),1),'TABLERO DIARIO'!$ALW$2:$AWW$2,"<="&EOMONTH(AO$2,0)))=0,"-",SUMIFS('TABLERO DIARIO'!#REF!,'TABLERO DIARIO'!$ALW$2:$AWW$2,">="&DATE(2026,MONTH(AO$2),1),'TABLERO DIARIO'!$ALW$2:$AWW$2,"<="&EOMONTH(AO$2,0))) -> #REF! | BA45: =IFERROR(AVERAGE(D45:O45),"-") -> - | BB45: =IFERROR(AVERAGE(P45:AA45),"-") -> - | BC45: =IFERROR(SUMIFS(AB45:AM45,AB45:AM45,"<>0",AB45:AM45,"<>-",AB45:AM45,"<>",AB45:AM45,"<> ")/COUNTIFS(AB45:AM45,"<>0",AB45:AM45,"<>-",AB45:AM45,"<>",AB45:AM45,"<> "),"-") -> -
B46: PRE-OPERACIONALES | C46: % | D46: - | E46: - | F46: 0.96 | G46: 0.94 | H46: 0.96 | I46: 0.95 | J46: 0.95 | K46: 0.96 | L46: 0.97 | M46: 0.97 | N46: 0.98 | O46: 0.98 | P46: 0.98 | Q46: 0.98 | R46: 0.87 | S46: 0.9 | T46: 0.89 | U46: 0.91 | V46: 0.89 | W46: 0.92 | X46: 0.9 | Y46: 0.89 | Z46: 0.88 | AA46: 0.83 | AB46: 0.79 | AC46: 0.89 | AD46: 0.87 | AE46: 0.81 | AF46: 0.89 | AG46: 0.8961 | AH46: =SUMIFS('TABLERO DIARIO'!#REF!,'TABLERO DIARIO'!$F$2:$ZZ$2,">="&DATE(2025,MONTH(AH$2),1),'TABLERO DIARIO'!$F$2:$ZZ$2,"<="&EOMONTH(AH$2,0))/COUNTIFS('TABLERO DIARIO'!$F$2:$ZZ$2,">="&DATE(2025,MONTH(AH$2),1),'TABLERO DIARIO'!$F$2:$ZZ$2,"<="&EOMONTH(AH$2,0),'TABLERO DIARIO'!#REF!,"<>-") -> #REF! | AI46: =IFERROR(SUMIFS('TABLERO DIARIO'!#REF!,'TABLERO DIARIO'!$F$2:$ZZ$2,">="&DATE(2025,MONTH(AI$2),1),'TABLERO DIARIO'!$F$2:$ZZ$2,"<="&EOMONTH(AI$2,0))/COUNTIFS('TABLERO DIARIO'!$F$2:$ZZ$2,">="&DATE(2025,MONTH(AI$2),1),'TABLERO DIARIO'!$F$2:$ZZ$2,"<="&EOMONTH(AI$2,0),'TABLERO DIARIO'!#REF!,"<>-"),"-") -> - | AJ46: =IFERROR(SUMIFS('TABLERO DIARIO'!#REF!,'TABLERO DIARIO'!$F$2:$ABL$2,">="&DATE(2025,MONTH(AJ$2),1),'TABLERO DIARIO'!$F$2:$ABL$2,"<="&EOMONTH(AJ$2,0))/COUNTIFS('TABLERO DIARIO'!$F$2:$ABL$2,">="&DATE(2025,MONTH(AJ$2),1),'TABLERO DIARIO'!$F$2:$ABL$2,"<="&EOMONTH(AJ$2,0),'TABLERO DIARIO'!#REF!,"<>-"),"-") -> - | AK46: =IFERROR(SUMIFS('TABLERO DIARIO'!#REF!,'TABLERO DIARIO'!$F$2:$AEV$2,">="&DATE(2025,MONTH(AK$2),1),'TABLERO DIARIO'!$F$2:$AEV$2,"<="&EOMONTH(AK$2,0))/COUNTIFS('TABLERO DIARIO'!$F$2:$AEV$2,">="&DATE(2025,MONTH(AK$2),1),'TABLERO DIARIO'!$F$2:$AEV$2,"<="&EOMONTH(AK$2,0),'TABLERO DIARIO'!#REF!,"<>-"),"-") -> - | AL46: =IFERROR(SUMIFS('TABLERO DIARIO'!#REF!,'TABLERO DIARIO'!$AEV$2:$AII$2,">="&DATE(2025,MONTH(AL$2),1),'TABLERO DIARIO'!$AEV$2:$AII$2,"<="&EOMONTH(AL$2,0))/COUNTIFS('TABLERO DIARIO'!$AEV$2:$AII$2,">="&DATE(2025,MONTH(AL$2),1),'TABLERO DIARIO'!$AEV$2:$AII$2,"<="&EOMONTH(AL$2,0),'TABLERO DIARIO'!#REF!,"<>-"),"-") -> - | AM46: =IFERROR(SUMIFS('TABLERO DIARIO'!#REF!,'TABLERO DIARIO'!$AEV$2:$AMC$2,">="&DATE(2025,MONTH(AM$2),1),'TABLERO DIARIO'!$AEV$2:$AMC$2,"<="&EOMONTH(AM$2,0))/COUNTIFS('TABLERO DIARIO'!$AEV$2:$AMC$2,">="&DATE(2025,MONTH(AM$2),1),'TABLERO DIARIO'!$AEV$2:$AMC$2,"<="&EOMONTH(AM$2,0),'TABLERO DIARIO'!#REF!,"<>-"),"-") -> - | AN46: =IFERROR(SUMIFS('TABLERO DIARIO'!#REF!,'TABLERO DIARIO'!$ALW$2:$ASW$2,">="&DATE(2026,MONTH(AN$2),1),'TABLERO DIARIO'!$ALW$2:$ASW$2,"<="&EOMONTH(AN$2,0))/COUNTIFS('TABLERO DIARIO'!$ALW$2:$ASW$2,">="&DATE(2026,MONTH(AN$2),1),'TABLERO DIARIO'!$ALW$2:$ASW$2,"<="&EOMONTH(AN$2,0),'TABLERO DIARIO'!#REF!,"<>-"),"-") -> - | AO46: =IFERROR(SUMIFS('TABLERO DIARIO'!#REF!,'TABLERO DIARIO'!$ALW$2:$ASW$2,">="&DATE(2026,MONTH(AO$2),1),'TABLERO DIARIO'!$ALW$2:$ASW$2,"<="&EOMONTH(AO$2,0))/COUNTIFS('TABLERO DIARIO'!$ALW$2:$ASW$2,">="&DATE(2026,MONTH(AO$2),1),'TABLERO DIARIO'!$ALW$2:$ASW$2,"<="&EOMONTH(AO$2,0),'TABLERO DIARIO'!#REF!,"<>-"),"-") -> - | BA46: =IFERROR(AVERAGE(D46:O46),"-") -> 0.962 | BB46: =IFERROR(AVERAGE(P46:AA46),"-") -> 0.90333333 | BC46: =IFERROR(SUMIFS(AB46:AM46,AB46:AM46,"<>0",AB46:AM46,"<>-",AB46:AM46,"<>",AB46:AM46,"<> ")/COUNTIFS(AB46:AM46,"<>0",AB46:AM46,"<>-",AB46:AM46,"<>",AB46:AM46,"<> "),"-") -> -
BC47: =IFERROR(SUMIFS(AB47:AM47,AB47:AM47,"<>0",AB47:AM47,"<>-",AB47:AM47,"<>",AB47:AM47,"<> ")/COUNTIFS(AB47:AM47,"<>0",AB47:AM47,"<>-",AB47:AM47,"<>",AB47:AM47,"<> "),"-") -> -
B48: VENTA REAL VS FORECAST | C48: % | D48: -0.01 | E48: -0.16 | F48: 0 | G48: -0.01 | H48: -0.13 | I48: -0.18 | J48: -0.17 | K48: -0.15 | L48: -0.12 | M48: -0.08 | N48: -0.18 | O48: -0.29 | P48: 0.02 | Q48: 0.03 | R48: -0.19 | S48: -0.13 | T48: -0.12 | U48: -0.19 | V48: 0.09 | W48: 0.03 | X48: -0.03 | Y48: 0.04 | Z48: 0.03 | AA48: 0.01 | AB48: 0.04 | AC48: 0.01 | AD48: -0.04 | AE48: -0.05 | AF48: -0.06 | AG48: -0.2 | AH48: -0.02 | AI48: -0.16 | AJ48: -0.07 | AK48: -0.12 | AL48: -0.15 | AM48: 0 | AN48: -0.06 | AO48: -0.07 | BA48: =IFERROR(AVERAGE(D48:O48),"-") -> -0.12333333 | BB48: =IFERROR(AVERAGE(P48:AA48),"-") -> -0.034166667 | BC48: =IFERROR(SUMIFS(AB48:AM48,AB48:AM48,"<>0",AB48:AM48,"<>-",AB48:AM48,"<>",AB48:AM48,"<> ")/COUNTIFS(AB48:AM48,"<>0",AB48:AM48,"<>-",AB48:AM48,"<>",AB48:AM48,"<> "),"-") -> -0.074545455
B49: ERROR ABS % PROMEDIO TOTAL | C49: % | P49: 0.6 | Q49: 0.8 | R49: 0.99 | S49: 0.71 | T49: 1.15 | U49: 0.94 | V49: 0.67 | W49: 0.97 | X49: 0.76 | Y49: 0.62 | Z49: 0.91 | AA49: 0.6 | AB49: 0.58 | AC49: 0.49 | AD49: 0.67 | AE49: 0.59 | AF49: h | AG49: 0.677 | AH49: 0.569 | AI49: 0.892 | AJ49: 0.564 | AK49: 0.625 | AL49: 0.67 | AM49: 0.716 | AN49: 0.784 | AO49: 0.762 | BA49: =IFERROR(AVERAGE(D49:O49),"-") -> - | BB49: =IFERROR(AVERAGE(P49:AA49),"-") -> 0.81 | BC49: =IFERROR(SUMIFS(AB49:AM49,AB49:AM49,"<>0",AB49:AM49,"<>-",AB49:AM49,"<>",AB49:AM49,"<> ")/COUNTIFS(AB49:AM49,"<>0",AB49:AM49,"<>-",AB49:AM49,"<>",AB49:AM49,"<> "),"-") -> 0.58691667
B50: HAMBURGUESAS Y PULPETAS | C50: % | P50: 0.62 | Q50: 0.88 | R50: 0.97 | S50: 0.71 | T50: 1.36 | U50: 0.99 | V50: 0.78 | W50: 1.04 | X50: 0.89 | Y50: 0.63 | Z50: 1.01 | AA50: 0.6 | AB50: 0.53 | AC50: 0.48 | AD50: 0.65 | AE50: 0.6 | AF50: 0.6 | AG50: 0.617 | AH50: 0.607 | AI50: 0.994 | AJ50: 0.633 | AK50: 0.662 | AL50: 0.7 | AM50: 0.737 | AN50: 0.885 | AO50: 0.83 | BA50: =IFERROR(AVERAGE(D50:O50),"-") -> - | BB50: =IFERROR(AVERAGE(P50:AA50),"-") -> 0.87333333 | BC50: =IFERROR(SUMIFS(AB50:AM50,AB50:AM50,"<>0",AB50:AM50,"<>-",AB50:AM50,"<>",AB50:AM50,"<> ")/COUNTIFS(AB50:AM50,"<>0",AB50:AM50,"<>-",AB50:AM50,"<>",AB50:AM50,"<> "),"-") -> 0.65083333
B51: SALCHICHAS | C51: % | P51: 0.34 | Q51: 0.32 | R51: 0.44 | S51: 0.66 | T51: 0.54 | U51: 0.61 | V51: 0.34 | W51: 0.78 | X51: 0.42 | Y51: 0.69 | Z51: 0.66 | AA51: 0.52 | AB51: 0.73 | AC51: 0.49 | AD51: 0.87 | AE51: 0.52 | AF51: 0.613 | AG51: 0.912 | AH51: 0.415 | AI51: 0.75 | AJ51: 0.449 | AK51: 0.632 | AL51: 0.406 | AM51: 0.674 | AN51: 0.584 | AO51: 0.632 | BA51: =IFERROR(AVERAGE(D51:O51),"-") -> - | BB51: =IFERROR(AVERAGE(P51:AA51),"-") -> 0.52666667 | BC51: =IFERROR(SUMIFS(AB51:AM51,AB51:AM51,"<>0",AB51:AM51,"<>-",AB51:AM51,"<>",AB51:AM51,"<> ")/COUNTIFS(AB51:AM51,"<>0",AB51:AM51,"<>-",AB51:AM51,"<>",AB51:AM51,"<> "),"-") -> 0.62175
B52: RESTO | C52: % | P52: 1.13 | Q52: 1.43 | R52: 2.95 | S52: 0.89 | T52: 0.63 | U52: 1.23 | V52: 0.36 | W52: 0.53 | X52: 0.33 | Y52: 0.31 | Z52: 0.7 | AA52: 0.94 | AB52: 0.57 | AC52: 0.59 | AD52: 0.28 | AE52: 0.61 | AF52: 0.328 | AG52: 0.432 | AH52: 0.707 | AI52: 0.495 | AJ52: 0.328 | AK52: 0.331 | AL52: 1.056 | AM52: 0.656 | AN52: 0.539 | AO52: 0.583 | BA52: =IFERROR(AVERAGE(D52:O52),"-") -> - | BB52: =IFERROR(AVERAGE(P52:AA52),"-") -> 0.9525 | BC52: =IFERROR(SUMIFS(AB52:AM52,AB52:AM52,"<>0",AB52:AM52,"<>-",AB52:AM52,"<>",AB52:AM52,"<> ")/COUNTIFS(AB52:AM52,"<>0",AB52:AM52,"<>-",AB52:AM52,"<>",AB52:AM52,"<> "),"-") -> 0.53191667
B53: ERROR ABS % PONDERADO TOTAL | C53: % | P53: 0.3 | Q53: 0.3 | R53: 0.35 | S53: 0.29 | T53: 0.32 | U53: 0.35 | V53: 0.31 | W53: 0.3 | X53: 0.25 | Y53: 0.25 | Z53: 0.27 | AA53: 0.24 | AB53: 0.25 | AC53: 0.23 | AD53: 0.27 | AE53: 0.29 | AF53: 0.326 | AG53: 0.316 | AH53: 0.248 | AI53: 0.339 | AJ53: 0.318 | AK53: 0.23 | AL53: 0.321 | AM53: 0.258 | AN53: 0.293 | AO53: 0.296 | BA53: =IFERROR(AVERAGE(D53:O53),"-") -> - | BB53: =IFERROR(AVERAGE(P53:AA53),"-") -> 0.29416667 | BC53: =IFERROR(SUMIFS(AB53:AM53,AB53:AM53,"<>0",AB53:AM53,"<>-",AB53:AM53,"<>",AB53:AM53,"<> ")/COUNTIFS(AB53:AM53,"<>0",AB53:AM53,"<>-",AB53:AM53,"<>",AB53:AM53,"<> "),"-") -> 0.283
B54: HAMBURGUESAS Y PULPETAS | C54: % | P54: 0.36 | Q54: 0.34 | R54: 0.38 | S54: 0.32 | T54: 0.37 | U54: 0.4 | V54: 0.35 | W54: 0.37 | X54: 0.28 | Y54: 0.28 | Z54: 0.28 | AA54: 0.25 | AB54: 0.22 | AC54: 0.23 | AD54: 0.25 | AE54: 0.3 | AF54: 0.326 | AG54: 0.298 | AH54: 0.231 | AI54: 0.339 | AJ54: 0.311 | AK54: 0.224 | AL54: 0.349 | AM54: 0.256 | AN54: 0.26 | AO54: 0.314 | BA54: =IFERROR(AVERAGE(D54:O54),"-") -> - | BB54: =IFERROR(AVERAGE(P54:AA54),"-") -> 0.33166667 | BC54: =IFERROR(SUMIFS(AB54:AM54,AB54:AM54,"<>0",AB54:AM54,"<>-",AB54:AM54,"<>",AB54:AM54,"<> ")/COUNTIFS(AB54:AM54,"<>0",AB54:AM54,"<>-",AB54:AM54,"<>",AB54:AM54,"<> "),"-") -> 0.27783333
B55: SALCHICHAS | C55: % | P55: 0.18 | Q55: 0.23 | R55: 0.29 | S55: 0.24 | T55: 0.23 | U55: 0.25 | V55: 0.23 | W55: 0.17 | X55: 0.19 | Y55: 0.2 | Z55: 0.25 | AA55: 0.2 | AB55: 0.3 | AC55: 0.22 | AD55: 0.31 | AE55: 0.27 | AF55: 0.33 | AG55: 0.338 | AH55: 0.256 | AI55: 0.354 | AJ55: 0.33 | AK55: 0.223 | AL55: 0.233 | AM55: 0.251 | AN55: 0.32 | AO55: 0.254 | BA55: =IFERROR(AVERAGE(D55:O55),"-") -> - | BB55: =IFERROR(AVERAGE(P55:AA55),"-") -> 0.22166667 | BC55: =IFERROR(SUMIFS(AB55:AM55,AB55:AM55,"<>0",AB55:AM55,"<>-",AB55:AM55,"<>",AB55:AM55,"<> ")/COUNTIFS(AB55:AM55,"<>0",AB55:AM55,"<>-",AB55:AM55,"<>",AB55:AM55,"<> "),"-") -> 0.28458333
B56: RESTO | C56: % | P56: 0.97 | Q56: 1.51 | R56: 0.45 | S56: 0.68 | T56: 0.23 | U56: 1.18 | V56: 0.36 | W56: 0.58 | X56: 0.31 | Y56: 0.27 | Z56: 1.03 | AA56: 1.01 | AB56: 0.31 | AC56: 0.16 | AD56: 0.18 | AE56: 0.32 | AF56: 0.262 | AG56: 0.5 | AH56: 0.735 | AI56: 0.277 | AJ56: 0.297 | AK56: 0.458 | AL56: 0.686 | AM56: 0.35 | AN56: 0.734 | AO56: 0.436 | BA56: =IFERROR(AVERAGE(D56:O56),"-") -> - | BB56: =IFERROR(AVERAGE(P56:AA56),"-") -> 0.715 | BC56: =IFERROR(SUMIFS(AB56:AM56,AB56:AM56,"<>0",AB56:AM56,"<>-",AB56:AM56,"<>",AB56:AM56,"<> ")/COUNTIFS(AB56:AM56,"<>0",AB56:AM56,"<>-",AB56:AM56,"<>",AB56:AM56,"<> "),"-") -> 0.37791667
B58: REMITOS ESCANEADOS | C58: % | G58: 0.96 | H58: 0.98 | I58: 0.94 | J58: 0.94 | K58: 0.99 | L58: 0.9 | M58: 0.8 | N58: 0.96 | O58: 0.965 | P58: 0.87 | Q58: 0.76 | S58: 0.947 | T58: 0.988 | U58: 0.993 | V58: 0.996 | W58: 0.992 | X58: 0.969 | Y58: 0.997 | Z58: 0.992 | AA58: 0.979 | AB58: 0.9952 | AC58: 0.9941 | AD58: 0.9963 | AE58: 0.9932 | AF58: 0.9929 | AG58: 0.9952 | AH58: 0.9972 | AI58: 0.9882 | AJ58: 0.9926 | AK58: 0.9973 | AL58: 0.988 | AM58: 0.931 | AN58: 0.9436 | AO58: 0.8243 | BA58: =IFERROR(AVERAGE(D58:O58),"-") -> 0.93722222 | BB58: =IFERROR(AVERAGE(P58:AA58),"-") -> 0.953 | BC58: =IFERROR(SUMIFS(AB58:AM58,AB58:AM58,"<>0",AB58:AM58,"<>-",AB58:AM58,"<>",AB58:AM58,"<> ")/COUNTIFS(AB58:AM58,"<>0",AB58:AM58,"<>-",AB58:AM58,"<>",AB58:AM58,"<> "),"-") -> 0.98843333
B59: CALIDAD DE CARGA LOGÍSTICA | C59: % | G59: 0.79 | H59: 0.88 | I59: 0.9 | J59: 0.91 | K59: 0.88 | L59: 0.88 | M59: 0.87 | N59: 0.87 | O59: 0.81 | P59: 0.75 | Q59: 0.74 | R59: 0.78 | S59: 0.82 | T59: 0.79 | U59: 0.72 | V59: 0.81 | W59: 0.79 | X59: 0.81 | Y59: 0.74 | Z59: 0.72 | AA59: 0.73 | AB59: 0.69 | AC59: 0.6961 | AD59: 0.6571 | AE59: 0.7599 | AF59: 0.7458 | AG59: 0.7651 | AH59: 0.8008 | AI59: 0.841 | AJ59: 0.77 | AK59: 0.87 | AL59: 0.82 | AM59: 0.78 | AN59: 0.77 | BA59: =IFERROR(AVERAGE(D59:O59),"-") -> 0.86555556 | BB59: =IFERROR(AVERAGE(P59:AA59),"-") -> 0.76666667 | BC59: =IFERROR(SUMIFS(AB59:AM59,AB59:AM59,"<>0",AB59:AM59,"<>-",AB59:AM59,"<>",AB59:AM59,"<> ")/COUNTIFS(AB59:AM59,"<>0",AB59:AM59,"<>-",AB59:AM59,"<>",AB59:AM59,"<> "),"-") -> 0.76631667
B60: HIGIENE DE LA CAJA | C60: % | G60: 0.83 | H60: 0.94 | I60: 0.97 | J60: 0.97 | K60: 0.97 | L60: 0.99 | M60: 1 | N60: 1 | O60: 1 | P60: 1 | Q60: 1 | R60: 0.99 | S60: 1 | T60: 0.95 | U60: 0.8 | V60: 0.97 | W60: 0.99 | X60: 1 | Y60: 1 | Z60: 0.99 | AA60: 0.98 | AB60: 0.99 | AC60: 1 | AD60: 0.9813 | AE60: 0.9926 | AF60: 0.9961 | AG60: 1 | AH60: 1 | AI60: 0.9883 | AJ60: 0.9954 | AK60: 1 | AL60: 0.99 | AM60: 1 | AN60: 1 | BA60: =IFERROR(AVERAGE(D60:O60),"-") -> 0.96333333 | BB60: =IFERROR(AVERAGE(P60:AA60),"-") -> 0.9725 | BC60: =IFERROR(SUMIFS(AB60:AM60,AB60:AM60,"<>0",AB60:AM60,"<>-",AB60:AM60,"<>",AB60:AM60,"<> ")/COUNTIFS(AB60:AM60,"<>0",AB60:AM60,"<>-",AB60:AM60,"<>",AB60:AM60,"<> "),"-") -> 0.994475
B61: TEMPERATURA DE LA CAJA | C61: % | G61: 0.62 | H61: 0.66 | I61: 0.73 | J61: 0.79 | K61: 0.68 | L61: 0.68 | M61: 0.59 | N61: 0.55 | O61: 0.43 | P61: 0.31 | Q61: 0.3 | R61: 0.34 | S61: 0.5 | T61: 0.59 | U61: 0.52 | V61: 0.64 | W61: 0.5 | X61: 0.49 | Y61: 0.37 | Z61: 0.33 | AA61: 0.36 | AB61: 0.35 | AC61: 0.2899 | AD61: 0.2388 | AE61: 0.4275 | AF61: 0.4826 | AG61: 0.5948 | AH61: 0.6778 | AI61: 0.7135 | AJ61: 0.5854 | AK61: 0.48 | AL61: 0.44 | AM61: 0.38 | AN61: 0.34 | BA61: =IFERROR(AVERAGE(D61:O61),"-") -> 0.63666667 | BB61: =IFERROR(AVERAGE(P61:AA61),"-") -> 0.4375 | BC61: =IFERROR(SUMIFS(AB61:AM61,AB61:AM61,"<>0",AB61:AM61,"<>-",AB61:AM61,"<>",AB61:AM61,"<> ")/COUNTIFS(AB61:AM61,"<>0",AB61:AM61,"<>-",AB61:AM61,"<>",AB61:AM61,"<> "),"-") -> 0.47169167
B62: PRESENTACIÓN DEL CHOFER | C62: % | G62: 0.97 | H62: 0.98 | I62: 0.99 | J62: 0.95 | K62: 0.93 | L62: 0.93 | M62: 0.97 | N62: 1 | O62: 0.99 | P62: 0.99 | Q62: 0.98 | R62: 0.98 | S62: 0.97 | T62: 0.96 | U62: 0.95 | V62: 0.92 | W62: 0.95 | X62: 0.96 | Y62: 0.92 | Z62: 0.9 | AA62: 0.92 | AB62: 0.92 | AC62: 0.9153 | AD62: 0.9179 | AE62: 0.9442 | AF62: 0.9961 | AG62: 0.871 | AH62: 0.9179 | AI62: 0.9857 | AJ62: 0.9942 | AK62: 0.99 | AL62: 1 | AM62: 0.97 | AN62: 0.99 | BA62: =IFERROR(AVERAGE(D62:O62),"-") -> 0.96777778 | BB62: =IFERROR(AVERAGE(P62:AA62),"-") -> 0.95 | BC62: =IFERROR(SUMIFS(AB62:AM62,AB62:AM62,"<>0",AB62:AM62,"<>-",AB62:AM62,"<>",AB62:AM62,"<> ")/COUNTIFS(AB62:AM62,"<>0",AB62:AM62,"<>-",AB62:AM62,"<>",AB62:AM62,"<> "),"-") -> 0.95185833
B63: TEMPERATURA PROM. DEL PRODUCTO | C63: % | G63: 0.73 | H63: 0.94 | I63: 0.91 | J63: 0.94 | K63: 0.92 | L63: 0.92 | M63: 0.9 | N63: 0.93 | O63: 0.82 | P63: 0.68 | Q63: 0.68 | R63: 0.82 | S63: 0.83 | T63: 0.65 | U63: 0.61 | V63: 0.71 | W63: 0.72 | X63: 0.8 | Y63: 0.66 | Z63: 0.65 | AA63: 0.66 | AB63: 0.51 | AC63: 0.5792 | AD63: 0.4902 | AE63: 0.6751 | AF63: 0.5857 | AG63: 0.5948 | AH63: 0.6075 | AI63: 0.6765 | AJ63: 0.5 | AK63: 0.58 | AL63: 0.59 | AM63: 0.68 | AN63: 0.56 | BA63: =IFERROR(AVERAGE(D63:O63),"-") -> 0.89 | BB63: =IFERROR(AVERAGE(P63:AA63),"-") -> 0.70583333 | BC63: =IFERROR(SUMIFS(AB63:AM63,AB63:AM63,"<>0",AB63:AM63,"<>-",AB63:AM63,"<>",AB63:AM63,"<> ")/COUNTIFS(AB63:AM63,"<>0",AB63:AM63,"<>-",AB63:AM63,"<>",AB63:AM63,"<> "),"-") -> 0.58908333
B64: FALTANTES CPC | C64: TN | P64: - | Q64: - | R64: - | S64: - | T64: - | U64: - | V64: - | W64: - | X64: - | Y64: - | Z64: - | AA64: - | AB64: =IFERROR(IF(SUMIFS(#REF!,#REF!,">="&DATE(2025,MONTH(AB$2),1),#REF!,"<="&EOMONTH(AB$2,0),#REF!,"SI")=0,"-",(-1/1000)*SUMIFS(#REF!,#REF!,">="&DATE(2025,MONTH(AB$2),1),#REF!,"<="&EOMONTH(AB$2,0),#REF!,">="&DATE(2025,MONTH(AB$2),1),#REF!,"<="&EOMONTH(AB$2,0),#REF!,"SI")),"REVISAR") -> REVISAR | AC64: =IFERROR(IF(SUMIFS(#REF!,#REF!,">="&DATE(2025,MONTH(AC$2),1),#REF!,"<="&EOMONTH(AC$2,0),#REF!,"SI")=0,"-",(-1/1000)*SUMIFS(#REF!,#REF!,">="&DATE(2025,MONTH(AC$2),1),#REF!,"<="&EOMONTH(AC$2,0),#REF!,">="&DATE(2025,MONTH(AC$2),1),#REF!,"<="&EOMONTH(AC$2,0),#REF!,"SI")),"REVISAR") -> REVISAR | AD64: =IFERROR(IF(SUMIFS(#REF!,#REF!,">="&DATE(2025,MONTH(AD$2),1),#REF!,"<="&EOMONTH(AD$2,0),#REF!,"SI")=0,"-",(-1/1000)*SUMIFS(#REF!,#REF!,">="&DATE(2025,MONTH(AD$2),1),#REF!,"<="&EOMONTH(AD$2,0),#REF!,">="&DATE(2025,MONTH(AD$2),1),#REF!,"<="&EOMONTH(AD$2,0),#REF!,"SI")),"REVISAR") -> REVISAR | AE64: =IFERROR(IF(SUMIFS(#REF!,#REF!,">="&DATE(2025,MONTH(AE$2),1),#REF!,"<="&EOMONTH(AE$2,0),#REF!,"SI")=0,"-",(-1/1000)*SUMIFS(#REF!,#REF!,">="&DATE(2025,MONTH(AE$2),1),#REF!,"<="&EOMONTH(AE$2,0),#REF!,">="&DATE(2025,MONTH(AE$2),1),#REF!,"<="&EOMONTH(AE$2,0),#REF!,"SI")),"REVISAR") -> REVISAR | AF64: =IFERROR(IF(SUMIFS(#REF!,#REF!,">="&DATE(2025,MONTH(AF$2),1),#REF!,"<="&EOMONTH(AF$2,0),#REF!,"SI")=0,"-",(-1/1000)*SUMIFS(#REF!,#REF!,">="&DATE(2025,MONTH(AF$2),1),#REF!,"<="&EOMONTH(AF$2,0),#REF!,">="&DATE(2025,MONTH(AF$2),1),#REF!,"<="&EOMONTH(AF$2,0),#REF!,"SI")),"REVISAR") -> REVISAR | AG64: =IFERROR(IF(SUMIFS(#REF!,#REF!,">="&DATE(2025,MONTH(AG$2),1),#REF!,"<="&EOMONTH(AG$2,0),#REF!,"SI")=0,"-",(-1/1000)*SUMIFS(#REF!,#REF!,">="&DATE(2025,MONTH(AG$2),1),#REF!,"<="&EOMONTH(AG$2,0),#REF!,">="&DATE(2025,MONTH(AG$2),1),#REF!,"<="&EOMONTH(AG$2,0),#REF!,"SI")),"REVISAR") -> REVISAR | AH64: =IFERROR(IF(SUMIFS(#REF!,#REF!,">="&DATE(2025,MONTH(AH$2),1),#REF!,"<="&EOMONTH(AH$2,0),#REF!,"SI")=0,"-",(-1/1000)*SUMIFS(#REF!,#REF!,">="&DATE(2025,MONTH(AH$2),1),#REF!,"<="&EOMONTH(AH$2,0),#REF!,">="&DATE(2025,MONTH(AH$2),1),#REF!,"<="&EOMONTH(AH$2,0),#REF!,"SI")),"REVISAR") -> REVISAR | AI64: =IFERROR(IF(SUMIFS(#REF!,#REF!,">="&DATE(2025,MONTH(AI$2),1),#REF!,"<="&EOMONTH(AI$2,0),#REF!,"SI")=0,"-",(-1/1000)*SUMIFS(#REF!,#REF!,">="&DATE(2025,MONTH(AI$2),1),#REF!,"<="&EOMONTH(AI$2,0),#REF!,">="&DATE(2025,MONTH(AI$2),1),#REF!,"<="&EOMONTH(AI$2,0),#REF!,"SI")),"REVISAR") -> REVISAR | ... AM64: =IFERROR(IF(SUMIFS(#REF!,#REF!,">="&DATE(2025,MONTH(AM$2),1),#REF!,"<="&EOMONTH(AM$2,0),#REF!,"SI")=0,"-",(-1/1000)*SUMIFS(#REF!,#REF!,">="&DATE(2025,MONTH(AM$2),1),#REF!,"<="&EOMONTH(AM$2,0),#REF!,">="&DATE(2025,MONTH(AM$2),1),#REF!,"<="&EOMONTH(AM$2,0),#REF!,"SI")),"REVISAR") -> REVISAR | AN64: =IFERROR(IF(SUMIFS(#REF!,#REF!,">="&DATE(2026,MONTH(AN$2),1),#REF!,"<="&EOMONTH(AN$2,0),#REF!,"SI")=0,"-",(-1/1000)*SUMIFS(#REF!,#REF!,">="&DATE(2026,MONTH(AN$2),1),#REF!,"<="&EOMONTH(AN$2,0),#REF!,">="&DATE(2026,MONTH(AN$2),1),#REF!,"<="&EOMONTH(AN$2,0),#REF!,"SI")),"REVISAR") -> REVISAR | AO64: =IFERROR(IF(SUMIFS(#REF!,#REF!,">="&DATE(2026,MONTH(AO$2),1),#REF!,"<="&EOMONTH(AO$2,0),#REF!,"SI")=0,"-",(-1/1000)*SUMIFS(#REF!,#REF!,">="&DATE(2026,MONTH(AO$2),1),#REF!,"<="&EOMONTH(AO$2,0),#REF!,">="&DATE(2026,MONTH(AO$2),1),#REF!,"<="&EOMONTH(AO$2,0),#REF!,"SI")),"REVISAR") -> REVISAR | BA64: =IFERROR(AVERAGE(D64:O64),"-") -> - | BB64: =IFERROR(AVERAGE(P64:AA64),"-") -> - | BC64: =IFERROR(SUMIFS(AB64:AM64,AB64:AM64,"<>0",AB64:AM64,"<>-",AB64:AM64,"<>",AB64:AM64,"<> ")/COUNTIFS(AB64:AM64,"<>0",AB64:AM64,"<>-",AB64:AM64,"<>",AB64:AM64,"<> "),"-") -> 0
B65: RECHAZOS + DEVOLUCIONES | C65: TN | G65: 1.0% | H65: 4.0% | I65: 3.4% | J65: 2.6% | K65: 2.0% | L65: 1.0% | M65: 0.7% | N65: 0.7% | O65: 0.6% | P65: 0.5% | Q65: 0.8% | R65: 1.0% | S65: 1.1% | T65: 0.7% | U65: 1.5% | V65: 0.9% | W65: 0.8% | X65: - | Y65: - | Z65: - | AA65: - | AB65: =IF(SUMIFS('TABLERO DIARIO'!#REF!,'TABLERO DIARIO'!$I$2:$ZZ$2,">="&DATE(2025,MONTH(AB$2),1),'TABLERO DIARIO'!$I$2:$ZZ$2,"<="&EOMONTH(AB$2,0))/1000=0,"-",SUMIFS('TABLERO DIARIO'!#REF!,'TABLERO DIARIO'!$I$2:$ZZ$2,">="&DATE(2025,MONTH(AB$2),1),'TABLERO DIARIO'!$I$2:$ZZ$2,"<="&EOMONTH(AB$2,0))/1000) -> #REF! | AC65: =IF(SUMIFS('TABLERO DIARIO'!#REF!,'TABLERO DIARIO'!$I$2:$ZZ$2,">="&DATE(2025,MONTH(AC$2),1),'TABLERO DIARIO'!$I$2:$ZZ$2,"<="&EOMONTH(AC$2,0))/1000=0,"-",SUMIFS('TABLERO DIARIO'!#REF!,'TABLERO DIARIO'!$I$2:$ZZ$2,">="&DATE(2025,MONTH(AC$2),1),'TABLERO DIARIO'!$I$2:$ZZ$2,"<="&EOMONTH(AC$2,0))/1000) -> #REF! | AD65: =IF(SUMIFS('TABLERO DIARIO'!#REF!,'TABLERO DIARIO'!$I$2:$ZZ$2,">="&DATE(2025,MONTH(AD$2),1),'TABLERO DIARIO'!$I$2:$ZZ$2,"<="&EOMONTH(AD$2,0))/1000=0,"-",SUMIFS('TABLERO DIARIO'!#REF!,'TABLERO DIARIO'!$I$2:$ZZ$2,">="&DATE(2025,MONTH(AD$2),1),'TABLERO DIARIO'!$I$2:$ZZ$2,"<="&EOMONTH(AD$2,0))/1000) -> #REF! | AE65: =IF(SUMIFS('TABLERO DIARIO'!#REF!,'TABLERO DIARIO'!$I$2:$ZZ$2,">="&DATE(2025,MONTH(AE$2),1),'TABLERO DIARIO'!$I$2:$ZZ$2,"<="&EOMONTH(AE$2,0))/1000=0,"-",SUMIFS('TABLERO DIARIO'!#REF!,'TABLERO DIARIO'!$I$2:$ZZ$2,">="&DATE(2025,MONTH(AE$2),1),'TABLERO DIARIO'!$I$2:$ZZ$2,"<="&EOMONTH(AE$2,0))/1000) -> #REF! | AF65: =IF(SUMIFS('TABLERO DIARIO'!#REF!,'TABLERO DIARIO'!$I$2:$ZZ$2,">="&DATE(2025,MONTH(AF$2),1),'TABLERO DIARIO'!$I$2:$ZZ$2,"<="&EOMONTH(AF$2,0))/1000=0,"-",SUMIFS('TABLERO DIARIO'!#REF!,'TABLERO DIARIO'!$I$2:$ZZ$2,">="&DATE(2025,MONTH(AF$2),1),'TABLERO DIARIO'!$I$2:$ZZ$2,"<="&EOMONTH(AF$2,0))/1000) -> #REF! | AG65: =IF(SUMIFS('TABLERO DIARIO'!#REF!,'TABLERO DIARIO'!$I$2:$ZZ$2,">="&DATE(2025,MONTH(AG$2),1),'TABLERO DIARIO'!$I$2:$ZZ$2,"<="&EOMONTH(AG$2,0))/1000=0,"-",SUMIFS('TABLERO DIARIO'!#REF!,'TABLERO DIARIO'!$I$2:$ZZ$2,">="&DATE(2025,MONTH(AG$2),1),'TABLERO DIARIO'!$I$2:$ZZ$2,"<="&EOMONTH(AG$2,0))/1000) -> #REF! | AH65: =IF(SUMIFS('TABLERO DIARIO'!#REF!,'TABLERO DIARIO'!$I$2:$ZZ$2,">="&DATE(2025,MONTH(AH$2),1),'TABLERO DIARIO'!$I$2:$ZZ$2,"<="&EOMONTH(AH$2,0))/1000=0,"-",SUMIFS('TABLERO DIARIO'!#REF!,'TABLERO DIARIO'!$I$2:$ZZ$2,">="&DATE(2025,MONTH(AH$2),1),'TABLERO DIARIO'!$I$2:$ZZ$2,"<="&EOMONTH(AH$2,0))/1000) -> #REF! | AI65: =IF(SUMIFS('TABLERO DIARIO'!#REF!,'TABLERO DIARIO'!$I$2:$ZZ$2,">="&DATE(2025,MONTH(AI$2),1),'TABLERO DIARIO'!$I$2:$ZZ$2,"<="&EOMONTH(AI$2,0))/1000=0,"-",SUMIFS('TABLERO DIARIO'!#REF!,'TABLERO DIARIO'!$I$2:$ZZ$2,">="&DATE(2025,MONTH(AI$2),1),'TABLERO DIARIO'!$I$2:$ZZ$2,"<="&EOMONTH(AI$2,0))/1000) -> #REF! | AJ65: =IF(SUMIFS('TABLERO DIARIO'!#REF!,'TABLERO DIARIO'!$I$2:$ZZ$2,">="&DATE(2025,MONTH(AJ$2),1),'TABLERO DIARIO'!$I$2:$ZZ$2,"<="&EOMONTH(AJ$2,0))/1000=0,"-",SUMIFS('TABLERO DIARIO'!#REF!,'TABLERO DIARIO'!$I$2:$ZZ$2,">="&DATE(2025,MONTH(AJ$2),1),'TABLERO DIARIO'!$I$2:$ZZ$2,"<="&EOMONTH(AJ$2,0))/1000) -> #REF! | AK65: =IF(SUMIFS('TABLERO DIARIO'!#REF!,'TABLERO DIARIO'!$I$2:$AEV$2,">="&DATE(2025,MONTH(AK$2),1),'TABLERO DIARIO'!$I$2:$AEV$2,"<="&EOMONTH(AK$2,0))/1000=0,"-",SUMIFS('TABLERO DIARIO'!#REF!,'TABLERO DIARIO'!$I$2:$AEV$2,">="&DATE(2025,MONTH(AK$2),1),'TABLERO DIARIO'!$I$2:$AEV$2,"<="&EOMONTH(AK$2,0))/1000) -> #REF! | AL65: =IF(SUMIFS('TABLERO DIARIO'!#REF!,'TABLERO DIARIO'!$I$2:$AMA$2,">="&DATE(2025,MONTH(AL$2),1),'TABLERO DIARIO'!$I$2:$AMA$2,"<="&EOMONTH(AL$2,0))/1000=0,"-",SUMIFS('TABLERO DIARIO'!#REF!,'TABLERO DIARIO'!$I$2:$AMA$2,">="&DATE(2025,MONTH(AL$2),1),'TABLERO DIARIO'!$I$2:$AMA$2,"<="&EOMONTH(AL$2,0))/1000) -> #REF! | AM65: =IF(SUMIFS('TABLERO DIARIO'!#REF!,'TABLERO DIARIO'!$I$2:$AMA$2,">="&DATE(2025,MONTH(AM$2),1),'TABLERO DIARIO'!$I$2:$AMA$2,"<="&EOMONTH(AM$2,0))/1000=0,"-",SUMIFS('TABLERO DIARIO'!#REF!,'TABLERO DIARIO'!$I$2:$AMA$2,">="&DATE(2025,MONTH(AM$2),1),'TABLERO DIARIO'!$I$2:$AMA$2,"<="&EOMONTH(AM$2,0))/1000) -> #REF! | AN65: =IF(SUMIFS('TABLERO DIARIO'!#REF!,'TABLERO DIARIO'!$I$2:$ASW$2,">="&DATE(2026,MONTH(AN$2),1),'TABLERO DIARIO'!$I$2:$ASW$2,"<="&EOMONTH(AN$2,0))/1000=0,"-",SUMIFS('TABLERO DIARIO'!#REF!,'TABLERO DIARIO'!$I$2:$ASW$2,">="&DATE(2026,MONTH(AN$2),1),'TABLERO DIARIO'!$I$2:$ASW$2,"<="&EOMONTH(AN$2,0))/1000) -> #REF! | AO65: =IF(SUMIFS('TABLERO DIARIO'!#REF!,'TABLERO DIARIO'!$I$2:$ASW$2,">="&DATE(2026,MONTH(AO$2),1),'TABLERO DIARIO'!$I$2:$ASW$2,"<="&EOMONTH(AO$2,0))/1000=0,"-",SUMIFS('TABLERO DIARIO'!#REF!,'TABLERO DIARIO'!$I$2:$ASW$2,">="&DATE(2026,MONTH(AO$2),1),'TABLERO DIARIO'!$I$2:$ASW$2,"<="&EOMONTH(AO$2,0))/1000) -> #REF! | BA65: =IFERROR(AVERAGE(D65:O65),"-") -> - | BB65: =IFERROR(AVERAGE(P65:AA65),"-") -> - | BC65: =IFERROR(SUMIFS(AB65:AM65,AB65:AM65,"<>0",AB65:AM65,"<>-",AB65:AM65,"<>",AB65:AM65,"<> ")/COUNTIFS(AB65:AM65,"<>0",AB65:AM65,"<>-",AB65:AM65,"<>",AB65:AM65,"<> "),"-") -> -
B66: RECHAZOS + DEVOLUCIONES | C66: PAQ | AB66: =IF(SUMIFS('TABLERO DIARIO'!#REF!,'TABLERO DIARIO'!$I$2:$ZZ$2,">="&DATE(2025,MONTH(AB$2),1),'TABLERO DIARIO'!$I$2:$ZZ$2,"<="&EOMONTH(AB$2,0))=0,"-",SUMIFS('TABLERO DIARIO'!#REF!,'TABLERO DIARIO'!$I$2:$ZZ$2,">="&DATE(2025,MONTH(AB$2),1),'TABLERO DIARIO'!$I$2:$ZZ$2,"<="&EOMONTH(AB$2,0))) -> #REF! | AC66: =IF(SUMIFS('TABLERO DIARIO'!#REF!,'TABLERO DIARIO'!$I$2:$ZZ$2,">="&DATE(2025,MONTH(AC$2),1),'TABLERO DIARIO'!$I$2:$ZZ$2,"<="&EOMONTH(AC$2,0))=0,"-",SUMIFS('TABLERO DIARIO'!#REF!,'TABLERO DIARIO'!$I$2:$ZZ$2,">="&DATE(2025,MONTH(AC$2),1),'TABLERO DIARIO'!$I$2:$ZZ$2,"<="&EOMONTH(AC$2,0))) -> #REF! | AD66: =IF(SUMIFS('TABLERO DIARIO'!#REF!,'TABLERO DIARIO'!$I$2:$ZZ$2,">="&DATE(2025,MONTH(AD$2),1),'TABLERO DIARIO'!$I$2:$ZZ$2,"<="&EOMONTH(AD$2,0))=0,"-",SUMIFS('TABLERO DIARIO'!#REF!,'TABLERO DIARIO'!$I$2:$ZZ$2,">="&DATE(2025,MONTH(AD$2),1),'TABLERO DIARIO'!$I$2:$ZZ$2,"<="&EOMONTH(AD$2,0))) -> #REF! | AE66: =IF(SUMIFS('TABLERO DIARIO'!#REF!,'TABLERO DIARIO'!$I$2:$ZZ$2,">="&DATE(2025,MONTH(AE$2),1),'TABLERO DIARIO'!$I$2:$ZZ$2,"<="&EOMONTH(AE$2,0))=0,"-",SUMIFS('TABLERO DIARIO'!#REF!,'TABLERO DIARIO'!$I$2:$ZZ$2,">="&DATE(2025,MONTH(AE$2),1),'TABLERO DIARIO'!$I$2:$ZZ$2,"<="&EOMONTH(AE$2,0))) -> #REF! | AF66: =IF(SUMIFS('TABLERO DIARIO'!#REF!,'TABLERO DIARIO'!$I$2:$ZZ$2,">="&DATE(2025,MONTH(AF$2),1),'TABLERO DIARIO'!$I$2:$ZZ$2,"<="&EOMONTH(AF$2,0))=0,"-",SUMIFS('TABLERO DIARIO'!#REF!,'TABLERO DIARIO'!$I$2:$ZZ$2,">="&DATE(2025,MONTH(AF$2),1),'TABLERO DIARIO'!$I$2:$ZZ$2,"<="&EOMONTH(AF$2,0))) -> #REF! | AG66: =IF(SUMIFS('TABLERO DIARIO'!#REF!,'TABLERO DIARIO'!$I$2:$ZZ$2,">="&DATE(2025,MONTH(AG$2),1),'TABLERO DIARIO'!$I$2:$ZZ$2,"<="&EOMONTH(AG$2,0))=0,"-",SUMIFS('TABLERO DIARIO'!#REF!,'TABLERO DIARIO'!$I$2:$ZZ$2,">="&DATE(2025,MONTH(AG$2),1),'TABLERO DIARIO'!$I$2:$ZZ$2,"<="&EOMONTH(AG$2,0))) -> #REF! | AH66: =IF(SUMIFS('TABLERO DIARIO'!#REF!,'TABLERO DIARIO'!$I$2:$ZZ$2,">="&DATE(2025,MONTH(AH$2),1),'TABLERO DIARIO'!$I$2:$ZZ$2,"<="&EOMONTH(AH$2,0))=0,"-",SUMIFS('TABLERO DIARIO'!#REF!,'TABLERO DIARIO'!$I$2:$ZZ$2,">="&DATE(2025,MONTH(AH$2),1),'TABLERO DIARIO'!$I$2:$ZZ$2,"<="&EOMONTH(AH$2,0))) -> #REF! | AI66: =IF(SUMIFS('TABLERO DIARIO'!#REF!,'TABLERO DIARIO'!$I$2:$ZZ$2,">="&DATE(2025,MONTH(AI$2),1),'TABLERO DIARIO'!$I$2:$ZZ$2,"<="&EOMONTH(AI$2,0))=0,"-",SUMIFS('TABLERO DIARIO'!#REF!,'TABLERO DIARIO'!$I$2:$ZZ$2,">="&DATE(2025,MONTH(AI$2),1),'TABLERO DIARIO'!$I$2:$ZZ$2,"<="&EOMONTH(AI$2,0))) -> #REF! | AJ66: =IF(SUMIFS('TABLERO DIARIO'!#REF!,'TABLERO DIARIO'!$I$2:$ZZ$2,">="&DATE(2025,MONTH(AJ$2),1),'TABLERO DIARIO'!$I$2:$ZZ$2,"<="&EOMONTH(AJ$2,0))=0,"-",SUMIFS('TABLERO DIARIO'!#REF!,'TABLERO DIARIO'!$I$2:$ZZ$2,">="&DATE(2025,MONTH(AJ$2),1),'TABLERO DIARIO'!$I$2:$ZZ$2,"<="&EOMONTH(AJ$2,0))) -> #REF! | AK66: =IF(SUMIFS('TABLERO DIARIO'!#REF!,'TABLERO DIARIO'!$I$2:$AEV$2,">="&DATE(2025,MONTH(AK$2),1),'TABLERO DIARIO'!$I$2:$AEV$2,"<="&EOMONTH(AK$2,0))=0,"-",SUMIFS('TABLERO DIARIO'!#REF!,'TABLERO DIARIO'!$I$2:$AEV$2,">="&DATE(2025,MONTH(AK$2),1),'TABLERO DIARIO'!$I$2:$AEV$2,"<="&EOMONTH(AK$2,0))) -> #REF! | AL66: =IF(SUMIFS('TABLERO DIARIO'!#REF!,'TABLERO DIARIO'!$AEV$2:$AMA$2,">="&DATE(2025,MONTH(AL$2),1),'TABLERO DIARIO'!$AEV$2:$AMA$2,"<="&EOMONTH(AL$2,0))=0,"-",SUMIFS('TABLERO DIARIO'!#REF!,'TABLERO DIARIO'!$AEV$2:$AMA$2,">="&DATE(2025,MONTH(AL$2),1),'TABLERO DIARIO'!$AEV$2:$AMA$2,"<="&EOMONTH(AL$2,0))) -> #REF! | AM66: =IF(SUMIFS('TABLERO DIARIO'!#REF!,'TABLERO DIARIO'!$AEV$2:$AMA$2,">="&DATE(2025,MONTH(AM$2),1),'TABLERO DIARIO'!$AEV$2:$AMA$2,"<="&EOMONTH(AM$2,0))=0,"-",SUMIFS('TABLERO DIARIO'!#REF!,'TABLERO DIARIO'!$AEV$2:$AMA$2,">="&DATE(2025,MONTH(AM$2),1),'TABLERO DIARIO'!$AEV$2:$AMA$2,"<="&EOMONTH(AM$2,0))) -> #REF! | AN66: =IF(SUMIFS('TABLERO DIARIO'!#REF!,'TABLERO DIARIO'!$ALW$2:$ASW$2,">="&DATE(2026,MONTH(AN$2),1),'TABLERO DIARIO'!$ALW$2:$ASW$2,"<="&EOMONTH(AN$2,0))=0,"-",SUMIFS('TABLERO DIARIO'!#REF!,'TABLERO DIARIO'!$ALW$2:$ASW$2,">="&DATE(2026,MONTH(AN$2),1),'TABLERO DIARIO'!$ALW$2:$ASW$2,"<="&EOMONTH(AN$2,0))) -> #REF! | AO66: =IF(SUMIFS('TABLERO DIARIO'!#REF!,'TABLERO DIARIO'!$ALW$2:$ASW$2,">="&DATE(2026,MONTH(AO$2),1),'TABLERO DIARIO'!$ALW$2:$ASW$2,"<="&EOMONTH(AO$2,0))=0,"-",SUMIFS('TABLERO DIARIO'!#REF!,'TABLERO DIARIO'!$ALW$2:$ASW$2,">="&DATE(2026,MONTH(AO$2),1),'TABLERO DIARIO'!$ALW$2:$ASW$2,"<="&EOMONTH(AO$2,0))) -> #REF! | BA66: =IFERROR(AVERAGE(D66:O66),"-") -> - | BB66: =IFERROR(AVERAGE(P66:AA66),"-") -> - | BC66: =IFERROR(SUMIFS(AB66:AM66,AB66:AM66,"<>0",AB66:AM66,"<>-",AB66:AM66,"<>",AB66:AM66,"<> ")/COUNTIFS(AB66:AM66,"<>0",AB66:AM66,"<>-",AB66:AM66,"<>",AB66:AM66,"<> "),"-") -> -
B67: RECHAZOS + DEVOLUCIONES | C67: BOCAS | AB67: {=IF(COUNTA(_xlfn.UNIQUE(_xlfn._xlws.FILTER(#REF!,(#REF!>=DATE(2025,MONTH('MES CERRADO'!AB2),1))*(#REF!<=EOMONTH('MES CERRADO'!AB2,0))*(#REF!<>""))))=1,"-",COUNTA(_xlfn.UNIQUE(_xlfn._xlws.FILTER(#REF!,(#REF!>=DATE(2025,MONTH('MES CERRADO'!AB2),1))*(#REF!<=EOMONTH('MES CERRADO'!AB2,0))*(#REF!<>"")))))} -> - | AC67: {=IF(COUNTA(_xlfn.UNIQUE(_xlfn._xlws.FILTER(#REF!,(#REF!>=DATE(2025,MONTH('MES CERRADO'!AC2),1))*(#REF!<=EOMONTH('MES CERRADO'!AC2,0))*(#REF!<>""))))=1,"-",COUNTA(_xlfn.UNIQUE(_xlfn._xlws.FILTER(#REF!,(#REF!>=DATE(2025,MONTH('MES CERRADO'!AC2),1))*(#REF!<=EOMONTH('MES CERRADO'!AC2,0))*(#REF!<>"")))))} -> - | AD67: {=IF(COUNTA(_xlfn.UNIQUE(_xlfn._xlws.FILTER(#REF!,(#REF!>=DATE(2025,MONTH('MES CERRADO'!AD2),1))*(#REF!<=EOMONTH('MES CERRADO'!AD2,0))*(#REF!<>""))))=1,"-",COUNTA(_xlfn.UNIQUE(_xlfn._xlws.FILTER(#REF!,(#REF!>=DATE(2025,MONTH('MES CERRADO'!AD2),1))*(#REF!<=EOMONTH('MES CERRADO'!AD2,0))*(#REF!<>"")))))} -> - | AE67: {=IF(COUNTA(_xlfn.UNIQUE(_xlfn._xlws.FILTER(#REF!,(#REF!>=DATE(2025,MONTH('MES CERRADO'!AE2),1))*(#REF!<=EOMONTH('MES CERRADO'!AE2,0))*(#REF!<>""))))=1,"-",COUNTA(_xlfn.UNIQUE(_xlfn._xlws.FILTER(#REF!,(#REF!>=DATE(2025,MONTH('MES CERRADO'!AE2),1))*(#REF!<=EOMONTH('MES CERRADO'!AE2,0))*(#REF!<>"")))))} -> - | AF67: {=IF(COUNTA(_xlfn.UNIQUE(_xlfn._xlws.FILTER(#REF!,(#REF!>=DATE(2025,MONTH('MES CERRADO'!AF2),1))*(#REF!<=EOMONTH('MES CERRADO'!AF2,0))*(#REF!<>""))))=1,"-",COUNTA(_xlfn.UNIQUE(_xlfn._xlws.FILTER(#REF!,(#REF!>=DATE(2025,MONTH('MES CERRADO'!AF2),1))*(#REF!<=EOMONTH('MES CERRADO'!AF2,0))*(#REF!<>"")))))} -> - | AG67: {=IF(COUNTA(_xlfn.UNIQUE(_xlfn._xlws.FILTER(#REF!,(#REF!>=DATE(2025,MONTH('MES CERRADO'!AG2),1))*(#REF!<=EOMONTH('MES CERRADO'!AG2,0))*(#REF!<>""))))=1,"-",COUNTA(_xlfn.UNIQUE(_xlfn._xlws.FILTER(#REF!,(#REF!>=DATE(2025,MONTH('MES CERRADO'!AG2),1))*(#REF!<=EOMONTH('MES CERRADO'!AG2,0))*(#REF!<>"")))))} -> - | AH67: {=IF(COUNTA(_xlfn.UNIQUE(_xlfn._xlws.FILTER(#REF!,(#REF!>=DATE(2025,MONTH('MES CERRADO'!AH2),1))*(#REF!<=EOMONTH('MES CERRADO'!AH2,0))*(#REF!<>""))))=1,"-",COUNTA(_xlfn.UNIQUE(_xlfn._xlws.FILTER(#REF!,(#REF!>=DATE(2025,MONTH('MES CERRADO'!AH2),1))*(#REF!<=EOMONTH('MES CERRADO'!AH2,0))*(#REF!<>"")))))} -> - | AI67: {=IF(COUNTA(_xlfn.UNIQUE(_xlfn._xlws.FILTER(#REF!,(#REF!>=DATE(2025,MONTH('MES CERRADO'!AI2),1))*(#REF!<=EOMONTH('MES CERRADO'!AI2,0))*(#REF!<>""))))=1,"-",COUNTA(_xlfn.UNIQUE(_xlfn._xlws.FILTER(#REF!,(#REF!>=DATE(2025,MONTH('MES CERRADO'!AI2),1))*(#REF!<=EOMONTH('MES CERRADO'!AI2,0))*(#REF!<>"")))))} -> - | ... AM67: {=IF(COUNTA(_xlfn.UNIQUE(_xlfn._xlws.FILTER(#REF!,(#REF!>=DATE(2025,MONTH('MES CERRADO'!AM2),1))*(#REF!<=EOMONTH('MES CERRADO'!AM2,0))*(#REF!<>""))))=1,"-",COUNTA(_xlfn.UNIQUE(_xlfn._xlws.FILTER(#REF!,(#REF!>=DATE(2025,MONTH('MES CERRADO'!AM2),1))*(#REF!<=EOMONTH('MES CERRADO'!AM2,0))*(#REF!<>"")))))} -> - | AN67: {=IF(COUNTA(_xlfn.UNIQUE(_xlfn._xlws.FILTER(#REF!,(#REF!>=DATE(2026,MONTH('MES CERRADO'!AN2),1))*(#REF!<=EOMONTH('MES CERRADO'!AN2,0))*(#REF!<>""))))=1,"-",COUNTA(_xlfn.UNIQUE(_xlfn._xlws.FILTER(#REF!,(#REF!>=DATE(2026,MONTH('MES CERRADO'!AN2),1))*(#REF!<=EOMONTH('MES CERRADO'!AN2,0))*(#REF!<>"")))))} -> - | AO67: {=IF(COUNTA(_xlfn.UNIQUE(_xlfn._xlws.FILTER(#REF!,(#REF!>=DATE(2026,MONTH('MES CERRADO'!AO2),1))*(#REF!<=EOMONTH('MES CERRADO'!AO2,0))*(#REF!<>""))))=1,"-",COUNTA(_xlfn.UNIQUE(_xlfn._xlws.FILTER(#REF!,(#REF!>=DATE(2026,MONTH('MES CERRADO'!AO2),1))*(#REF!<=EOMONTH('MES CERRADO'!AO2,0))*(#REF!<>"")))))} -> - | BA67: =IFERROR(AVERAGE(D67:O67),"-") -> - | BB67: =IFERROR(AVERAGE(P67:AA67),"-") -> - | BC67: =IFERROR(SUMIFS(AB67:AM67,AB67:AM67,"<>0",AB67:AM67,"<>-",AB67:AM67,"<>",AB67:AM67,"<> ")/COUNTIFS(AB67:AM67,"<>0",AB67:AM67,"<>-",AB67:AM67,"<>",AB67:AM67,"<> "),"-") -> -
B68: CANT DE UNIDADES SALIDA - PROMEDIO MES | C68: UNI | AB68: =IFERROR((SUMIFS('TABLERO DIARIO'!#REF!,'TABLERO DIARIO'!$I$2:$ZZ$2,">="&DATE(2025,MONTH(AB$2),1),'TABLERO DIARIO'!$I$2:$ZZ$2,"<="&EOMONTH(AB$2,0))/COUNTIFS('TABLERO DIARIO'!$I$2:$ZZ$2,">="&DATE(2025,MONTH(AB$2),1),'TABLERO DIARIO'!$I$2:$ZZ$2,"<="&EOMONTH(AB$2,0),'TABLERO DIARIO'!#REF!,"<>0",'TABLERO DIARIO'!#REF!,"<>-",'TABLERO DIARIO'!#REF!,"<>")),"-") -> - | AC68: =IFERROR((SUMIFS('TABLERO DIARIO'!#REF!,'TABLERO DIARIO'!$I$2:$ZZ$2,">="&DATE(2025,MONTH(AC$2),1),'TABLERO DIARIO'!$I$2:$ZZ$2,"<="&EOMONTH(AC$2,0))/COUNTIFS('TABLERO DIARIO'!$I$2:$ZZ$2,">="&DATE(2025,MONTH(AC$2),1),'TABLERO DIARIO'!$I$2:$ZZ$2,"<="&EOMONTH(AC$2,0),'TABLERO DIARIO'!#REF!,"<>0",'TABLERO DIARIO'!#REF!,"<>-",'TABLERO DIARIO'!#REF!,"<>")),"-") -> - | AD68: =IFERROR((SUMIFS('TABLERO DIARIO'!#REF!,'TABLERO DIARIO'!$I$2:$ZZ$2,">="&DATE(2025,MONTH(AD$2),1),'TABLERO DIARIO'!$I$2:$ZZ$2,"<="&EOMONTH(AD$2,0))/COUNTIFS('TABLERO DIARIO'!$I$2:$ZZ$2,">="&DATE(2025,MONTH(AD$2),1),'TABLERO DIARIO'!$I$2:$ZZ$2,"<="&EOMONTH(AD$2,0),'TABLERO DIARIO'!#REF!,"<>0",'TABLERO DIARIO'!#REF!,"<>-",'TABLERO DIARIO'!#REF!,"<>")),"-") -> - | AE68: =IFERROR((SUMIFS('TABLERO DIARIO'!#REF!,'TABLERO DIARIO'!$I$2:$ZZ$2,">="&DATE(2025,MONTH(AE$2),1),'TABLERO DIARIO'!$I$2:$ZZ$2,"<="&EOMONTH(AE$2,0))/COUNTIFS('TABLERO DIARIO'!$I$2:$ZZ$2,">="&DATE(2025,MONTH(AE$2),1),'TABLERO DIARIO'!$I$2:$ZZ$2,"<="&EOMONTH(AE$2,0),'TABLERO DIARIO'!#REF!,"<>0",'TABLERO DIARIO'!#REF!,"<>-",'TABLERO DIARIO'!#REF!,"<>")),"-") -> - | AF68: =IFERROR((SUMIFS('TABLERO DIARIO'!#REF!,'TABLERO DIARIO'!$I$2:$ZZ$2,">="&DATE(2025,MONTH(AF$2),1),'TABLERO DIARIO'!$I$2:$ZZ$2,"<="&EOMONTH(AF$2,0))/COUNTIFS('TABLERO DIARIO'!$I$2:$ZZ$2,">="&DATE(2025,MONTH(AF$2),1),'TABLERO DIARIO'!$I$2:$ZZ$2,"<="&EOMONTH(AF$2,0),'TABLERO DIARIO'!#REF!,"<>0",'TABLERO DIARIO'!#REF!,"<>-",'TABLERO DIARIO'!#REF!,"<>")),"-") -> - | AG68: =IFERROR((SUMIFS('TABLERO DIARIO'!#REF!,'TABLERO DIARIO'!$I$2:$ZZ$2,">="&DATE(2025,MONTH(AG$2),1),'TABLERO DIARIO'!$I$2:$ZZ$2,"<="&EOMONTH(AG$2,0))/COUNTIFS('TABLERO DIARIO'!$I$2:$ZZ$2,">="&DATE(2025,MONTH(AG$2),1),'TABLERO DIARIO'!$I$2:$ZZ$2,"<="&EOMONTH(AG$2,0),'TABLERO DIARIO'!#REF!,"<>0",'TABLERO DIARIO'!#REF!,"<>-",'TABLERO DIARIO'!#REF!,"<>")),"-") -> - | AH68: =IFERROR((SUMIFS('TABLERO DIARIO'!#REF!,'TABLERO DIARIO'!$I$2:$ZZ$2,">="&DATE(2025,MONTH(AH$2),1),'TABLERO DIARIO'!$I$2:$ZZ$2,"<="&EOMONTH(AH$2,0))/COUNTIFS('TABLERO DIARIO'!$I$2:$ZZ$2,">="&DATE(2025,MONTH(AH$2),1),'TABLERO DIARIO'!$I$2:$ZZ$2,"<="&EOMONTH(AH$2,0),'TABLERO DIARIO'!#REF!,"<>0",'TABLERO DIARIO'!#REF!,"<>-",'TABLERO DIARIO'!#REF!,"<>")),"-") -> - | AI68: =IFERROR((SUMIFS('TABLERO DIARIO'!#REF!,'TABLERO DIARIO'!$I$2:$ZZ$2,">="&DATE(2025,MONTH(AI$2),1),'TABLERO DIARIO'!$I$2:$ZZ$2,"<="&EOMONTH(AI$2,0))/COUNTIFS('TABLERO DIARIO'!$I$2:$ZZ$2,">="&DATE(2025,MONTH(AI$2),1),'TABLERO DIARIO'!$I$2:$ZZ$2,"<="&EOMONTH(AI$2,0),'TABLERO DIARIO'!#REF!,"<>0",'TABLERO DIARIO'!#REF!,"<>-",'TABLERO DIARIO'!#REF!,"<>")),"-") -> - | AJ68: =IFERROR((SUMIFS('TABLERO DIARIO'!#REF!,'TABLERO DIARIO'!$I$2:$ZZ$2,">="&DATE(2025,MONTH(AJ$2),1),'TABLERO DIARIO'!$I$2:$ZZ$2,"<="&EOMONTH(AJ$2,0))/COUNTIFS('TABLERO DIARIO'!$I$2:$ZZ$2,">="&DATE(2025,MONTH(AJ$2),1),'TABLERO DIARIO'!$I$2:$ZZ$2,"<="&EOMONTH(AJ$2,0),'TABLERO DIARIO'!#REF!,"<>0",'TABLERO DIARIO'!#REF!,"<>-",'TABLERO DIARIO'!#REF!,"<>")),"-") -> - | AK68: =IFERROR((SUMIFS('TABLERO DIARIO'!#REF!,'TABLERO DIARIO'!$I$2:$AEV$2,">="&DATE(2025,MONTH(AK$2),1),'TABLERO DIARIO'!$I$2:$AEV$2,"<="&EOMONTH(AK$2,0))/COUNTIFS('TABLERO DIARIO'!$I$2:$AEV$2,">="&DATE(2025,MONTH(AK$2),1),'TABLERO DIARIO'!$I$2:$AEV$2,"<="&EOMONTH(AK$2,0),'TABLERO DIARIO'!#REF!,"<>0",'TABLERO DIARIO'!#REF!,"<>-",'TABLERO DIARIO'!#REF!,"<>")),"-") -> - | AL68: =IFERROR((SUMIFS('TABLERO DIARIO'!#REF!,'TABLERO DIARIO'!$AEV$2:$AMA$2,">="&DATE(2025,MONTH(AL$2),1),'TABLERO DIARIO'!$AEV$2:$AMA$2,"<="&EOMONTH(AL$2,0))/COUNTIFS('TABLERO DIARIO'!$AEV$2:$AMA$2,">="&DATE(2025,MONTH(AL$2),1),'TABLERO DIARIO'!$AEV$2:$AMA$2,"<="&EOMONTH(AL$2,0),'TABLERO DIARIO'!#REF!,"<>0",'TABLERO DIARIO'!#REF!,"<>-",'TABLERO DIARIO'!#REF!,"<>")),"-") -> - | AM68: =IFERROR((SUMIFS('TABLERO DIARIO'!#REF!,'TABLERO DIARIO'!$AEV$2:$AMA$2,">="&DATE(2025,MONTH(AM$2),1),'TABLERO DIARIO'!$AEV$2:$AMA$2,"<="&EOMONTH(AM$2,0))/COUNTIFS('TABLERO DIARIO'!$AEV$2:$AMA$2,">="&DATE(2025,MONTH(AM$2),1),'TABLERO DIARIO'!$AEV$2:$AMA$2,"<="&EOMONTH(AM$2,0),'TABLERO DIARIO'!#REF!,"<>0",'TABLERO DIARIO'!#REF!,"<>-",'TABLERO DIARIO'!#REF!,"<>")),"-") -> - | AN68: =IFERROR((SUMIFS('TABLERO DIARIO'!#REF!,'TABLERO DIARIO'!$ALW$2:$ASW$2,">="&DATE(2026,MONTH(AN$2),1),'TABLERO DIARIO'!$ALW$2:$ASW$2,"<="&EOMONTH(AN$2,0))/COUNTIFS('TABLERO DIARIO'!$ALW$2:$ASW$2,">="&DATE(2026,MONTH(AN$2),1),'TABLERO DIARIO'!$ALW$2:$ASW$2,"<="&EOMONTH(AN$2,0),'TABLERO DIARIO'!#REF!,"<>0",'TABLERO DIARIO'!#REF!,"<>-",'TABLERO DIARIO'!#REF!,"<>")),"-") -> - | AO68: =IFERROR((SUMIFS('TABLERO DIARIO'!#REF!,'TABLERO DIARIO'!$ALW$2:$ASW$2,">="&DATE(2026,MONTH(AO$2),1),'TABLERO DIARIO'!$ALW$2:$ASW$2,"<="&EOMONTH(AO$2,0))/COUNTIFS('TABLERO DIARIO'!$ALW$2:$ASW$2,">="&DATE(2026,MONTH(AO$2),1),'TABLERO DIARIO'!$ALW$2:$ASW$2,"<="&EOMONTH(AO$2,0),'TABLERO DIARIO'!#REF!,"<>0",'TABLERO DIARIO'!#REF!,"<>-",'TABLERO DIARIO'!#REF!,"<>")),"-") -> - | BA68: =IFERROR(AVERAGE(D68:O68),"-") -> - | BB68: =IFERROR(AVERAGE(P68:AA68),"-") -> - | BC68: =IFERROR(SUMIFS(AB68:AM68,AB68:AM68,"<>0",AB68:AM68,"<>-",AB68:AM68,"<>",AB68:AM68,"<> ")/COUNTIFS(AB68:AM68,"<>0",AB68:AM68,"<>-",AB68:AM68,"<>",AB68:AM68,"<> "),"-") -> -
B69: HORARIO FIN DESPACHO - PROMEDIO MES | C69: HS | AB69: =IFERROR(SUMIFS('TABLERO DIARIO'!$F$36:$ZZ$36,'TABLERO DIARIO'!$F$36:$ZZ$36,"<>0",'TABLERO DIARIO'!$F$36:$ZZ$36,"<>-",'TABLERO DIARIO'!$F$2:$ZZ$2,">="&DATE(2025,MONTH(AB$2),1),'TABLERO DIARIO'!$F$2:$ZZ$2,"<="&EOMONTH(AB$2,0))/COUNTIFS('TABLERO DIARIO'!$F$36:$ZZ$36,"<>0",'TABLERO DIARIO'!$F$36:$ZZ$36,"<>-",'TABLERO DIARIO'!$F$36:$ZZ$36,"<>",'TABLERO DIARIO'!$F$2:$ZZ$2,">="&DATE(2025,MONTH(AB$2),1),'TABLERO DIARIO'!$F$2:$ZZ$2,"<="&EOMONTH(AB$2,0)),"-") -> - | AC69: =IFERROR(SUMIFS('TABLERO DIARIO'!$F$36:$ZZ$36,'TABLERO DIARIO'!$F$36:$ZZ$36,"<>0",'TABLERO DIARIO'!$F$36:$ZZ$36,"<>-",'TABLERO DIARIO'!$F$2:$ZZ$2,">="&DATE(2025,MONTH(AC$2),1),'TABLERO DIARIO'!$F$2:$ZZ$2,"<="&EOMONTH(AC$2,0))/COUNTIFS('TABLERO DIARIO'!$F$36:$ZZ$36,"<>0",'TABLERO DIARIO'!$F$36:$ZZ$36,"<>-",'TABLERO DIARIO'!$F$36:$ZZ$36,"<>",'TABLERO DIARIO'!$F$2:$ZZ$2,">="&DATE(2025,MONTH(AC$2),1),'TABLERO DIARIO'!$F$2:$ZZ$2,"<="&EOMONTH(AC$2,0)),"-") -> 0.2791956 | AD69: =IFERROR(SUMIFS('TABLERO DIARIO'!$F$36:$ZZ$36,'TABLERO DIARIO'!$F$36:$ZZ$36,"<>0",'TABLERO DIARIO'!$F$36:$ZZ$36,"<>-",'TABLERO DIARIO'!$F$2:$ZZ$2,">="&DATE(2025,MONTH(AD$2),1),'TABLERO DIARIO'!$F$2:$ZZ$2,"<="&EOMONTH(AD$2,0))/COUNTIFS('TABLERO DIARIO'!$F$36:$ZZ$36,"<>0",'TABLERO DIARIO'!$F$36:$ZZ$36,"<>-",'TABLERO DIARIO'!$F$36:$ZZ$36,"<>",'TABLERO DIARIO'!$F$2:$ZZ$2,">="&DATE(2025,MONTH(AD$2),1),'TABLERO DIARIO'!$F$2:$ZZ$2,"<="&EOMONTH(AD$2,0)),"-") -> 0.28321759 | AE69: =IFERROR(SUMIFS('TABLERO DIARIO'!$F$36:$ZZ$36,'TABLERO DIARIO'!$F$36:$ZZ$36,"<>0",'TABLERO DIARIO'!$F$36:$ZZ$36,"<>-",'TABLERO DIARIO'!$F$2:$ZZ$2,">="&DATE(2025,MONTH(AE$2),1),'TABLERO DIARIO'!$F$2:$ZZ$2,"<="&EOMONTH(AE$2,0))/COUNTIFS('TABLERO DIARIO'!$F$36:$ZZ$36,"<>0",'TABLERO DIARIO'!$F$36:$ZZ$36,"<>-",'TABLERO DIARIO'!$F$36:$ZZ$36,"<>",'TABLERO DIARIO'!$F$2:$ZZ$2,">="&DATE(2025,MONTH(AE$2),1),'TABLERO DIARIO'!$F$2:$ZZ$2,"<="&EOMONTH(AE$2,0)),"-") -> 0.28709491 | AF69: =IFERROR(SUMIFS('TABLERO DIARIO'!$F$36:$ZZ$36,'TABLERO DIARIO'!$F$36:$ZZ$36,"<>0",'TABLERO DIARIO'!$F$36:$ZZ$36,"<>-",'TABLERO DIARIO'!$F$2:$ZZ$2,">="&DATE(2025,MONTH(AF$2),1),'TABLERO DIARIO'!$F$2:$ZZ$2,"<="&EOMONTH(AF$2,0))/COUNTIFS('TABLERO DIARIO'!$F$36:$ZZ$36,"<>0",'TABLERO DIARIO'!$F$36:$ZZ$36,"<>-",'TABLERO DIARIO'!$F$36:$ZZ$36,"<>",'TABLERO DIARIO'!$F$2:$ZZ$2,">="&DATE(2025,MONTH(AF$2),1),'TABLERO DIARIO'!$F$2:$ZZ$2,"<="&EOMONTH(AF$2,0)),"-") -> 0.27660256 | AG69: =IFERROR(SUMIFS('TABLERO DIARIO'!$F$36:$ZZ$36,'TABLERO DIARIO'!$F$36:$ZZ$36,"<>0",'TABLERO DIARIO'!$F$36:$ZZ$36,"<>-",'TABLERO DIARIO'!$F$2:$ZZ$2,">="&DATE(2025,MONTH(AG$2),1),'TABLERO DIARIO'!$F$2:$ZZ$2,"<="&EOMONTH(AG$2,0))/COUNTIFS('TABLERO DIARIO'!$F$36:$ZZ$36,"<>0",'TABLERO DIARIO'!$F$36:$ZZ$36,"<>-",'TABLERO DIARIO'!$F$36:$ZZ$36,"<>",'TABLERO DIARIO'!$F$2:$ZZ$2,">="&DATE(2025,MONTH(AG$2),1),'TABLERO DIARIO'!$F$2:$ZZ$2,"<="&EOMONTH(AG$2,0)),"-") -> 0.28794192 | AH69: =IFERROR(SUMIFS('TABLERO DIARIO'!$F$36:$ZZ$36,'TABLERO DIARIO'!$F$36:$ZZ$36,"<>0",'TABLERO DIARIO'!$F$36:$ZZ$36,"<>-",'TABLERO DIARIO'!$F$2:$ZZ$2,">="&DATE(2025,MONTH(AH$2),1),'TABLERO DIARIO'!$F$2:$ZZ$2,"<="&EOMONTH(AH$2,0))/COUNTIFS('TABLERO DIARIO'!$F$36:$ZZ$36,"<>0",'TABLERO DIARIO'!$F$36:$ZZ$36,"<>-",'TABLERO DIARIO'!$F$36:$ZZ$36,"<>",'TABLERO DIARIO'!$F$2:$ZZ$2,">="&DATE(2025,MONTH(AH$2),1),'TABLERO DIARIO'!$F$2:$ZZ$2,"<="&EOMONTH(AH$2,0)),"-") -> 0.30074786 | AI69: =IFERROR(SUMIFS('TABLERO DIARIO'!$F$36:$ZZ$36,'TABLERO DIARIO'!$F$36:$ZZ$36,"<>0",'TABLERO DIARIO'!$F$36:$ZZ$36,"<>-",'TABLERO DIARIO'!$F$2:$ZZ$2,">="&DATE(2025,MONTH(AI$2),1),'TABLERO DIARIO'!$F$2:$ZZ$2,"<="&EOMONTH(AI$2,0))/COUNTIFS('TABLERO DIARIO'!$F$36:$ZZ$36,"<>0",'TABLERO DIARIO'!$F$36:$ZZ$36,"<>-",'TABLERO DIARIO'!$F$36:$ZZ$36,"<>",'TABLERO DIARIO'!$F$2:$ZZ$2,">="&DATE(2025,MONTH(AI$2),1),'TABLERO DIARIO'!$F$2:$ZZ$2,"<="&EOMONTH(AI$2,0)),"-") -> 0.28378739 | AJ69: =IFERROR(SUMIFS('TABLERO DIARIO'!$F$36:$ZZ$36,'TABLERO DIARIO'!$F$36:$ZZ$36,"<>0",'TABLERO DIARIO'!$F$36:$ZZ$36,"<>-",'TABLERO DIARIO'!$F$2:$ZZ$2,">="&DATE(2025,MONTH(AJ$2),1),'TABLERO DIARIO'!$F$2:$ZZ$2,"<="&EOMONTH(AJ$2,0))/COUNTIFS('TABLERO DIARIO'!$F$36:$ZZ$36,"<>0",'TABLERO DIARIO'!$F$36:$ZZ$36,"<>-",'TABLERO DIARIO'!$F$36:$ZZ$36,"<>",'TABLERO DIARIO'!$F$2:$ZZ$2,">="&DATE(2025,MONTH(AJ$2),1),'TABLERO DIARIO'!$F$2:$ZZ$2,"<="&EOMONTH(AJ$2,0)),"-") -> 0.28510802 | AK69: =IFERROR(SUMIFS('TABLERO DIARIO'!$F$36:$AEV$36,'TABLERO DIARIO'!$F$36:$AEV$36,"<>0",'TABLERO DIARIO'!$F$36:$AEV$36,"<>-",'TABLERO DIARIO'!$F$2:$AEV$2,">="&DATE(2025,MONTH(AK$2),1),'TABLERO DIARIO'!$F$2:$AEV$2,"<="&EOMONTH(AK$2,0))/COUNTIFS('TABLERO DIARIO'!$F$36:$AEV$36,"<>0",'TABLERO DIARIO'!$F$36:$AEV$36,"<>-",'TABLERO DIARIO'!$F$36:$AEV$36,"<>",'TABLERO DIARIO'!$F$2:$AEV$2,">="&DATE(2025,MONTH(AK$2),1),'TABLERO DIARIO'!$F$2:$AEV$2,"<="&EOMONTH(AK$2,0)),"-") -> 0.27327675 | AL69: =IFERROR(SUMIFS('TABLERO DIARIO'!$AEV$36:$AMA$36,'TABLERO DIARIO'!$AEV$36:$AMA$36,"<>0",'TABLERO DIARIO'!$AEV$36:$AMA$36,"<>-",'TABLERO DIARIO'!$AEV$2:$AMA$2,">="&DATE(2025,MONTH(AL$2),1),'TABLERO DIARIO'!$AEV$2:$AMA$2,"<="&EOMONTH(AL$2,0))/COUNTIFS('TABLERO DIARIO'!$AEV$36:$AMA$36,"<>0",'TABLERO DIARIO'!$AEV$36:$AMA$36,"<>-",'TABLERO DIARIO'!$AEV$36:$AMA$36,"<>",'TABLERO DIARIO'!$AEV$2:$AMA$2,">="&DATE(2025,MONTH(AL$2),1),'TABLERO DIARIO'!$AEV$2:$AMA$2,"<="&EOMONTH(AL$2,0)),"-") -> 0.27806713 | AM69: =IFERROR(SUMIFS('TABLERO DIARIO'!$AEV$36:$AMA$36,'TABLERO DIARIO'!$AEV$36:$AMA$36,"<>0",'TABLERO DIARIO'!$AEV$36:$AMA$36,"<>-",'TABLERO DIARIO'!$AEV$2:$AMA$2,">="&DATE(2025,MONTH(AM$2),1),'TABLERO DIARIO'!$AEV$2:$AMA$2,"<="&EOMONTH(AM$2,0))/COUNTIFS('TABLERO DIARIO'!$AEV$36:$AMA$36,"<>0",'TABLERO DIARIO'!$AEV$36:$AMA$36,"<>-",'TABLERO DIARIO'!$AEV$36:$AMA$36,"<>",'TABLERO DIARIO'!$AEV$2:$AMA$2,">="&DATE(2025,MONTH(AM$2),1),'TABLERO DIARIO'!$AEV$2:$AMA$2,"<="&EOMONTH(AM$2,0)),"-") -> 0.31458333 | AN69: =IFERROR(SUMIFS('TABLERO DIARIO'!$ALW$36:$ASW$36,'TABLERO DIARIO'!$ALW$36:$ASW$36,"<>0",'TABLERO DIARIO'!$ALW$36:$ASW$36,"<>-",'TABLERO DIARIO'!$ALW$2:$ASW$2,">="&DATE(2026,MONTH(AN$2),1),'TABLERO DIARIO'!$ALW$2:$ASW$2,"<="&EOMONTH(AN$2,0))/COUNTIFS('TABLERO DIARIO'!$ALW$36:$ASW$36,"<>0",'TABLERO DIARIO'!$ALW$36:$ASW$36,"<>-",'TABLERO DIARIO'!$ALW$36:$ASW$36,"<>",'TABLERO DIARIO'!$ALW$2:$ASW$2,">="&DATE(2026,MONTH(AN$2),1),'TABLERO DIARIO'!$ALW$2:$ASW$2,"<="&EOMONTH(AN$2,0)),"-") -> 0.30942842 | AO69: =IFERROR(SUMIFS('TABLERO DIARIO'!$ALW$36:$ASW$36,'TABLERO DIARIO'!$ALW$36:$ASW$36,"<>0",'TABLERO DIARIO'!$ALW$36:$ASW$36,"<>-",'TABLERO DIARIO'!$ALW$2:$ASW$2,">="&DATE(2026,MONTH(AO$2),1),'TABLERO DIARIO'!$ALW$2:$ASW$2,"<="&EOMONTH(AO$2,0))/COUNTIFS('TABLERO DIARIO'!$ALW$36:$ASW$36,"<>0",'TABLERO DIARIO'!$ALW$36:$ASW$36,"<>-",'TABLERO DIARIO'!$ALW$36:$ASW$36,"<>",'TABLERO DIARIO'!$ALW$2:$ASW$2,">="&DATE(2026,MONTH(AO$2),1),'TABLERO DIARIO'!$ALW$2:$ASW$2,"<="&EOMONTH(AO$2,0)),"-") -> 0.24718915 | BA69: =IFERROR(AVERAGE(D69:O69),"-") -> - | BB69: =IFERROR(AVERAGE(P69:AA69),"-") -> - | BC69: =IFERROR(SUMIFS(AB69:AM69,AB69:AM69,"<>0",AB69:AM69,"<>-",AB69:AM69,"<>",AB69:AM69,"<> ")/COUNTIFS(AB69:AM69,"<>0",AB69:AM69,"<>-",AB69:AM69,"<>",AB69:AM69,"<> "),"-") -> 0.28632937
B70: FALTANTES ABASTECIMIENTO CATTER | C70: CAJAS | AB70: =IFERROR(IF(-1*SUMIFS(#REF!,#REF!,">="&DATE(2025,MONTH(AB$2),1),#REF!,"<="&EOMONTH(AB$2,0),#REF!,"Cajas")=0,"-",-1*SUMIFS(#REF!,#REF!,">="&DATE(2025,MONTH(AB$2),1),#REF!,"<="&EOMONTH(AB$2,0),#REF!,"Cajas")),"-") -> - | AC70: =IFERROR(IF(-1*SUMIFS(#REF!,#REF!,">="&DATE(2025,MONTH(AC$2),1),#REF!,"<="&EOMONTH(AC$2,0),#REF!,"Cajas")=0,"-",-1*SUMIFS(#REF!,#REF!,">="&DATE(2025,MONTH(AC$2),1),#REF!,"<="&EOMONTH(AC$2,0),#REF!,"Cajas")),"-") -> - | AD70: =IFERROR(IF(-1*SUMIFS(#REF!,#REF!,">="&DATE(2025,MONTH(AD$2),1),#REF!,"<="&EOMONTH(AD$2,0),#REF!,"Cajas")=0,"-",-1*SUMIFS(#REF!,#REF!,">="&DATE(2025,MONTH(AD$2),1),#REF!,"<="&EOMONTH(AD$2,0),#REF!,"Cajas")),"-") -> - | AE70: =IFERROR(IF(-1*SUMIFS(#REF!,#REF!,">="&DATE(2025,MONTH(AE$2),1),#REF!,"<="&EOMONTH(AE$2,0),#REF!,"Cajas")=0,"-",-1*SUMIFS(#REF!,#REF!,">="&DATE(2025,MONTH(AE$2),1),#REF!,"<="&EOMONTH(AE$2,0),#REF!,"Cajas")),"-") -> - | AF70: =IFERROR(IF(-1*SUMIFS(#REF!,#REF!,">="&DATE(2025,MONTH(AF$2),1),#REF!,"<="&EOMONTH(AF$2,0),#REF!,"Cajas")=0,"-",-1*SUMIFS(#REF!,#REF!,">="&DATE(2025,MONTH(AF$2),1),#REF!,"<="&EOMONTH(AF$2,0),#REF!,"Cajas")),"-") -> - | AG70: =IFERROR(IF(-1*SUMIFS(#REF!,#REF!,">="&DATE(2025,MONTH(AG$2),1),#REF!,"<="&EOMONTH(AG$2,0),#REF!,"Cajas")=0,"-",-1*SUMIFS(#REF!,#REF!,">="&DATE(2025,MONTH(AG$2),1),#REF!,"<="&EOMONTH(AG$2,0),#REF!,"Cajas")),"-") -> - | AH70: =IFERROR(IF(-1*SUMIFS(#REF!,#REF!,">="&DATE(2025,MONTH(AH$2),1),#REF!,"<="&EOMONTH(AH$2,0),#REF!,"Cajas")=0,"-",-1*SUMIFS(#REF!,#REF!,">="&DATE(2025,MONTH(AH$2),1),#REF!,"<="&EOMONTH(AH$2,0),#REF!,"Cajas")),"-") -> - | AI70: =IFERROR(IF(-1*SUMIFS(#REF!,#REF!,">="&DATE(2025,MONTH(AI$2),1),#REF!,"<="&EOMONTH(AI$2,0),#REF!,"Cajas")=0,"-",-1*SUMIFS(#REF!,#REF!,">="&DATE(2025,MONTH(AI$2),1),#REF!,"<="&EOMONTH(AI$2,0),#REF!,"Cajas")),"-") -> - | ... AM70: =IFERROR(IF(-1*SUMIFS(#REF!,#REF!,">="&DATE(2025,MONTH(AM$2),1),#REF!,"<="&EOMONTH(AM$2,0),#REF!,"Cajas")=0,"-",-1*SUMIFS(#REF!,#REF!,">="&DATE(2025,MONTH(AM$2),1),#REF!,"<="&EOMONTH(AM$2,0),#REF!,"Cajas")),"-") -> - | AN70: =IFERROR(IF(-1*SUMIFS(#REF!,#REF!,">="&DATE(2026,MONTH(AN$2),1),#REF!,"<="&EOMONTH(AN$2,0),#REF!,"Cajas")=0,"-",-1*SUMIFS(#REF!,#REF!,">="&DATE(2026,MONTH(AN$2),1),#REF!,"<="&EOMONTH(AN$2,0),#REF!,"Cajas")),"-") -> - | AO70: =IFERROR(IF(-1*SUMIFS(#REF!,#REF!,">="&DATE(2026,MONTH(AO$2),1),#REF!,"<="&EOMONTH(AO$2,0),#REF!,"Cajas")=0,"-",-1*SUMIFS(#REF!,#REF!,">="&DATE(2026,MONTH(AO$2),1),#REF!,"<="&EOMONTH(AO$2,0),#REF!,"Cajas")),"-") -> - | BA70: =IFERROR(AVERAGE(D70:O70),"-") -> - | BB70: =IFERROR(AVERAGE(P70:AA70),"-") -> - | BC70: =IFERROR(SUMIFS(AB70:AM70,AB70:AM70,"<>0",AB70:AM70,"<>-",AB70:AM70,"<>",AB70:AM70,"<> ")/COUNTIFS(AB70:AM70,"<>0",AB70:AM70,"<>-",AB70:AM70,"<>",AB70:AM70,"<> "),"-") -> -
B71: FALTANTES ABASTECIMIENTO CATTER | C71: PALLETS | AB71: =IFERROR(IF(-1*SUMIFS(#REF!,#REF!,">="&DATE(2025,MONTH(AB$2),1),#REF!,"<="&EOMONTH(AB$2,0),#REF!,"Pallet")=0,"-",-1*SUMIFS(#REF!,#REF!,">="&DATE(2025,MONTH(AB$2),1),#REF!,"<="&EOMONTH(AB$2,0),#REF!,"Pallet")),"-") -> - | AC71: =IFERROR(IF(-1*SUMIFS(#REF!,#REF!,">="&DATE(2025,MONTH(AC$2),1),#REF!,"<="&EOMONTH(AC$2,0),#REF!,"Pallet")=0,"-",-1*SUMIFS(#REF!,#REF!,">="&DATE(2025,MONTH(AC$2),1),#REF!,"<="&EOMONTH(AC$2,0),#REF!,"Pallet")),"-") -> - | AD71: =IFERROR(IF(-1*SUMIFS(#REF!,#REF!,">="&DATE(2025,MONTH(AD$2),1),#REF!,"<="&EOMONTH(AD$2,0),#REF!,"Pallet")=0,"-",-1*SUMIFS(#REF!,#REF!,">="&DATE(2025,MONTH(AD$2),1),#REF!,"<="&EOMONTH(AD$2,0),#REF!,"Pallet")),"-") -> - | AE71: =IFERROR(IF(-1*SUMIFS(#REF!,#REF!,">="&DATE(2025,MONTH(AE$2),1),#REF!,"<="&EOMONTH(AE$2,0),#REF!,"Pallet")=0,"-",-1*SUMIFS(#REF!,#REF!,">="&DATE(2025,MONTH(AE$2),1),#REF!,"<="&EOMONTH(AE$2,0),#REF!,"Pallet")),"-") -> - | AF71: =IFERROR(IF(-1*SUMIFS(#REF!,#REF!,">="&DATE(2025,MONTH(AF$2),1),#REF!,"<="&EOMONTH(AF$2,0),#REF!,"Pallet")=0,"-",-1*SUMIFS(#REF!,#REF!,">="&DATE(2025,MONTH(AF$2),1),#REF!,"<="&EOMONTH(AF$2,0),#REF!,"Pallet")),"-") -> - | AG71: =IFERROR(IF(-1*SUMIFS(#REF!,#REF!,">="&DATE(2025,MONTH(AG$2),1),#REF!,"<="&EOMONTH(AG$2,0),#REF!,"Pallet")=0,"-",-1*SUMIFS(#REF!,#REF!,">="&DATE(2025,MONTH(AG$2),1),#REF!,"<="&EOMONTH(AG$2,0),#REF!,"Pallet")),"-") -> - | AH71: =IFERROR(IF(-1*SUMIFS(#REF!,#REF!,">="&DATE(2025,MONTH(AH$2),1),#REF!,"<="&EOMONTH(AH$2,0),#REF!,"Pallet")=0,"-",-1*SUMIFS(#REF!,#REF!,">="&DATE(2025,MONTH(AH$2),1),#REF!,"<="&EOMONTH(AH$2,0),#REF!,"Pallet")),"-") -> - | AI71: =IFERROR(IF(-1*SUMIFS(#REF!,#REF!,">="&DATE(2025,MONTH(AI$2),1),#REF!,"<="&EOMONTH(AI$2,0),#REF!,"Pallet")=0,"-",-1*SUMIFS(#REF!,#REF!,">="&DATE(2025,MONTH(AI$2),1),#REF!,"<="&EOMONTH(AI$2,0),#REF!,"Pallet")),"-") -> - | ... AM71: =IFERROR(IF(-1*SUMIFS(#REF!,#REF!,">="&DATE(2025,MONTH(AM$2),1),#REF!,"<="&EOMONTH(AM$2,0),#REF!,"Pallet")=0,"-",-1*SUMIFS(#REF!,#REF!,">="&DATE(2025,MONTH(AM$2),1),#REF!,"<="&EOMONTH(AM$2,0),#REF!,"Pallet")),"-") -> - | AN71: =IFERROR(IF(-1*SUMIFS(#REF!,#REF!,">="&DATE(2026,MONTH(AN$2),1),#REF!,"<="&EOMONTH(AN$2,0),#REF!,"Pallet")=0,"-",-1*SUMIFS(#REF!,#REF!,">="&DATE(2026,MONTH(AN$2),1),#REF!,"<="&EOMONTH(AN$2,0),#REF!,"Pallet")),"-") -> - | AO71: =IFERROR(IF(-1*SUMIFS(#REF!,#REF!,">="&DATE(2026,MONTH(AO$2),1),#REF!,"<="&EOMONTH(AO$2,0),#REF!,"Pallet")=0,"-",-1*SUMIFS(#REF!,#REF!,">="&DATE(2026,MONTH(AO$2),1),#REF!,"<="&EOMONTH(AO$2,0),#REF!,"Pallet")),"-") -> - | BA71: - | BB71: - | BC71: =IFERROR(SUMIFS(AB71:AM71,AB71:AM71,"<>0",AB71:AM71,"<>-",AB71:AM71,"<>",AB71:AM71,"<> ")/COUNTIFS(AB71:AM71,"<>0",AB71:AM71,"<>-",AB71:AM71,"<>",AB71:AM71,"<> "),"-") -> -
B72: FALTANTES + RECHAZOS DESPACHOS CATTER | C72: CAJAS | AB72: =IFERROR(IF(-1*SUMIFS(#REF!,#REF!,">="&DATE(2025,MONTH(AB$2),1),#REF!,"<="&EOMONTH(AB$2,0))=0,"-",-1*SUMIFS(#REF!,#REF!,">="&DATE(2025,MONTH(AB$2),1),#REF!,"<="&EOMONTH(AB$2,0))),"-") -> - | AC72: =IFERROR(IF(-1*SUMIFS(#REF!,#REF!,">="&DATE(2025,MONTH(AC$2),1),#REF!,"<="&EOMONTH(AC$2,0))=0,"-",-1*SUMIFS(#REF!,#REF!,">="&DATE(2025,MONTH(AC$2),1),#REF!,"<="&EOMONTH(AC$2,0))),"-") -> - | AD72: =IFERROR(IF(-1*SUMIFS(#REF!,#REF!,">="&DATE(2025,MONTH(AD$2),1),#REF!,"<="&EOMONTH(AD$2,0))=0,"-",-1*SUMIFS(#REF!,#REF!,">="&DATE(2025,MONTH(AD$2),1),#REF!,"<="&EOMONTH(AD$2,0))),"-") -> - | AE72: =IFERROR(IF(-1*SUMIFS(#REF!,#REF!,">="&DATE(2025,MONTH(AE$2),1),#REF!,"<="&EOMONTH(AE$2,0))=0,"-",-1*SUMIFS(#REF!,#REF!,">="&DATE(2025,MONTH(AE$2),1),#REF!,"<="&EOMONTH(AE$2,0))),"-") -> - | AF72: =IFERROR(IF(-1*SUMIFS(#REF!,#REF!,">="&DATE(2025,MONTH(AF$2),1),#REF!,"<="&EOMONTH(AF$2,0))=0,"-",-1*SUMIFS(#REF!,#REF!,">="&DATE(2025,MONTH(AF$2),1),#REF!,"<="&EOMONTH(AF$2,0))),"-") -> - | AG72: =IFERROR(IF(-1*SUMIFS(#REF!,#REF!,">="&DATE(2025,MONTH(AG$2),1),#REF!,"<="&EOMONTH(AG$2,0))=0,"-",-1*SUMIFS(#REF!,#REF!,">="&DATE(2025,MONTH(AG$2),1),#REF!,"<="&EOMONTH(AG$2,0))),"-") -> - | AH72: =IFERROR(IF(-1*SUMIFS(#REF!,#REF!,">="&DATE(2025,MONTH(AH$2),1),#REF!,"<="&EOMONTH(AH$2,0))=0,"-",-1*SUMIFS(#REF!,#REF!,">="&DATE(2025,MONTH(AH$2),1),#REF!,"<="&EOMONTH(AH$2,0))),"-") -> - | AI72: =IFERROR(IF(-1*SUMIFS(#REF!,#REF!,">="&DATE(2025,MONTH(AI$2),1),#REF!,"<="&EOMONTH(AI$2,0))=0,"-",-1*SUMIFS(#REF!,#REF!,">="&DATE(2025,MONTH(AI$2),1),#REF!,"<="&EOMONTH(AI$2,0))),"-") -> - | ... AM72: =IFERROR(IF(-1*SUMIFS(#REF!,#REF!,">="&DATE(2025,MONTH(AM$2),1),#REF!,"<="&EOMONTH(AM$2,0))=0,"-",-1*SUMIFS(#REF!,#REF!,">="&DATE(2025,MONTH(AM$2),1),#REF!,"<="&EOMONTH(AM$2,0))),"-") -> - | AN72: =IFERROR(IF(-1*SUMIFS(#REF!,#REF!,">="&DATE(2026,MONTH(AN$2),1),#REF!,"<="&EOMONTH(AN$2,0))=0,"-",-1*SUMIFS(#REF!,#REF!,">="&DATE(2026,MONTH(AN$2),1),#REF!,"<="&EOMONTH(AN$2,0))),"-") -> - | AO72: =IFERROR(IF(-1*SUMIFS(#REF!,#REF!,">="&DATE(2026,MONTH(AO$2),1),#REF!,"<="&EOMONTH(AO$2,0))=0,"-",-1*SUMIFS(#REF!,#REF!,">="&DATE(2026,MONTH(AO$2),1),#REF!,"<="&EOMONTH(AO$2,0))),"-") -> - | BA72: =IFERROR(AVERAGE(D72:O72),"-") -> - | BB72: =IFERROR(AVERAGE(P72:AA72),"-") -> - | BC72: =IFERROR(SUMIFS(AB72:AM72,AB72:AM72,"<>0",AB72:AM72,"<>-",AB72:AM72,"<>",AB72:AM72,"<> ")/COUNTIFS(AB72:AM72,"<>0",AB72:AM72,"<>-",AB72:AM72,"<>",AB72:AM72,"<> "),"-") -> -
B73: FALTANTES + RECHAZOS DESPACHOS CATTER | C73: BOCAS | AB73: {=IF(COUNTA(_xlfn.UNIQUE(_xlfn._xlws.FILTER(#REF!,(#REF!>=DATE(2025,MONTH('MES CERRADO'!AB$2),1))*(#REF!<=EOMONTH('MES CERRADO'!AB$2,0))*(#REF!<>""))))=1,"-",COUNTA(_xlfn.UNIQUE(_xlfn._xlws.FILTER(#REF!,(#REF!>=DATE(2025,MONTH('MES CERRADO'!AB$2),1))*(#REF!<=EOMONTH('MES CERRADO'!AB$2,0))*(#REF!<>"")))))} -> - | AC73: {=IF(COUNTA(_xlfn.UNIQUE(_xlfn._xlws.FILTER(#REF!,(#REF!>=DATE(2025,MONTH('MES CERRADO'!AC$2),1))*(#REF!<=EOMONTH('MES CERRADO'!AC$2,0))*(#REF!<>""))))=1,"-",COUNTA(_xlfn.UNIQUE(_xlfn._xlws.FILTER(#REF!,(#REF!>=DATE(2025,MONTH('MES CERRADO'!AC$2),1))*(#REF!<=EOMONTH('MES CERRADO'!AC$2,0))*(#REF!<>"")))))} -> - | AD73: {=IF(COUNTA(_xlfn.UNIQUE(_xlfn._xlws.FILTER(#REF!,(#REF!>=DATE(2025,MONTH('MES CERRADO'!AD$2),1))*(#REF!<=EOMONTH('MES CERRADO'!AD$2,0))*(#REF!<>""))))=1,"-",COUNTA(_xlfn.UNIQUE(_xlfn._xlws.FILTER(#REF!,(#REF!>=DATE(2025,MONTH('MES CERRADO'!AD$2),1))*(#REF!<=EOMONTH('MES CERRADO'!AD$2,0))*(#REF!<>"")))))} -> - | AE73: {=IF(COUNTA(_xlfn.UNIQUE(_xlfn._xlws.FILTER(#REF!,(#REF!>=DATE(2025,MONTH('MES CERRADO'!AE$2),1))*(#REF!<=EOMONTH('MES CERRADO'!AE$2,0))*(#REF!<>""))))=1,"-",COUNTA(_xlfn.UNIQUE(_xlfn._xlws.FILTER(#REF!,(#REF!>=DATE(2025,MONTH('MES CERRADO'!AE$2),1))*(#REF!<=EOMONTH('MES CERRADO'!AE$2,0))*(#REF!<>"")))))} -> - | AF73: {=IF(COUNTA(_xlfn.UNIQUE(_xlfn._xlws.FILTER(#REF!,(#REF!>=DATE(2025,MONTH('MES CERRADO'!AF$2),1))*(#REF!<=EOMONTH('MES CERRADO'!AF$2,0))*(#REF!<>""))))=1,"-",COUNTA(_xlfn.UNIQUE(_xlfn._xlws.FILTER(#REF!,(#REF!>=DATE(2025,MONTH('MES CERRADO'!AF$2),1))*(#REF!<=EOMONTH('MES CERRADO'!AF$2,0))*(#REF!<>"")))))} -> - | AG73: {=IF(COUNTA(_xlfn.UNIQUE(_xlfn._xlws.FILTER(#REF!,(#REF!>=DATE(2025,MONTH('MES CERRADO'!AG$2),1))*(#REF!<=EOMONTH('MES CERRADO'!AG$2,0))*(#REF!<>""))))=1,"-",COUNTA(_xlfn.UNIQUE(_xlfn._xlws.FILTER(#REF!,(#REF!>=DATE(2025,MONTH('MES CERRADO'!AG$2),1))*(#REF!<=EOMONTH('MES CERRADO'!AG$2,0))*(#REF!<>"")))))} -> - | AH73: {=IF(COUNTA(_xlfn.UNIQUE(_xlfn._xlws.FILTER(#REF!,(#REF!>=DATE(2025,MONTH('MES CERRADO'!AH$2),1))*(#REF!<=EOMONTH('MES CERRADO'!AH$2,0))*(#REF!<>""))))=1,"-",COUNTA(_xlfn.UNIQUE(_xlfn._xlws.FILTER(#REF!,(#REF!>=DATE(2025,MONTH('MES CERRADO'!AH$2),1))*(#REF!<=EOMONTH('MES CERRADO'!AH$2,0))*(#REF!<>"")))))} -> - | AI73: {=IF(COUNTA(_xlfn.UNIQUE(_xlfn._xlws.FILTER(#REF!,(#REF!>=DATE(2025,MONTH('MES CERRADO'!AI$2),1))*(#REF!<=EOMONTH('MES CERRADO'!AI$2,0))*(#REF!<>""))))=1,"-",COUNTA(_xlfn.UNIQUE(_xlfn._xlws.FILTER(#REF!,(#REF!>=DATE(2025,MONTH('MES CERRADO'!AI$2),1))*(#REF!<=EOMONTH('MES CERRADO'!AI$2,0))*(#REF!<>"")))))} -> - | ... AM73: {=IF(COUNTA(_xlfn.UNIQUE(_xlfn._xlws.FILTER(#REF!,(#REF!>=DATE(2025,MONTH('MES CERRADO'!AM$2),1))*(#REF!<=EOMONTH('MES CERRADO'!AM$2,0))*(#REF!<>""))))=1,"-",COUNTA(_xlfn.UNIQUE(_xlfn._xlws.FILTER(#REF!,(#REF!>=DATE(2025,MONTH('MES CERRADO'!AM$2),1))*(#REF!<=EOMONTH('MES CERRADO'!AM$2,0))*(#REF!<>"")))))} -> - | AN73: {=IF(COUNTA(_xlfn.UNIQUE(_xlfn._xlws.FILTER(#REF!,(#REF!>=DATE(2026,MONTH('MES CERRADO'!AN$2),1))*(#REF!<=EOMONTH('MES CERRADO'!AN$2,0))*(#REF!<>""))))=1,"-",COUNTA(_xlfn.UNIQUE(_xlfn._xlws.FILTER(#REF!,(#REF!>=DATE(2026,MONTH('MES CERRADO'!AN$2),1))*(#REF!<=EOMONTH('MES CERRADO'!AN$2,0))*(#REF!<>"")))))} -> - | AO73: {=IF(COUNTA(_xlfn.UNIQUE(_xlfn._xlws.FILTER(#REF!,(#REF!>=DATE(2026,MONTH('MES CERRADO'!AO$2),1))*(#REF!<=EOMONTH('MES CERRADO'!AO$2,0))*(#REF!<>""))))=1,"-",COUNTA(_xlfn.UNIQUE(_xlfn._xlws.FILTER(#REF!,(#REF!>=DATE(2026,MONTH('MES CERRADO'!AO$2),1))*(#REF!<=EOMONTH('MES CERRADO'!AO$2,0))*(#REF!<>"")))))} -> - | BA73: =IFERROR(AVERAGE(D73:O73),"-") -> - | BB73: =IFERROR(AVERAGE(P73:AA73),"-") -> - | BC73: =IFERROR(SUMIFS(AB73:AM73,AB73:AM73,"<>0",AB73:AM73,"<>-",AB73:AM73,"<>",AB73:AM73,"<> ")/COUNTIFS(AB73:AM73,"<>0",AB73:AM73,"<>-",AB73:AM73,"<>",AB73:AM73,"<> "),"-") -> -
B74: FLETES COMERCIALES | C74: % | G74: 0.0315 | H74: 0.015 | I74: 0.023 | J74: 0.024 | K74: 0.022 | L74: 0.026 | M74: 0.021 | N74: 0.024 | O74: 0.0183 | P74: 0.0131 | Q74: 0.024 | R74: 0.021 | S74: 0.0271 | T74: 0.0209 | U74: 0.0217 | V74: 0.0215 | W74: 0.0242 | X74: 0.0222 | Y74: 0.0198 | Z74: 0.0183 | AA74: 0.027 | AB74: 0.023 | AC74: 0.029 | AD74: 0.027 | AE74: 0.026 | AF74: 0.026 | AG74: 0.027 | AH74: 0.02 | AI74: 0.032 | AJ74: 0.022 | AK74: 0.025 | AL74: 0.027 | AM74: 0.022 | AN74: 0.024 | BA74: =IFERROR(AVERAGE(D74:O74),"-") -> 0.022755556 | BB74: =IFERROR(AVERAGE(P74:AA74),"-") -> 0.021733333 | BC74: =IFERROR(SUMIFS(AB74:AM74,AB74:AM74,"<>0",AB74:AM74,"<>-",AB74:AM74,"<>",AB74:AM74,"<> ")/COUNTIFS(AB74:AM74,"<>0",AB74:AM74,"<>-",AB74:AM74,"<>",AB74:AM74,"<> "),"-") -> 0.0255
B75: FLETES MP DEPOSITOS/ PLANTA | C75: % | AB75: 0.001 | AC75: 0.001 | AD75: 0.002 | AE75: 0.002 | AF75: 0.002 | AG75: 0.002 | AH75: 0.003 | AI75: 0.001 | AJ75: 0.001 | AK75: 0.001 | AL75: 0.001 | AM75: 0.001 | AN75: 0.002 | BA75: =IFERROR(AVERAGE(D75:O75),"-") -> - | BB75: =IFERROR(AVERAGE(P75:AA75),"-") -> - | BC75: =IFERROR(SUMIFS(AB75:AM75,AB75:AM75,"<>0",AB75:AM75,"<>-",AB75:AM75,"<>",AB75:AM75,"<> ")/COUNTIFS(AB75:AM75,"<>0",AB75:AM75,"<>-",AB75:AM75,"<>",AB75:AM75,"<> "),"-") -> 0.0015
B76: FLETES PT DEPOSITOS/ PLANTA | C76: % | AB76: 0.001 | AC76: 0.001 | AD76: 0.001 | AE76: 0.001 | AF76: 0.002 | AG76: 0.001 | AH76: 0 | AI76: 0.001 | AJ76: 0.002 | AK76: 0.001 | AL76: 0.002 | AM76: 0.001 | AN76: 0.002 | BA76: =IFERROR(AVERAGE(D76:O76),"-") -> - | BB76: =IFERROR(AVERAGE(P76:AA76),"-") -> - | BC76: =IFERROR(SUMIFS(AB76:AM76,AB76:AM76,"<>0",AB76:AM76,"<>-",AB76:AM76,"<>",AB76:AM76,"<> ")/COUNTIFS(AB76:AM76,"<>0",AB76:AM76,"<>-",AB76:AM76,"<>",AB76:AM76,"<> "),"-") -> 0.0012727273
B77: OCUPACIÓN EN CAMIONES | C77: % | D77: - | E77: - | F77: - | G77: - | H77: - | I77: - | J77: - | K77: - | L77: - | M77: - | N77: - | O77: 0.603 | P77: 0.621 | Q77: 0.642 | R77: 0.611 | S77: 0.703 | T77: 0.727 | U77: 0.724 | V77: 0.647 | W77: 0.688 | X77: 0.651 | Y77: 0.66 | Z77: 0.701 | AA77: 0.635 | AB77: 0.634 | AC77: 0.63 | AD77: 0.607 | AE77: 0.614 | AF77: - | AG77: - | AH77: - | AI77: - | AJ77: - | AK77: - | BA77: =IFERROR(AVERAGE(D77:O77),"-") -> 0.603 | BB77: =IFERROR(AVERAGE(P77:AA77),"-") -> 0.6675 | BC77: =IFERROR(SUMIFS(AB77:AM77,AB77:AM77,"<>0",AB77:AM77,"<>-",AB77:AM77,"<>",AB77:AM77,"<> ")/COUNTIFS(AB77:AM77,"<>0",AB77:AM77,"<>-",AB77:AM77,"<>",AB77:AM77,"<> "),"-") -> 0.41416667
B79: SAC - HAMBURGUESAS/ MEDALLONES | C79: UNI | D79: 41 | E79: 42 | F79: 50 | G79: =+SUM(G80:G115) -> 42 | H79: =+SUM(H80:H115) -> 29 | I79: =+SUM(I80:I115) -> 46 | J79: =+SUM(J80:J115) -> 33 | K79: =+SUM(K80:K115) -> 32 | L79: =+SUM(L80:L115) -> 34 | M79: =+SUM(M80:M115) -> 32 | N79: =+SUM(N80:N115) -> 26 | ... AA79: =+SUM(AA80:AA115) -> 72 | AB79: =+AB80+AB84+AB94+AB97+AB100+AB101+AB108+AB109+AB115 -> 57 | AC79: =+AC80+AC84+AC94+AC97+AC100+AC101+AC108+AC109+AC115 -> 49 | AD79: =+AD80+AD84+AD94+AD97+AD100+AD101+AD108+AD109+AD115 -> 80 | AE79: =+AE80+AE84+AE94+AE97+AE100+AE101+AE108+AE109+AE115 -> 72 | AF79: =+AF80+AF84+AF94+AF97+AF100+AF101+AF108+AF109+AF115 -> 77 | AG79: =+AG80+AG84+AG94+AG97+AG100+AG101+AG108+AG109+AG115 -> 55 | AH79: =+AH80+AH84+AH94+AH97+AH100+AH101+AH108+AH109+AH115 -> 55 | AI79: =+AI80+AI84+AI94+AI97+AI100+AI101+AI108+AI109+AI115 -> 56 | ... AO79: =+AO80+AO84+AO94+AO97+AO100+AO101+AO108+AO109+AO115 -> 36 | BA79: =IFERROR(AVERAGE(D79:O79),"-") -> 36 | BB79: =IFERROR(AVERAGE(P79:AA79),"-") -> 51 | BC79: =IFERROR(SUMIFS(AB79:AM79,AB79:AM79,"<>0",AB79:AM79,"<>-",AB79:AM79,"<>",AB79:AM79,"<> ")/COUNTIFS(AB79:AM79,"<>0",AB79:AM79,"<>-",AB79:AM79,"<>",AB79:AM79,"<> "),"-") -> 59.833333
B80: FALTA UNIDAD | C80: UNI | G80: 10 | H80: 14 | I80: 16 | J80: 13 | K80: 9 | L80: 14 | M80: 17 | N80: 9 | O80: 13 | P80: 13 | Q80: 7 | R80: 28 | S80: 36 | T80: 15 | U80: 17 | V80: 15 | W80: 18 | X80: 18 | Y80: 20 | Z80: 29 | AA80: 32 | AB80: 24 | AC80: 18 | AD80: 36 | AE80: 35 | AF80: 31 | AG80: 25 | AH80: 22 | AI80: 23 | AJ80: 16 | AK80: 21 | AL80: 23 | AM80: 21 | AN80: =+SUM(AN81:AN83) -> 33 | AO80: =+SUM(AO81:AO83) -> 12 | BA80: =IFERROR(AVERAGE(D80:O80),"-") -> 12.777778 | BB80: =IFERROR(AVERAGE(P80:AA80),"-") -> 20.666667 | BC80: =IFERROR(SUMIFS(AB80:AM80,AB80:AM80,"<>0",AB80:AM80,"<>-",AB80:AM80,"<>",AB80:AM80,"<> ")/COUNTIFS(AB80:AM80,"<>0",AB80:AM80,"<>-",AB80:AM80,"<>",AB80:AM80,"<> "),"-") -> 24.583333
B81: FALTA UNIDAD-FALTA UN FLOWPACK EN ESTUCHE | C81: UNI | AB81: 1 | AC81: 1 | AE81: 3 | AF81: 10 | AG81: 2 | AH81: 5 | AI81: 1 | AK81: 2 | AL81: 2 | AM81: 1 | AN81: 6 | AO81: 0
B82: FALTA UNIDAD-FALTA UN PEDAZO DE HAMBURGUESA | C82: UNI | AB82: 3 | AC82: 5 | AD82: 10 | AE82: 7 | AF82: 5 | AG82: 11 | AH82: 5 | AI82: 6 | AJ82: 1 | AK82: 4 | AL82: 8 | AM82: 6 | AN82: 7 | AO82: 2
B83: FALTA UNIDAD-FALTA UNIDAD BOLSITA/FLOWPACK | C83: UNI | AB83: 20 | AC83: 12 | AD83: 26 | AE83: 25 | AF83: 16 | AG83: 12 | AH83: 12 | AI83: 16 | AJ83: 15 | AK83: 15 | AL83: 13 | AM83: 14 | AN83: 20 | AO83: 10
B84: CUERPO EXTRAÑO | C84: UNI | G84: 10 | H84: 2 | I84: 14 | J84: 9 | K84: 10 | L84: 6 | M84: 9 | N84: 5 | O84: 5 | P84: 11 | Q84: 8 | R84: 13 | S84: 12 | T84: 8 | U84: 13 | V84: 19 | W84: 11 | X84: 12 | Y84: 9 | Z84: 14 | AA84: 9 | AB84: 6 | AC84: 8 | AD84: 15 | AE84: 9 | AF84: 17 | AG84: 11 | AH84: 16 | AI84: 13 | AJ84: 25 | AK84: 16 | AL84: 7 | AM84: 10 | AN84: =+SUM(AN85:AN93) -> 7 | AO84: =+SUM(AO85:AO93) -> 5 | BA84: =IFERROR(AVERAGE(D84:O84),"-") -> 7.7777778 | BB84: =IFERROR(AVERAGE(P84:AA84),"-") -> 11.583333 | BC84: =IFERROR(SUMIFS(AB84:AM84,AB84:AM84,"<>0",AB84:AM84,"<>-",AB84:AM84,"<>",AB84:AM84,"<> ")/COUNTIFS(AB84:AM84,"<>0",AB84:AM84,"<>-",AB84:AM84,"<>",AB84:AM84,"<> "),"-") -> 12.75
B85: CUERPO EXTRAÑO-CARTILAGO | C85: UNI | AB85: 1 | AF85: 1 | AI85: 1 | AJ85: 1 | AK85: 1 | AL85: 0 | AM85: 0 | AN85: 0 | AO85: 0
B86: CUERPO EXTRAÑO-INSECTO | C86: UNI | AB86: 1 | AF86: 1 | AK86: 0 | AL86: 1 | AM86: 0 | AN86: 0 | AO86: 2
B87: CUERPO EXTRAÑO-HUESO | C87: UNI | AB87: 2 | AC87: 1 | AD87: 4 | AE87: 2 | AF87: 5 | AG87: 2 | AH87: 4 | AI87: 2 | AJ87: 2 | AK87: 3 | AL87: 0 | AM87: 1 | AN87: 3 | AO87: 1
B88: CUERPO EXTRAÑO-METAL | C88: UNI | AF88: 1 | AH88: 1 | AI88: 3 | AK88: 0 | AL88: 0 | AM88: 1 | AN88: 0 | AO88: 0
B89: CUERPO EXTRAÑO-OTRO | C89: UNI | AC89: 1 | AD89: 2 | AE89: 2 | AF89: 2 | AG89: 1 | AH89: 5 | AI89: 2 | AJ89: 5 | AK89: 2 | AL89: 0 | AM89: 5 | AN89: 1 | AO89: 1
B90: CUERPO EXTRAÑO-PELO | C90: UNI | AC90: 2 | AD90: 6 | AF90: 1 | AG90: 2 | AH90: 2 | AI90: 3 | AJ90: 3 | AK90: 1 | AL90: 2 | AM90: 0 | AN90: 1 | AO90: 0
B91: CUERPO EXTRAÑO-PLASTICO | C91: UNI | AB91: 1 | AC91: 4 | AD91: 1 | AE91: 3 | AF91: 6 | AG91: 3 | AH91: 3 | AI91: 2 | AJ91: 8 | AK91: 8 | AL91: 3 | AM91: 2 | AN91: 0 | AO91: 0
B92: CUERPO EXTRAÑO-TRIPA | C92: UNI | AB92: 1 | AD92: 2 | AE92: 1 | AG92: 3 | AH92: 1 | AJ92: 6 | AK92: 1 | AL92: 1 | AM92: 1 | AN92: 1 | AO92: 1
B93: CUERPO EXTRAÑO-VIDRIO | C93: UNI | AE93: 1 | AK93: 0 | AL93: 0 | AN93: 1 | AO93: 0
B94: MAL SELLADO | C94: UNI | G94: 1 | H94: - | I94: - | J94: - | K94: 1 | L94: 1 | M94: - | N94: 2 | O94: - | P94: 1 | Q94: - | R94: - | S94: - | T94: 1 | U94: 1 | V94: - | W94: - | X94: - | Y94: 4 | Z94: 2 | AA94: 1 | AB94: 1 | AC94: 1 | AD94: 0 | AE94: 0 | AF94: 1 | AG94: 1 | AH94: 1 | AI94: 1 | AJ94: 2 | AK94: 0 | AL94: 0 | AM94: 0 | AN94: =+SUM(AN95:AN96) -> 0 | AO94: =+SUM(AO95:AO96) -> 1 | BA94: =IFERROR(AVERAGE(D94:O94),"-") -> 1.25 | BB94: =IFERROR(AVERAGE(P94:AA94),"-") -> 1.6666667 | BC94: =IFERROR(SUMIFS(AB94:AM94,AB94:AM94,"<>0",AB94:AM94,"<>-",AB94:AM94,"<>",AB94:AM94,"<> ")/COUNTIFS(AB94:AM94,"<>0",AB94:AM94,"<>-",AB94:AM94,"<>",AB94:AM94,"<> "),"-") -> 1.1428571
B95: MAL SELLADO-CAJA/ESTUCHE | C95: UNI | AB95: 1 | AH95: 1 | AK95: 0 | AL95: 0 | AM95: 0 | AN95: 0 | AO95: 0
B96: MAL SELLADO-FLOWPACK | C96: UNI | AC96: 1 | AF96: 1 | AG96: 1 | AI96: 1 | AJ96: 2 | AK96: 0 | AL96: 0 | AM96: 0 | AN96: 0 | AO96: 1
B97: CAMBIO CALIDAD/SABOR | C97: UNI | G97: 2 | H97: - | I97: 1 | J97: 2 | K97: - | L97: - | M97: - | N97: 1 | O97: - | P97: 2 | Q97: 1 | R97: 1 | S97: 2 | T97: 1 | U97: 1 | V97: - | W97: 1 | X97: - | Y97: - | Z97: - | AA97: - | AB97: 0 | AC97: 2 | AD97: 3 | AE97: 4 | AF97: 5 | AG97: 0 | AH97: 2 | AI97: 2 | AJ97: 2 | AK97: 1 | AL97: 2 | AM97: 4 | AN97: =+SUM(AN98:AN99) -> 1 | AO97: =+SUM(AO98:AO99) -> 1 | BA97: =IFERROR(AVERAGE(D97:O97),"-") -> 1.5 | BB97: =IFERROR(AVERAGE(P97:AA97),"-") -> 1.2857143 | BC97: =IFERROR(SUMIFS(AB97:AM97,AB97:AM97,"<>0",AB97:AM97,"<>-",AB97:AM97,"<>",AB97:AM97,"<> ")/COUNTIFS(AB97:AM97,"<>0",AB97:AM97,"<>-",AB97:AM97,"<>",AB97:AM97,"<> "),"-") -> 2.7
B98: CAMBIO-CALIDAD | C98: UNI | AC98: 2 | AD98: 2 | AE98: 4 | AF98: 5 | AH98: 2 | AI98: 2 | AJ98: 2 | AK98: 1 | AL98: 2 | AM98: 3 | AN98: 1 | AO98: 1
B99: CAMBIO-SABOR | C99: UNI | AD99: 1 | AK99: 0 | AL99: 0 | AM99: 1 | AN99: 0 | AO99: 0
B100: CONTENIDO | C100: UNI | G100: - | H100: - | I100: - | J100: - | K100: - | L100: - | M100: 1 | N100: 1 | O100: - | P100: 2 | Q100: - | R100: - | S100: - | T100: - | U100: - | V100: 1 | W100: - | X100: - | Y100: - | Z100: 2 | AA100: - | AB100: 1 | AC100: 0 | AD100: 0 | AE100: 0 | AF100: 1 | AG100: 0 | AH100: 1 | AI100: 2 | AJ100: 0 | AK100: 1 | AL100: 0 | AM100: 0 | AN100: 0 | AO100: 0 | BA100: =IFERROR(AVERAGE(D100:O100),"-") -> 1 | BB100: =IFERROR(AVERAGE(P100:AA100),"-") -> 1.6666667 | BC100: =IFERROR(SUMIFS(AB100:AM100,AB100:AM100,"<>0",AB100:AM100,"<>-",AB100:AM100,"<>",AB100:AM100,"<> ")/COUNTIFS(AB100:AM100,"<>0",AB100:AM100,"<>-",AB100:AM100,"<>",AB100:AM100,"<> "),"-") -> 1.2
B101: MAL ESTADO | C101: UNI | G101: 4 | H101: 9 | I101: 8 | J101: 4 | K101: 7 | L101: 3 | M101: - | N101: 2 | O101: - | P101: 6 | Q101: 1 | R101: 5 | S101: 4 | T101: 11 | U101: 6 | V101: 1 | W101: 1 | X101: 4 | Y101: 4 | Z101: 5 | AA101: 7 | AB101: 5 | AC101: 8 | AD101: 14 | AE101: 13 | AF101: 9 | AG101: 9 | AH101: 3 | AI101: 8 | AJ101: 10 | AK101: 10 | AL101: 13 | AM101: 7 | AN101: =+SUM(AN102:AN107) -> 19 | AO101: =+SUM(AO102:AO107) -> 9 | BA101: =IFERROR(AVERAGE(D101:O101),"-") -> 5.2857143 | BB101: =IFERROR(AVERAGE(P101:AA101),"-") -> 4.5833333 | BC101: =IFERROR(SUMIFS(AB101:AM101,AB101:AM101,"<>0",AB101:AM101,"<>-",AB101:AM101,"<>",AB101:AM101,"<> ")/COUNTIFS(AB101:AM101,"<>0",AB101:AM101,"<>-",AB101:AM101,"<>",AB101:AM101,"<> "),"-") -> 9.0833333
B102: MAL ESTADO-MANCHAS EN HAMBURGUESA | C102: UNI | AD102: 2 | AE102: 2 | AF102: 1 | AI102: 2 | AK102: 0 | AL102: 1 | AM102: 1 | AN102: 1 | AO102: 1
B103: MAL ESTADO-MAS CLARA | C103: UNI | AE103: 1 | AI103: 1 | AJ103: 2 | AK103: 1 | AL103: 0 | AM103: 0 | AN103: 0 | AO103: 0
...

Sheet TABLERO DIARIO
B2: TABLERO OPERACIONES | F2: 45688 | I2: 45689 | L2: 45690 | O2: 45691 | R2: 45692 | U2: 45693 | X2: 45694 | AA2: 45695 | AD2: 45696 | AG2: 45697 | AJ2: 45698 | AM2: 45699 | AP2: 45700 | AS2: 45701 | AV2: 45702 | AY2: 45703 | BB2: 45704 | BE2: 45705 | BH2: 45706 | BK2: 45707 | BN2: 45708 | BQ2: 45709 | BT2: 45710 | BW2: 45711 | BZ2: 45712 | CC2: 45713 | CF2: 45714 | CI2: 45715 | CL2: 45716 | CO2: 45717 | CR2: 45718 | CU2: 45719 | CX2: 45720 | DA2: 45721 | DD2: 45722 | DG2: 45723 | DJ2: 45724 | DM2: 45725 | DP2: 45726 | DS2: 45727 | DV2: 45728 | DY2: 45729 | EB2: 45730 | EE2: 45731 | EH2: 45732 | EK2: 45733 | EN2: 45734 | EQ2: 45735 | ET2: 45736 | EW2: 45737 | EZ2: 45738 | FC2: 45739 | FF2: 45740 | FI2: 45741 | FL2: 45742 | FO2: 45743 | FR2: 45744 | FU2: 45745 | FX2: 45746 | GA2: 45747 | GD2: 45748 | GG2: 45749 | GJ2: 45750 | GM2: 45751 | GP2: 45752 | GS2: 45753 | GV2: 45754 | GY2: 45755 | HB2: 45756 | HE2: 45757 | HH2: 45758 | HK2: 45759 | HN2: 45760 | HQ2: 45761 | HT2: 45762 | HW2: 45763 | HZ2: 45764 | IC2: 45765 | IF2: 45766 | II2: 45767 | IL2: 45768 | IO2: 45769 | IR2: 45770 | IU2: 45771 | IX2: 45772 | JA2: 45773 | JD2: 45774 | JG2: 45775 | JJ2: 45776 | JM2: 45777 | JP2: 45778 | JS2: 45779 | JV2: =+JS2+1 -> 45780 | JY2: =+JV2+1 -> 45781 | KB2: =+JY2+1 -> 45782 | KE2: =+KB2+1 -> 45783 | KH2: =+KE2+1 -> 45784 | KK2: =+KH2+1 -> 45785 | KN2: =+KK2+1 -> 45786 | KQ2: =+KN2+1 -> 45787 | KT2: =+KQ2+1 -> 45788 | KW2: =+KT2+1 -> 45789 | KZ2: =+KW2+1 -> 45790 | LC2: =+KZ2+1 -> 45791 | LF2: =+LC2+1 -> 45792 | LI2: =+LF2+1 -> 45793 | LL2: =+LI2+1 -> 45794 | LO2: =+LL2+1 -> 45795 | LR2: =+LO2+1 -> 45796 | LU2: =+LR2+1 -> 45797 | LX2: =+LU2+1 -> 45798 | MA2: =+LX2+1 -> 45799 | MD2: =+MA2+1 -> 45800 | MG2: =+MD2+1 -> 45801 | MJ2: =+MG2+1 -> 45802 | MM2: =+MJ2+1 -> 45803 | MP2: =+MM2+1 -> 45804 | MS2: =+MP2+1 -> 45805 | MV2: =+MS2+1 -> 45806 | MY2: =+MV2+1 -> 45807 | NB2: =+MY2+1 -> 45808 | NE2: =+NB2+1 -> 45809 | NH2: =+NE2+1 -> 45810 | NK2: =+NH2+1 -> 45811 | NN2: =+NK2+1 -> 45812 | NQ2: =+NN2+1 -> 45813 | NT2: =+NQ2+1 -> 45814 | NW2: =+NT2+1 -> 45815 | NZ2: =+NW2+1 -> 45816 | OC2: =+NZ2+1 -> 45817 | OF2: =+OC2+1 -> 45818 | OI2: =+OF2+1 -> 45819 | OL2: =+OI2+1 -> 45820 | OO2: =+OL2+1 -> 45821 | OR2: =+OO2+1 -> 45822 | OU2: =+OR2+1 -> 45823 | OX2: =+OU2+1 -> 45824 | PA2: =+OX2+1 -> 45825 | PD2: =+PA2+1 -> 45826 | PG2: =+PD2+1 -> 45827 | PJ2: =+PG2+1 -> 45828 | PM2: =+PJ2+1 -> 45829 | PP2: =+PM2+1 -> 45830 | PS2: =+PP2+1 -> 45831 | PV2: =+PS2+1 -> 45832 | PY2: =+PV2+1 -> 45833 | QB2: =+PY2+1 -> 45834 | QE2: =+QB2+1 -> 45835 | QH2: =+QE2+1 -> 45836 | QK2: =+QH2+1 -> 45837 | QN2: =+QK2+1 -> 45838 | QQ2: =+QN2+1 -> 45839 | QT2: =+QQ2+1 -> 45840 | QW2: =+QT2+1 -> 45841 | QZ2: =+QW2+1 -> 45842 | RC2: =+QZ2+1 -> 45843 | RF2: =+RC2+1 -> 45844 | RI2: =+RF2+1 -> 45845 | RL2: =+RI2+1 -> 45846 | RO2: =+RL2+1 -> 45847 | RR2: =+RO2+1 -> 45848 | RU2: =+RR2+1 -> 45849 | RX2: =+RU2+1 -> 45850 | SA2: =+RX2+1 -> 45851 | SD2: =+SA2+1 -> 45852 | SG2: =+SD2+1 -> 45853 | SJ2: =+SG2+1 -> 45854 | SM2: =+SJ2+1 -> 45855 | SP2: =+SM2+1 -> 45856 | SS2: =+SP2+1 -> 45857 | SV2: =+SS2+1 -> 45858 | SY2: =+SV2+1 -> 45859 | TB2: =+SY2+1 -> 45860 | TE2: =+TB2+1 -> 45861 | TH2: =+TE2+1 -> 45862 | TK2: =+TH2+1 -> 45863 | TN2: =+TK2+1 -> 45864 | TQ2: =+TN2+1 -> 45865 | TT2: =+TQ2+1 -> 45866 | TW2: =+TT2+1 -> 45867 | TZ2: =+TW2+1 -> 45868 | UC2: =+TZ2+1 -> 45869 | UF2: =+UC2+1 -> 45870 | UI2: =+UF2+1 -> 45871 | UL2: =+UI2+1 -> 45872 | UO2: =+UL2+1 -> 45873 | UR2: =+UO2+1 -> 45874 | UU2: =+UR2+1 -> 45875 | UX2: =+UU2+1 -> 45876 | VA2: =+UX2+1 -> 45877 | VD2: =+VA2+1 -> 45878 | VG2: =+VD2+1 -> 45879 | VJ2: =+VG2+1 -> 45880 | VM2: =+VJ2+1 -> 45881 | VP2: =+VM2+1 -> 45882 | VS2: =+VP2+1 -> 45883 | VV2: =+VS2+1 -> 45884 | VY2: =+VV2+1 -> 45885 | WB2: =+VY2+1 -> 45886 | WE2: =+WB2+1 -> 45887 | WH2: =+WE2+1 -> 45888 | WK2: =+WH2+1 -> 45889 | WN2: =+WK2+1 -> 45890 | WQ2: =+WN2+1 -> 45891 | WT2: =+WQ2+1 -> 45892 | WW2: =+WT2+1 -> 45893 | WZ2: =+WW2+1 -> 45894 | XC2: =+WZ2+1 -> 45895 | XF2: =+XC2+1 -> 45896 | XI2: =+XF2+1 -> 45897 | XL2: =+XI2+1 -> 45898 | XO2: =+XL2+1 -> 45899 | XR2: =+XO2+1 -> 45900 | XU2: =+XR2+1 -> 45901 | XX2: =+XU2+1 -> 45902 | YA2: =+XX2+1 -> 45903 | YD2: =+YA2+1 -> 45904 | YG2: =+YD2+1 -> 45905 | YJ2: =+YG2+1 -> 45906 | YM2: =+YJ2+1 -> 45907 | YP2: =+YM2+1 -> 45908 | YS2: =+YP2+1 -> 45909 | YV2: =+YS2+1 -> 45910 | YY2: =+YV2+1 -> 45911 | ZB2: =+YY2+1 -> 45912 | ZE2: =+ZB2+1 -> 45913 | ZH2: =+ZE2+1 -> 45914 | ZK2: =+ZH2+1 -> 45915 | ZN2: =+ZK2+1 -> 45916 | ZQ2: =+ZN2+1 -> 45917 | ZT2: =+ZQ2+1 -> 45918 | ZW2: =+ZT2+1 -> 45919 | ZZ2: =+ZW2+1 -> 45920 | AAC2: =+ZZ2+1 -> 45921 | AAF2: =+AAC2+1 -> 45922 | AAI2: =+AAF2+1 -> 45923 | AAL2: =+AAI2+1 -> 45924 | AAO2: =+AAL2+1 -> 45925 | AAR2: =+AAO2+1 -> 45926 | AAU2: =+AAR2+1 -> 45927 | AAX2: =+AAU2+1 -> 45928 | ABA2: =+AAX2+1 -> 45929 | ABD2: =+ABA2+1 -> 45930 | ABG2: =+ABD2+1 -> 45931 | ABJ2: =+ABG2+1 -> 45932 | ABM2: =+ABJ2+1 -> 45933 | ABP2: =+ABM2+1 -> 45934 | ABS2: =+ABP2+1 -> 45935 | ABV2: =+ABS2+1 -> 45936 | ABY2: =+ABV2+1 -> 45937 | ACB2: =+ABY2+1 -> 45938 | ACE2: =+ACB2+1 -> 45939 | ACH2: =+ACE2+1 -> 45940 | ACK2: =+ACH2+1 -> 45941 | ACN2: =+ACK2+1 -> 45942 | ACQ2: =+ACN2+1 -> 45943 | ACT2: =+ACQ2+1 -> 45944 | ACW2: =+ACT2+1 -> 45945 | ACZ2: =+ACW2+1 -> 45946 | ADC2: =+ACZ2+1 -> 45947 | ADF2: =+ADC2+1 -> 45948 | ADI2: =+ADF2+1 -> 45949 | ADL2: =+ADI2+1 -> 45950 | ADO2: =+ADL2+1 -> 45951 | ADR2: =+ADO2+1 -> 45952 | ADU2: =+ADR2+1 -> 45953 | ADX2: =+ADU2+1 -> 45954 | AEA2: =+ADX2+1 -> 45955 | AED2: =+AEA2+1 -> 45956 | AEG2: =+AED2+1 -> 45957 | AEJ2: =+AEG2+1 -> 45958 | AEM2: =+AEJ2+1 -> 45959 | AEP2: =+AEM2+1 -> 45960 | AES2: =+AEP2+1 -> 45961 | AEV2: =+AES2+1 -> 45962 | AEY2: =+AEV2+1 -> 45963 | AFB2: =+AEY2+1 -> 45964 | AFE2: =+AFB2+1 -> 45965 | AFH2: =+AFE2+1 -> 45966 | AFK2: =+AFH2+1 -> 45967 | AFN2: =+AFK2+1 -> 45968 | AFQ2: =+AFN2+1 -> 45969 | AFT2: =+AFQ2+1 -> 45970 | AFW2: =+AFT2+1 -> 45971 | AFZ2: =+AFW2+1 -> 45972 | AGC2: =+AFZ2+1 -> 45973 | AGF2: =+AGC2+1 -> 45974 | AGI2: =+AGF2+1 -> 45975 | AGL2: =+AGI2+1 -> 45976 | AGO2: =+AGL2+1 -> 45977 | AGR2: =+AGO2+1 -> 45978 | AGU2: =+AGR2+1 -> 45979 | AGX2: =+AGU2+1 -> 45980 | AHA2: =+AGX2+1 -> 45981 | AHD2: =+AHA2+1 -> 45982 | AHG2: =+AHD2+1 -> 45983 | AHJ2: =+AHG2+1 -> 45984 | AHM2: =+AHJ2+1 -> 45985 | AHP2: =+AHM2+1 -> 45986 | AHS2: =+AHP2+1 -> 45987 | AHV2: =+AHS2+1 -> 45988 | AHY2: =+AHV2+1 -> 45989 | AIB2: =+AHY2+1 -> 45990 | AIE2: =+AIB2+1 -> 45991 | AIH2: =+AIE2+1 -> 45992 | AIK2: =+AIH2+1 -> 45993 | AIN2: =+AIK2+1 -> 45994 | AIQ2: =+AIN2+1 -> 45995 | AIT2: =+AIQ2+1 -> 45996 | AIW2: =+AIT2+1 -> 45997 | AIZ2: =+AIW2+1 -> 45998 | AJC2: =+AIZ2+1 -> 45999 | AJF2: =+AJC2+1 -> 46000 | AJI2: =+AJF2+1 -> 46001 | AJL2: =+AJI2+1 -> 46002 | AJO2: =+AJL2+1 -> 46003 | AJR2: =+AJO2+1 -> 46004 | AJU2: =+AJR2+1 -> 46005 | AJX2: =+AJU2+1 -> 46006 | AKA2: =+AJX2+1 -> 46007 | AKD2: =+AKA2+1 -> 46008 | AKG2: =+AKD2+1 -> 46009 | AKJ2: =+AKG2+1 -> 46010 | AKM2: =+AKJ2+1 -> 46011 | AKP2: =+AKM2+1 -> 46012 | AKS2: =+AKP2+1 -> 46013 | AKV2: =+AKS2+1 -> 46014 | AKY2: =+AKV2+1 -> 46015 | ALB2: =+AKY2+1 -> 46016 | ALE2: =+ALB2+1 -> 46017 | ALH2: =+ALE2+1 -> 46018 | ALK2: =+ALH2+1 -> 46019 | ALN2: =+ALK2+1 -> 46020 | ALQ2: =+ALN2+1 -> 46021 | ALT2: =+ALQ2+1 -> 46022 | ALW2: =+ALT2+1 -> 46023 | ALZ2: =+ALW2+1 -> 46024 | AMC2: =+ALZ2+1 -> 46025 | AMF2: =+AMC2+1 -> 46026 | AMI2: =+AMF2+1 -> 46027 | AML2: =+AMI2+1 -> 46028 | AMO2: =+AML2+1 -> 46029 | AMR2: =+AMO2+1 -> 46030 | AMU2: =+AMR2+1 -> 46031 | AMX2: =+AMU2+1 -> 46032 | ANA2: =+AMX2+1 -> 46033 | AND2: =+ANA2+1 -> 46034 | ANG2: =+AND2+1 -> 46035 | ANJ2: =+ANG2+1 -> 46036 | ANM2: =+ANJ2+1 -> 46037 | ANP2: =+ANM2+1 -> 46038 | ANS2: =+ANP2+1 -> 46039 | ANV2: =+ANS2+1 -> 46040 | ANY2: =+ANV2+1 -> 46041 | AOB2: =+ANY2+1 -> 46042 | AOE2: =+AOB2+1 -> 46043 | AOH2: =+AOE2+1 -> 46044 | AOK2: =+AOH2+1 -> 46045 | AON2: =+AOK2+1 -> 46046 | AOQ2: =+AON2+1 -> 46047 | AOT2: =+AOQ2+1 -> 46048 | AOW2: =+AOT2+1 -> 46049 | AOZ2: =+AOW2+1 -> 46050 | APC2: =+AOZ2+1 -> 46051 | APF2: =+APC2+1 -> 46052 | API2: =+APF2+1 -> 46053 | APL2: =+API2+1 -> 46054 | APO2: =+APL2+1 -> 46055 | APR2: =+APO2+1 -> 46056 | APU2: =+APR2+1 -> 46057 | APX2: =+APU2+1 -> 46058 | AQA2: =+APX2+1 -> 46059 | AQD2: =+AQA2+1 -> 46060 | AQG2: =+AQD2+1 -> 46061 | AQJ2: =+AQG2+1 -> 46062 | AQM2: =+AQJ2+1 -> 46063 | AQP2: =+AQM2+1 -> 46064 | AQS2: =+AQP2+1 -> 46065 | AQV2: =+AQS2+1 -> 46066 | AQY2: =+AQV2+1 -> 46067 | ARB2: =+AQY2+1 -> 46068 | ARE2: =+ARB2+1 -> 46069 | ARH2: =+ARE2+1 -> 46070 | ARK2: =+ARH2+1 -> 46071 | ARN2: =+ARK2+1 -> 46072 | ARQ2: =+ARN2+1 -> 46073 | ART2: =+ARQ2+1 -> 46074 | ARW2: =+ART2+1 -> 46075 | ARZ2: =+ARW2+1 -> 46076 | ASC2: =+ARZ2+1 -> 46077 | ASF2: =+ASC2+1 -> 46078 | ASI2: =+ASF2+1 -> 46079 | ASL2: =+ASI2+1 -> 46080 | ASO2: =+ASL2+1 -> 46081 | ASR2: =+ASO2+1 -> 46082 | ASU2: =+ASR2+1 -> 46083 | ASX2: =+ASU2+1 -> 46084 | ATA2: =+ASX2+1 -> 46085 | ATD2: =+ATA2+1 -> 46086 | ATG2: =+ATD2+1 -> 46087 | ATJ2: =+ATG2+1 -> 46088 | ATM2: =+ATJ2+1 -> 46089 | ATP2: =+ATM2+1 -> 46090 | ATS2: =+ATP2+1 -> 46091 | ATV2: =+ATS2+1 -> 46092 | ATY2: =+ATV2+1 -> 46093 | AUB2: =+ATY2+1 -> 46094 | AUE2: =+AUB2+1 -> 46095 | AUH2: =+AUE2+1 -> 46096 | AUK2: =+AUH2+1 -> 46097 | AUN2: =+AUK2+1 -> 46098 | AUQ2: =+AUN2+1 -> 46099 | AUT2: =+AUQ2+1 -> 46100 | AUW2: =+AUT2+1 -> 46101 | AUZ2: =+AUW2+1 -> 46102 | AVC2: =+AUZ2+1 -> 46103 | AVF2: =+AVC2+1 -> 46104 | AVI2: =+AVF2+1 -> 46105 | AVL2: =+AVI2+1 -> 46106 | AVO2: =+AVL2+1 -> 46107 | AVR2: =+AVO2+1 -> 46108 | AVU2: =+AVR2+1 -> 46109 | AVX2: =+AVU2+1 -> 46110 | AWA2: =+AVX2+1 -> 46111 | AWD2: =+AWA2+1 -> 46112 | AWG2: =+AWD2+1 -> 46113 | AWJ2: =+AWG2+1 -> 46114 | AWM2: =+AWJ2+1 -> 46115 | AWP2: =+AWM2+1 -> 46116 | AWS2: =+AWP2+1 -> 46117 | AWV2: =+AWS2+1 -> 46118 | AWY2: =+AWV2+1 -> 46119 | AXB2: =+AWY2+1 -> 46120 | AXE2: =+AXB2+1 -> 46121 | AXH2: =+AXE2+1 -> 46122 | AXK2: =+AXH2+1 -> 46123 | AXN2: =+AXK2+1 -> 46124 | AXQ2: =+AXN2+1 -> 46125 | AXT2: =+AXQ2+1 -> 46126 | AXW2: =+AXT2+1 -> 46127 | AXZ2: =+AXW2+1 -> 46128 | AYC2: =+AXZ2+1 -> 46129 | AYF2: =+AYC2+1 -> 46130 | AYI2: =+AYF2+1 -> 46131 | AYL2: =+AYI2+1 -> 46132 | AYO2: =+AYL2+1 -> 46133 | AYR2: =+AYO2+1 -> 46134 | AYU2: =+AYR2+1 -> 46135 | AYX2: =+AYU2+1 -> 46136 | AZA2: =+AYX2+1 -> 46137 | AZD2: =+AZA2+1 -> 46138 | AZG2: =+AZD2+1 -> 46139 | AZJ2: =+AZG2+1 -> 46140 | AZM2: =+AZJ2+1 -> 46141 | AZP2: =+AZM2+1 -> 46142 | AZS2: =+AZP2+1 -> 46143 | AZV2: =+AZS2+1 -> 46144 | AZY2: =+AZV2+1 -> 46145 | BAB2: =+AZY2+1 -> 46146 | BAE2: =+BAB2+1 -> 46147 | BAH2: =+BAE2+1 -> 46148
F3: VIE | I3: SAB | L3: DOM | O3: LUN | R3: MAR | U3: MIE | X3: JUE | AA3: VIE | AD3: SAB | AG3: DOM | AJ3: LUN | AM3: MAR | AP3: MIE | AS3: JUE | AV3: VIE | AY3: SAB | BB3: DOM | BE3: LUN | BH3: MAR | BK3: MIE | BN3: JUE | BQ3: VIE | BT3: SAB | BW3: DOM | BZ3: LUN | CC3: MAR | CF3: MIE | CI3: JUE | CL3: VIE | CO3: SAB | CR3: DOM | CU3: LUN | CX3: MAR | DA3: MIE | DD3: JUE | DG3: VIE | DJ3: SAB | DM3: DOM | DP3: LUN | DS3: MAR | DV3: MIE | DY3: JUE | EB3: VIE | EE3: SAB | EH3: DOM | EK3: LUN | EN3: MAR | EQ3: MIE | ET3: JUE | EW3: VIE | EZ3: SAB | FC3: DOM | FF3: LUN | FI3: MAR | FL3: MIE | FO3: JUE | FR3: VIE | FU3: SAB | FX3: DOM | GA3: LUN | GD3: MAR | GG3: MIE | GJ3: JUE | GM3: VIE | GP3: SAB | GS3: DOM | GV3: LUN | GY3: MAR | HB3: MIE | HE3: JUE | HH3: VIE | HK3: SAB | HN3: DOM | HQ3: LUN | HT3: MAR | HW3: MIE | HZ3: JUE | IC3: VIE | IF3: SAB | II3: DOM | IL3: LUN | IO3: MAR | IR3: MIE | IU3: JUE | IX3: VIE | JA3: SAB | JD3: DOM | JG3: LUN | JJ3: MAR | JM3: MIE | JP3: JUE | JS3: VIE | JV3: SAB | JY3: DOM | KB3: LUN | KE3: MAR | KH3: MIE | KK3: JUE | KN3: VIE | KQ3: SAB | KT3: DOM | KW3: LUN | KZ3: MAR | LC3: MIE | LF3: JUE | LI3: VIE | LL3: SAB | LO3: DOM | LR3: LUN | LU3: MAR | LX3: MIE | MA3: JUE | MD3: VIE | MG3: SAB | MJ3: DOM | MM3: LUN | MP3: MAR | MS3: MIE | MV3: JUE | MY3: VIE | NB3: SAB | NE3: DOM | NH3: LUN | NK3: MAR | NN3: MIE | NQ3: JUE | NT3: VIE | NW3: SAB | NZ3: DOM | OC3: LUN | OF3: MAR | OI3: MIE | OL3: JUE | OO3: VIE | OR3: SAB | OU3: DOM | OX3: LUN | PA3: MAR | PD3: MIE | PG3: JUE | PJ3: VIE | PM3: SAB | PP3: DOM | PS3: LUN | PV3: MAR | PY3: MIE | QB3: JUE | QE3: VIE | QH3: SAB | QK3: DOM | QN3: LUN | QQ3: MAR | QT3: MIE | QW3: JUE | QZ3: VIE | RC3: SAB | RF3: DOM | RI3: LUN | RL3: MAR | RO3: MIE | RR3: JUE | RU3: VIE | RX3: SAB | SA3: DOM | SD3: LUN | SG3: MAR | SJ3: MIE | SM3: JUE | SP3: VIE | SS3: SAB | SV3: DOM | SY3: LUN | TB3: MAR | TE3: MIE | TH3: JUE | TK3: VIE | TN3: SAB | TQ3: DOM | TT3: LUN | TW3: MAR | TZ3: MIE | UC3: JUE | UF3: VIE | UI3: SAB | UL3: DOM | UO3: LUN | UR3: MAR | UU3: MIE | UX3: JUE | VA3: VIE | VD3: SAB | VG3: DOM | VJ3: LUN | VM3: MAR | VP3: MIE | VS3: JUE | VV3: VIE | VY3: SAB | WB3: DOM | WE3: LUN | WH3: MAR | WK3: MIE | WN3: JUE | WQ3: VIE | WT3: SAB | WW3: DOM | WZ3: LUN | XC3: MAR | XF3: MIE | XI3: JUE | XL3: VIE | XO3: SAB | XR3: DOM | XU3: LUN | XX3: MAR | YA3: MIE | YD3: JUE | YG3: VIE | YJ3: SAB | YM3: DOM | YP3: LUN | YS3: MAR | YV3: MIE | YY3: JUE | ZB3: VIE | ZE3: SAB | ZH3: DOM | ZK3: LUN | ZN3: MAR | ZQ3: MIE | ZT3: JUE | ZW3: VIE | ZZ3: SAB | AAC3: DOM | AAF3: LUN | AAI3: MAR | AAL3: MIE | AAO3: JUE | AAR3: VIE | AAU3: SAB | AAX3: DOM | ABA3: LUN | ABD3: MAR | ABG3: MIE | ABJ3: JUE | ABM3: VIE | ABP3: SAB | ABS3: DOM | ABV3: LUN | ABY3: MAR | ACB3: MIE | ACE3: JUE | ACH3: VIE | ACK3: SAB | ACN3: DOM | ACQ3: LUN | ACT3: MAR | ACW3: MIE | ACZ3: JUE | ADC3: VIE | ADF3: SAB | ADI3: DOM | ADL3: LUN | ADO3: MAR | ADR3: MIE | ADU3: JUE | ADX3: VIE | AEA3: SAB | AED3: DOM | AEG3: LUN | AEJ3: MAR | AEM3: MIE | AEP3: JUE | AES3: VIE | AEV3: SAB | AEY3: DOM | AFB3: LUN | AFE3: MAR | AFH3: MIE | AFK3: JUE | AFN3: VIE | AFQ3: SAB | AFT3: DOM | AFW3: LUN | AFZ3: MAR | AGC3: MIE | AGF3: JUE | AGI3: VIE | AGL3: SAB | AGO3: DOM | AGR3: LUN | AGU3: MAR | AGX3: MIE | AHA3: JUE | AHD3: VIE | AHG3: SAB | AHJ3: DOM | AHM3: LUN | AHP3: MAR | AHS3: MIE | AHV3: JUE | AHY3: VIE | AIB3: SAB | AIE3: DOM | AIH3: LUN | AIK3: MAR | AIN3: MIE | AIQ3: JUE | AIT3: VIE | AIW3: SAB | AIZ3: DOM | AJC3: LUN | AJF3: MAR | AJI3: MIE | AJL3: JUE | AJO3: VIE | AJR3: SAB | AJU3: DOM | AJX3: LUN | AKA3: MAR | AKD3: MIE | AKG3: JUE | AKJ3: VIE | AKM3: SAB | AKP3: DOM | AKS3: LUN | AKV3: MAR | AKY3: MIE | ALB3: JUE | ALE3: VIE | ALH3: SAB | ALK3: DOM | ALN3: LUN | ALQ3: MAR | ALT3: MIE | ALW3: JUE | ALZ3: VIE | AMC3: SAB | AMF3: DOM | AMI3: LUN | AML3: MAR | AMO3: MIE | AMR3: JUE | AMU3: VIE | AMX3: SAB | ANA3: DOM | AND3: LUN | ANG3: MAR | ANJ3: MIE | ANM3: JUE | ANP3: VIE | ANS3: SAB | ANV3: DOM | ANY3: LUN | AOB3: MAR | AOE3: MIE | AOH3: JUE | AOK3: VIE | AON3: SAB | AOQ3: DOM | AOT3: LUN | AOW3: MAR | AOZ3: MIE | APC3: JUE | APF3: VIE | API3: SAB | APL3: DOM | APO3: LUN | APR3: MAR | APU3: MIE | APX3: JUE | AQA3: VIE | AQD3: SAB | AQG3: DOM | AQJ3: LUN | AQM3: MAR | AQP3: MIE | AQS3: JUE | AQV3: VIE | AQY3: SAB | ARB3: DOM | ARE3: LUN | ARH3: MAR | ARK3: MIE | ARN3: JUE | ARQ3: VIE | ART3: SAB | ARW3: DOM | ARZ3: LUN | ASC3: MAR | ASF3: MIE | ASI3: JUE | ASL3: VIE | ASO3: SAB | ASR3: DOM | ASU3: LUN | ASX3: MAR | ATA3: MIE | ATD3: JUE | ATG3: VIE | ATJ3: SAB | ATM3: DOM | ATP3: LUN | ATS3: MAR | ATV3: MIE | ATY3: JUE | AUB3: VIE | AUE3: SAB | AUH3: DOM | AUK3: LUN | AUN3: MAR | AUQ3: MIE | AUT3: JUE | AUW3: VIE | AUZ3: SAB | AVC3: DOM | AVF3: LUN | AVI3: MAR | AVL3: MIE | AVO3: JUE | AVR3: VIE | AVU3: SAB | AVX3: DOM | AWA3: LUN | AWD3: MAR | AWG3: MIE | AWJ3: JUE | AWM3: VIE | AWP3: SAB | AWS3: DOM | AWV3: LUN | AWY3: MAR | AXB3: MIE | AXE3: JUE | AXH3: VIE | AXK3: SAB | AXN3: DOM | AXQ3: LUN | AXT3: MAR | AXW3: MIE | AXZ3: JUE | AYC3: VIE | AYF3: SAB | AYI3: DOM | AYL3: LUN | AYO3: MAR | AYR3: MIE | AYU3: JUE | AYX3: VIE | AZA3: SAB | AZD3: DOM | AZG3: LUN | AZJ3: MAR | AZM3: MIE | AZP3: JUE | AZS3: VIE | AZV3: SAB | AZY3: DOM | BAB3: LUN | BAE3: MAR | BAH3: MIE
